Workbook

Sheet LED計算式
AD1: =VLOOKUP(代理店入力用!H5,AB5:AE12,1,FALSE) -> 10 | AE1: =VLOOKUP(代理店入力用!H5,AB5:AE12,4,FALSE) -> 0
F2: 12 | G2: 12 | H2: 12 | I2: 12 | J2: 12 | K2: 12 | L2: 12 | M2: 12 | N2: 12 | O2: 12 | T2: =SUM(T4:T33) -> 0 | U2: =SUM(U4:U33) -> 0 | AB2: 契約月数 | AC2: =VLOOKUP(代理店入力用!H5,AB5:AE12,2,FALSE) -> 0.0109 | AD2: =VLOOKUP(代理店入力用!H5,AB5:AE12,3,FALSE) -> 120 | AE2: =180-AD2 -> 60 | AI2: =SUM(AI4:AI33) -> 0 | AJ2: =SUM(AJ4:AJ33) -> 0 | AK2: =SUM(AK4:AK33) -> 0
B3: 10年間コスト | C3: 毎月 | E3: 0 | F3: 1 | G3: 2 | H3: 3 | I3: 4 | J3: 5 | K3: 6 | L3: 7 | M3: 8 | N3: 9 | O3: 10 | S3: 商品原価 | T3: 商品合計 | U3: 工事費 | V3: 売価 | AI3: 現状 | AJ3: LEDのみ | AK3: 電力も
B4: =②前a!AS41 -> 0 | C4: =ROUNDDOWN(B4/120,1) -> 0 | E4: 0 | F4: =ROUNDDOWN($C$4*F2*F3,0) -> 0 | G4: =ROUNDDOWN($C$4*G2*G3,0) -> 0 | H4: =ROUNDDOWN($C$4*H2*H3,0) -> 0 | I4: =ROUNDDOWN($C$4*I2*I3,0) -> 0 | J4: =ROUNDDOWN($C$4*J2*J3,0) -> 0 | K4: =ROUNDDOWN($C$4*K2*K3,0) -> 0 | L4: =ROUNDDOWN($C$4*L2*L3,0) -> 0 | M4: =ROUNDDOWN($C$4*M2*M3,0) -> 0 | ... O4: =ROUNDDOWN($C$4*O2*O3,0) -> 0 | Q4: 1 | S4: =IFERROR(VLOOKUP(☆入力!$G16,選定!$C$1:$AG$100,8,FALSE),"0") -> 0 | T4: =S4*☆入力!L16 -> 0 | U4: =☆入力!AE16*☆入力!L16 -> 0 | V4: =ROUNDDOWN((T4+U4),0) -> 0 | X4: =IFERROR((代理店入力用!$D$5/☆入力!$AH$14)*☆入力!$AH16,"0") -> 0 | Y4: =X4/54 -> 0 | AB4: リース期間/年 | AC4: 料率 | AD4: リース期間月数 | AH4: A | AI4: =ROUNDDOWN(☆入力!W16*☆入力!X16,0) -> 0 | AJ4: =ROUNDDOWN(☆入力!AB16*☆入力!X16,0) -> 0 | AK4: =ROUNDDOWN(☆入力!AB16*☆入力!AD16,0) -> 0
Q5: 2 | S5: =IFERROR(VLOOKUP(☆入力!$G17,選定!$C$1:$AG$100,8,FALSE),"0") -> 0 | T5: =S5*☆入力!L17 -> 0 | U5: =☆入力!AE17*☆入力!L17 -> 0 | V5: =ROUNDDOWN((T5+U5),0) -> 0 | X5: =IFERROR((代理店入力用!$D$5/☆入力!$AH$14)*☆入力!$AH17,"0") -> 0 | Y5: =X5/54 -> 0 | AB5: 3 | AC5: 0.0306 | AD5: 36 | AE5: 7 | AH5: B | AI5: =ROUNDDOWN(☆入力!W17*☆入力!X17,0) -> 0 | AJ5: =ROUNDDOWN(☆入力!AB17*☆入力!X17,0) -> 0 | AK5: =ROUNDDOWN(☆入力!AB17*☆入力!AD17,0) -> 0
E6: =(☆入力!$AL$14+代理店入力用!$D$5)*(100%-☆入力!$AR$11) -> 0 | F6: =(☆入力!$AL$14+代理店入力用!$D$5)*(100%-☆入力!$AR$11) -> 0 | G6: =(☆入力!$AL$14+代理店入力用!$D$5)*(100%-☆入力!$AR$11) -> 0 | H6: =(☆入力!$AL$14+代理店入力用!$D$5)*(100%-☆入力!$AR$11) -> 0 | I6: =(☆入力!$AL$14+代理店入力用!$D$5)*(100%-☆入力!$AR$11) -> 0 | J6: =(☆入力!$AL$14+代理店入力用!$D$5)*(100%-☆入力!$AR$11) -> 0 | K6: =(☆入力!$AL$14+代理店入力用!$D$5)*(100%-☆入力!$AR$11) -> 0 | L6: =(☆入力!$AL$14+代理店入力用!$D$5)*(100%-☆入力!$AR$11) -> 0 | ... O6: =(☆入力!$AL$14+代理店入力用!$D$5)*(100%-☆入力!$AR$11) -> 0 | Q6: 3 | S6: =IFERROR(VLOOKUP(☆入力!$G18,選定!$C$1:$AG$100,8,FALSE),"0") -> 0 | T6: =S6*☆入力!L18 -> 0 | U6: =☆入力!AE18*☆入力!L18 -> 0 | V6: =ROUNDDOWN((T6+U6),0) -> 0 | X6: =IFERROR((代理店入力用!$D$5/☆入力!$AH$14)*☆入力!$AH18,"0") -> 0 | Y6: =X6/54 -> 0 | AB6: 4 | AC6: 0.0231 | AD6: 48 | AE6: 6 | AH6: C | AI6: =ROUNDDOWN(☆入力!W18*☆入力!X18,0) -> 0 | AJ6: =ROUNDDOWN(☆入力!AB18*☆入力!X18,0) -> 0 | AK6: =ROUNDDOWN(☆入力!AB18*☆入力!AD18,0) -> 0
B7: =③後a!AS41 -> 0 | C7: =ROUNDDOWN(B7/120,1) -> 0 | E7: 0 | F7: =ROUNDDOWN($C$7*F2*F3,0) -> 0 | G7: =ROUNDDOWN($C$7*G2*G3,0) -> 0 | H7: =ROUNDDOWN($C$7*H2*H3,0) -> 0 | I7: =ROUNDDOWN($C$7*I2*I3,0) -> 0 | J7: =ROUNDDOWN($C$7*J2*J3,0) -> 0 | K7: =ROUNDDOWN($C$7*K2*K3,0) -> 0 | L7: =ROUNDDOWN($C$7*L2*L3,0) -> 0 | M7: =ROUNDDOWN($C$7*M2*M3,0) -> 0 | ... O7: =ROUNDDOWN($C$7*O2*O3,0) -> 0 | Q7: 4 | S7: =IFERROR(VLOOKUP(☆入力!$G19,選定!$C$1:$AG$100,8,FALSE),"0") -> 0 | T7: =S7*☆入力!L19 -> 0 | U7: =☆入力!AE19*☆入力!L19 -> 0 | V7: =ROUNDDOWN((T7+U7),0) -> 0 | X7: =IFERROR((代理店入力用!$D$5/☆入力!$AH$14)*☆入力!$AH19,"0") -> 0 | Y7: =X7/54 -> 0 | AB7: 5 | AC7: 0.0187 | AD7: 60 | AE7: 5 | AH7: D | AI7: =ROUNDDOWN(☆入力!W19*☆入力!X19,0) -> 0 | AJ7: =ROUNDDOWN(☆入力!AB19*☆入力!X19,0) -> 0 | AK7: =ROUNDDOWN(☆入力!AB19*☆入力!AD19,0) -> 0
E8: =E6+E7 -> 0 | F8: =F6+F7 -> 0 | G8: =G6+G7 -> 0 | H8: =H6+H7 -> 0 | I8: =I6+I7 -> 0 | J8: =J6+J7 -> 0 | K8: =K6+K7 -> 0 | L8: =L6+L7 -> 0 | ... O8: =O6+O7 -> 0 | Q8: 5 | S8: =IFERROR(VLOOKUP(☆入力!$G20,選定!$C$1:$AG$100,8,FALSE),"0") -> 0 | T8: =S8*☆入力!L20 -> 0 | U8: =☆入力!AE20*☆入力!L20 -> 0 | V8: =ROUNDDOWN((T8+U8),0) -> 0 | X8: =IFERROR((代理店入力用!$D$5/☆入力!$AH$14)*☆入力!$AH20,"0") -> 0 | Y8: =X8/54 -> 0 | AB8: 6 | AC8: 0.0159 | AD8: 72 | AE8: 4 | AH8: E | AI8: =ROUNDDOWN(☆入力!W20*☆入力!X20,0) -> 0 | AJ8: =ROUNDDOWN(☆入力!AB20*☆入力!X20,0) -> 0 | AK8: =ROUNDDOWN(☆入力!AB20*☆入力!AD20,0) -> 0
Q9: 6 | S9: =IFERROR(VLOOKUP(☆入力!$G21,選定!$C$1:$AG$100,8,FALSE),"0") -> 0 | T9: =S9*☆入力!L21 -> 0 | U9: =☆入力!AE21*☆入力!L21 -> 0 | V9: =ROUNDDOWN((T9+U9),0) -> 0 | X9: =IFERROR((代理店入力用!$D$5/☆入力!$AH$14)*☆入力!$AH21,"0") -> 0 | Y9: =X9/54 -> 0 | AB9: 7 | AC9: 0.0141 | AD9: 84 | AE9: 3 | AH9: F | AI9: =ROUNDDOWN(☆入力!W21*☆入力!X21,0) -> 0 | AJ9: =ROUNDDOWN(☆入力!AB21*☆入力!X21,0) -> 0 | AK9: =ROUNDDOWN(☆入力!AB21*☆入力!AD21,0) -> 0
Q10: 7 | S10: =IFERROR(VLOOKUP(☆入力!$G22,選定!$C$1:$AG$100,8,FALSE),"0") -> 0 | T10: =S10*☆入力!L22 -> 0 | U10: =☆入力!AE22*☆入力!L22 -> 0 | V10: =ROUNDDOWN((T10+U10),0) -> 0 | X10: =IFERROR((代理店入力用!$D$5/☆入力!$AH$14)*☆入力!$AH22,"0") -> 0 | Y10: =X10/54 -> 0 | AB10: 8 | AC10: 0.0127 | AD10: 96 | AE10: 2 | AH10: G | AI10: =ROUNDDOWN(☆入力!W22*☆入力!X22,0) -> 0 | AJ10: =ROUNDDOWN(☆入力!AB22*☆入力!X22,0) -> 0 | AK10: =ROUNDDOWN(☆入力!AB22*☆入力!AD22,0) -> 0
E11: =(☆入力!$AL$14+代理店入力用!$D$5)*(100%-☆入力!$AR$11-☆入力!$AR$12) -> 0 | F11: =(☆入力!$AL$14+代理店入力用!$D$5)*(100%-☆入力!$AR$11-☆入力!$AR$12) -> 0 | G11: =(☆入力!$AL$14+代理店入力用!$D$5)*(100%-☆入力!$AR$11-☆入力!$AR$12) -> 0 | H11: =(☆入力!$AL$14+代理店入力用!$D$5)*(100%-☆入力!$AR$11-☆入力!$AR$12) -> 0 | I11: =(☆入力!$AL$14+代理店入力用!$D$5)*(100%-☆入力!$AR$11-☆入力!$AR$12) -> 0 | J11: =(☆入力!$AL$14+代理店入力用!$D$5)*(100%-☆入力!$AR$11-☆入力!$AR$12) -> 0 | K11: =(☆入力!$AL$14+代理店入力用!$D$5)*(100%-☆入力!$AR$11-☆入力!$AR$12) -> 0 | L11: =(☆入力!$AL$14+代理店入力用!$D$5)*(100%-☆入力!$AR$11-☆入力!$AR$12) -> 0 | ... O11: =(☆入力!$AL$14+代理店入力用!$D$5)*(100%-☆入力!$AR$11-☆入力!$AR$12) -> 0 | Q11: 8 | S11: =IFERROR(VLOOKUP(☆入力!$G23,選定!$C$1:$AG$100,8,FALSE),"0") -> 0 | T11: =S11*☆入力!L23 -> 0 | U11: =☆入力!AE23*☆入力!L23 -> 0 | V11: =ROUNDDOWN((T11+U11),0) -> 0 | X11: =IFERROR((代理店入力用!$D$5/☆入力!$AH$14)*☆入力!$AH23,"0") -> 0 | Y11: =X11/54 -> 0 | AB11: 9 | AC11: 0.0117 | AD11: 108 | AE11: 1 | AH11: H | AI11: =ROUNDDOWN(☆入力!W23*☆入力!X23,0) -> 0 | AJ11: =ROUNDDOWN(☆入力!AB23*☆入力!X23,0) -> 0 | AK11: =ROUNDDOWN(☆入力!AB23*☆入力!AD23,0) -> 0
B12: =B7 -> 0 | C12: =ROUNDDOWN(B12/120,1) -> 0 | E12: 0 | F12: =ROUNDDOWN($C$12*F2*F3,0) -> 0 | G12: =ROUNDDOWN($C$12*G2*G3,0) -> 0 | H12: =ROUNDDOWN($C$12*H2*H3,0) -> 0 | I12: =ROUNDDOWN($C$12*I2*I3,0) -> 0 | J12: =ROUNDDOWN($C$12*J2*J3,0) -> 0 | K12: =ROUNDDOWN($C$12*K2*K3,0) -> 0 | L12: =ROUNDDOWN($C$12*L2*L3,0) -> 0 | M12: =ROUNDDOWN($C$12*M2*M3,0) -> 0 | ... O12: =ROUNDDOWN($C$12*O2*O3,0) -> 0 | Q12: 9 | S12: =IFERROR(VLOOKUP(☆入力!$G24,選定!$C$1:$AG$100,8,FALSE),"0") -> 0 | T12: =S12*☆入力!L24 -> 0 | U12: =☆入力!AE24*☆入力!L24 -> 0 | V12: =ROUNDDOWN((T12+U12),0) -> 0 | X12: =IFERROR((代理店入力用!$D$5/☆入力!$AH$14)*☆入力!$AH24,"0") -> 0 | Y12: =X12/54 -> 0 | AB12: 10 | AC12: 0.0109 | AD12: 120 | AE12: 0 | AH12: I | AI12: =ROUNDDOWN(☆入力!W24*☆入力!X24,0) -> 0 | AJ12: =ROUNDDOWN(☆入力!AB24*☆入力!X24,0) -> 0 | AK12: =ROUNDDOWN(☆入力!AB24*☆入力!AD24,0) -> 0
E13: =E11+E12 -> 0 | F13: =F11+F12 -> 0 | G13: =G11+G12 -> 0 | H13: =H11+H12 -> 0 | I13: =I11+I12 -> 0 | J13: =J11+J12 -> 0 | K13: =K11+K12 -> 0 | L13: =L11+L12 -> 0 | ... O13: =O11+O12 -> 0 | Q13: 10 | S13: =IFERROR(VLOOKUP(☆入力!$G25,選定!$C$1:$AG$100,8,FALSE),"0") -> 0 | T13: =S13*☆入力!L25 -> 0 | U13: =☆入力!AE25*☆入力!L25 -> 0 | V13: =ROUNDDOWN((T13+U13),0) -> 0 | X13: =IFERROR((代理店入力用!$D$5/☆入力!$AH$14)*☆入力!$AH25,"0") -> 0 | Y13: =X13/54 -> 0 | AH13: J | AI13: =ROUNDDOWN(☆入力!W25*☆入力!X25,0) -> 0 | AJ13: =ROUNDDOWN(☆入力!AB25*☆入力!X25,0) -> 0 | AK13: =ROUNDDOWN(☆入力!AB25*☆入力!AD25,0) -> 0
Q14: 11 | S14: =IFERROR(VLOOKUP(☆入力!$G26,選定!$C$1:$AG$100,8,FALSE),"0") -> 0 | T14: =S14*☆入力!L26 -> 0 | U14: =☆入力!AE26*☆入力!L26 -> 0 | V14: =ROUNDDOWN((T14+U14),0) -> 0 | X14: =IFERROR((代理店入力用!$D$5/☆入力!$AH$14)*☆入力!$AH26,"0") -> 0 | Y14: =X14/54 -> 0 | AH14: K | AI14: =ROUNDDOWN(☆入力!W26*☆入力!X26,0) -> 0 | AJ14: =ROUNDDOWN(☆入力!AB26*☆入力!X26,0) -> 0 | AK14: =ROUNDDOWN(☆入力!AB26*☆入力!AD26,0) -> 0
Q15: 12 | S15: =IFERROR(VLOOKUP(☆入力!$G27,選定!$C$1:$AG$100,8,FALSE),"0") -> 0 | T15: =S15*☆入力!L27 -> 0 | U15: =☆入力!AE27*☆入力!L27 -> 0 | V15: =ROUNDDOWN((T15+U15),0) -> 0 | X15: =IFERROR((代理店入力用!$D$5/☆入力!$AH$14)*☆入力!$AH27,"0") -> 0 | Y15: =X15/54 -> 0 | AH15: L | AI15: =ROUNDDOWN(☆入力!W27*☆入力!X27,0) -> 0 | AJ15: =ROUNDDOWN(☆入力!AB27*☆入力!X27,0) -> 0 | AK15: =ROUNDDOWN(☆入力!AB27*☆入力!AD27,0) -> 0
C16: 現状 | D16: 5年間 | E16: 6年目以降 | H16: ⑥非なし | I16: ⑥非あり | M16: 360 | N16: =SUMIF(☆入力!H16:H40,360,☆入力!L16:L40) -> 0 | Q16: 13 | S16: =IFERROR(VLOOKUP(☆入力!$G28,選定!$C$1:$AG$100,8,FALSE),"0") -> 0 | T16: =S16*☆入力!L28 -> 0 | U16: =☆入力!AE28*☆入力!L28 -> 0 | V16: =ROUNDDOWN((T16+U16),0) -> 0 | X16: =IFERROR((代理店入力用!$D$5/☆入力!$AH$14)*☆入力!$AH28,"0") -> 0 | Y16: =X16/54 -> 0 | AH16: M | AI16: =ROUNDDOWN(☆入力!W28*☆入力!X28,0) -> 0 | AJ16: =ROUNDDOWN(☆入力!AB28*☆入力!X28,0) -> 0 | AK16: =ROUNDDOWN(☆入力!AB28*☆入力!AD28,0) -> 0
B17: B | M17: 720 | N17: =SUMIF(☆入力!H16:H40,720,☆入力!L16:L40) -> 0 | Q17: 14 | S17: =IFERROR(VLOOKUP(☆入力!$G29,選定!$C$1:$AG$100,8,FALSE),"0") -> 0 | T17: =S17*☆入力!L29 -> 0 | U17: =☆入力!AE29*☆入力!L29 -> 0 | V17: =ROUNDDOWN((T17+U17),0) -> 0 | X17: =IFERROR((代理店入力用!$D$5/☆入力!$AH$14)*☆入力!$AH29,"0") -> 0 | Y17: =X17/54 -> 0 | AH17: N | AI17: =ROUNDDOWN(☆入力!W29*☆入力!X29,0) -> 0 | AJ17: =ROUNDDOWN(☆入力!AB29*☆入力!X29,0) -> 0 | AK17: =ROUNDDOWN(☆入力!AB29*☆入力!AD29,0) -> 0
B18: バイパス | H18: 削減金額 | Q18: 15 | S18: =IFERROR(VLOOKUP(☆入力!$G30,選定!$C$1:$AG$100,8,FALSE),"0") -> 0 | T18: =S18*☆入力!L30 -> 0 | U18: =☆入力!AE30*☆入力!L30 -> 0 | V18: =ROUNDDOWN((T18+U18),0) -> 0 | X18: =IFERROR((代理店入力用!$D$5/☆入力!$AH$14)*☆入力!$AH30,"0") -> 0 | Y18: =X18/54 -> 0 | AH18: O | AI18: =ROUNDDOWN(☆入力!W30*☆入力!X30,0) -> 0 | AJ18: =ROUNDDOWN(☆入力!AB30*☆入力!X30,0) -> 0 | AK18: =ROUNDDOWN(☆入力!AB30*☆入力!AD30,0) -> 0
B19: 削減金額 | H19: リース代 | J19: =⑧見積書!J10 -> 0 | Q19: 16 | S19: =IFERROR(VLOOKUP(☆入力!$G31,選定!$C$1:$AG$100,8,FALSE),"0") -> 0 | T19: =S19*☆入力!L31 -> 0 | U19: =☆入力!AE31*☆入力!L31 -> 0 | V19: =ROUNDDOWN((T19+U19),0) -> 0 | X19: =IFERROR((代理店入力用!$D$5/☆入力!$AH$14)*☆入力!$AH31,"0") -> 0 | Y19: =X19/54 -> 0 | AH19: P | AI19: =ROUNDDOWN(☆入力!W31*☆入力!X31,0) -> 0 | AJ19: =ROUNDDOWN(☆入力!AB31*☆入力!X31,0) -> 0 | AK19: =ROUNDDOWN(☆入力!AB31*☆入力!AD31,0) -> 0
B20: リース代 | D20: =ROUNDDOWN(LED計算式!#REF!,1) -> #REF! | H20: 交換コスト | I20: =ROUNDDOWN((②前a!AS13+②前a!AS24)/120,0) -> 0 | J20: =ROUNDDOWN((③後a!AS13+③後a!AS24)/120,0) -> 0 | K20: =ROUNDDOWN((③後a!AS13+③後a!AS24)/120,0) -> 0 | M20: 電球数 | N20: 人工 | Q20: 17 | S20: =IFERROR(VLOOKUP(☆入力!$G32,選定!$C$1:$AG$100,8,FALSE),"0") -> 0 | T20: =S20*☆入力!L32 -> 0 | U20: =☆入力!AE32*☆入力!L32 -> 0 | V20: =ROUNDDOWN((T20+U20),0) -> 0 | X20: =IFERROR((代理店入力用!$D$5/☆入力!$AH$14)*☆入力!$AH32,"0") -> 0 | Y20: =X20/54 -> 0 | AH20: Q | AI20: =ROUNDDOWN(☆入力!W32*☆入力!X32,0) -> 0 | AJ20: =ROUNDDOWN(☆入力!AB32*☆入力!X32,0) -> 0 | AK20: =ROUNDDOWN(☆入力!AB32*☆入力!AD32,0) -> 0
B21: 電気代 | C21: =ROUNDDOWN(☆入力!Y14,1) -> 0 | D21: =ROUNDDOWN(☆入力!AC14,1) -> 0 | E21: =ROUNDDOWN(☆入力!AC14,1) -> 0 | H21: 電気代 | I21: =ROUNDDOWN(C21,0) -> 0 | J21: =ROUNDDOWN(D21,0) -> 0 | K21: =ROUNDDOWN(E21,0) -> 0 | M21: 0 | N21: 1 | Q21: 18 | S21: =IFERROR(VLOOKUP(☆入力!$G33,選定!$C$1:$AG$100,8,FALSE),"0") -> 0 | T21: =S21*☆入力!L33 -> 0 | U21: =☆入力!AE33*☆入力!L33 -> 0 | V21: =ROUNDDOWN((T21+U21),0) -> 0 | X21: =IFERROR((代理店入力用!$D$5/☆入力!$AH$14)*☆入力!$AH33,"0") -> 0 | Y21: =X21/54 -> 0 | AH21: R | AI21: =ROUNDDOWN(☆入力!W33*☆入力!X33,0) -> 0 | AJ21: =ROUNDDOWN(☆入力!AB33*☆入力!X33,0) -> 0 | AK21: =ROUNDDOWN(☆入力!AB33*☆入力!AD33,0) -> 0
B22: 合計 | C22: =SUM(C19:C21) -> 0 | D22: =SUM(D19:D21) -> #REF! | E22: =SUM(E19:E21) -> 0 | H22: 合計 | I22: =SUM(I20:I21) -> 0 | J22: =SUM(J19:J21) -> 0 | K22: =SUM(K19:K21) -> 0 | M22: 21 | N22: 2 | Q22: 19 | S22: =IFERROR(VLOOKUP(☆入力!$G34,選定!$C$1:$AG$100,8,FALSE),"0") -> 0 | T22: =S22*☆入力!L34 -> 0 | U22: =☆入力!AE34*☆入力!L34 -> 0 | V22: =ROUNDDOWN((T22+U22),0) -> 0 | X22: =IFERROR((代理店入力用!$D$5/☆入力!$AH$14)*☆入力!$AH34,"0") -> 0 | Y22: =X22/54 -> 0 | AH22: S | AI22: =ROUNDDOWN(☆入力!W34*☆入力!X34,0) -> 0 | AJ22: =ROUNDDOWN(☆入力!AB34*☆入力!X34,0) -> 0 | AK22: =ROUNDDOWN(☆入力!AB34*☆入力!AD34,0) -> 0
D23: =C22-D22 -> #REF! | E23: =C22-E22 -> 0 | J23: =INT(I22-J22) -> 0 | K23: =INT(I22-K22) -> 0 | M23: 41 | N23: 3 | Q23: 20 | S23: =IFERROR(VLOOKUP(☆入力!$G35,選定!$C$1:$AG$100,8,FALSE),"0") -> 0 | T23: =S23*☆入力!L35 -> 0 | U23: =☆入力!AE35*☆入力!L35 -> 0 | V23: =ROUNDDOWN((T23+U23),0) -> 0 | X23: =IFERROR((代理店入力用!$D$5/☆入力!$AH$14)*☆入力!$AH35,"0") -> 0 | Y23: =X23/54 -> 0 | AH23: T | AI23: =ROUNDDOWN(☆入力!W35*☆入力!X35,0) -> 0 | AJ23: =ROUNDDOWN(☆入力!AB35*☆入力!X35,0) -> 0 | AK23: =ROUNDDOWN(☆入力!AB35*☆入力!AD35,0) -> 0
D24: =100%-(D22/C22) -> #REF! | E24: =100%-(E22/C22) -> #DIV/0! | J24: =100%-(J22/I22) -> #DIV/0! | K24: =100%-(K22/I22) -> #DIV/0! | M24: 61 | N24: 4 | Q24: 21 | S24: =IFERROR(VLOOKUP(☆入力!$G36,選定!$C$1:$AG$100,8,FALSE),"0") -> 0 | T24: =S24*☆入力!L36 -> 0 | U24: =☆入力!AE36*☆入力!L36 -> 0 | V24: =ROUNDDOWN((T24+U24),0) -> 0 | X24: =IFERROR((代理店入力用!$D$5/☆入力!$AH$14)*☆入力!$AH36,"0") -> 0 | Y24: =X24/54 -> 0 | AH24: U | AI24: =ROUNDDOWN(☆入力!W36*☆入力!X36,0) -> 0 | AJ24: =ROUNDDOWN(☆入力!AB36*☆入力!X36,0) -> 0 | AK24: =ROUNDDOWN(☆入力!AB36*☆入力!AD36,0) -> 0
D25: =-(C22-D22) -> #REF! | J25: =-(I22-J22) -> 0 | M25: 81 | N25: 5 | Q25: 22 | S25: =IFERROR(VLOOKUP(☆入力!$G37,選定!$C$1:$AG$100,8,FALSE),"0") -> 0 | T25: =S25*☆入力!L37 -> 0 | U25: =☆入力!AE37*☆入力!L37 -> 0 | V25: =ROUNDDOWN((T25+U25),0) -> 0 | X25: =IFERROR((代理店入力用!$D$5/☆入力!$AH$14)*☆入力!$AH37,"0") -> 0 | Y25: =X25/54 -> 0 | AH25: V | AI25: =ROUNDDOWN(☆入力!W37*☆入力!X37,0) -> 0 | AJ25: =ROUNDDOWN(☆入力!AB37*☆入力!X37,0) -> 0 | AK25: =ROUNDDOWN(☆入力!AB37*☆入力!AD37,0) -> 0
M26: 100 | N26: 6 | Q26: 23 | S26: =IFERROR(VLOOKUP(☆入力!$G38,選定!$C$1:$AG$100,8,FALSE),"0") -> 0 | T26: =S26*☆入力!L38 -> 0 | U26: =☆入力!AE38*☆入力!L38 -> 0 | V26: =ROUNDDOWN((T26+U26),0) -> 0 | X26: =IFERROR((代理店入力用!$D$5/☆入力!$AH$14)*☆入力!$AH38,"0") -> 0 | Y26: =X26/54 -> 0 | AH26: W | AI26: =ROUNDDOWN(☆入力!W38*☆入力!X38,0) -> 0 | AJ26: =ROUNDDOWN(☆入力!AB38*☆入力!X38,0) -> 0 | AK26: =ROUNDDOWN(☆入力!AB38*☆入力!AD38,0) -> 0
M27: 1000 | N27: 50 | Q27: 24 | S27: =IFERROR(VLOOKUP(☆入力!$G39,選定!$C$1:$AG$100,8,FALSE),"0") -> 0 | T27: =S27*☆入力!L39 -> 0 | U27: =☆入力!AE39*☆入力!L39 -> 0 | V27: =ROUNDDOWN((T27+U27),0) -> 0 | X27: =IFERROR((代理店入力用!$D$5/☆入力!$AH$14)*☆入力!$AH39,"0") -> 0 | Y27: =X27/54 -> 0 | AH27: Z | AI27: =ROUNDDOWN(☆入力!W39*☆入力!X39,0) -> 0 | AJ27: =ROUNDDOWN(☆入力!AB39*☆入力!X39,0) -> 0 | AK27: =ROUNDDOWN(☆入力!AB39*☆入力!AD39,0) -> 0
Q28: 25 | S28: =IFERROR(VLOOKUP(☆入力!$G40,選定!$C$1:$AG$100,8,FALSE),"0") -> 0 | T28: =S28*☆入力!L40 -> 0 | U28: =☆入力!AE40*☆入力!L40 -> 0 | V28: =ROUNDDOWN((T28+U28),0) -> 0 | X28: =IFERROR((代理店入力用!$D$5/☆入力!$AH$14)*☆入力!$AH40,"0") -> 0 | Y28: =X28/54 -> 0 | AH28: Y | AI28: =ROUNDDOWN(☆入力!W40*☆入力!X40,0) -> 0 | AJ28: =ROUNDDOWN(☆入力!AB40*☆入力!X40,0) -> 0 | AK28: =ROUNDDOWN(☆入力!AB40*☆入力!AD40,0) -> 0
D29: =100%-(③後a!AS6/②前a!AS6) -> #DIV/0! | H29: ⑦非なし | I29: ⑦非あり | Q29: 26 | S29: =IFERROR(VLOOKUP(☆入力!$G41,選定!$C$1:$AG$100,8,FALSE),"0") -> 0 | T29: =S29*☆入力!L41 -> 0 | U29: =☆入力!AE41*☆入力!L41 -> 0 | V29: =ROUNDDOWN((T29+U29),0) -> 0 | X29: =IFERROR((代理店入力用!$D$5/☆入力!$AH$14)*☆入力!$AH41,"0") -> 0 | Y29: =X29/54 -> 0 | AH29: Z | AI29: =ROUNDDOWN(☆入力!W41*☆入力!X41,0) -> 0 | AJ29: =ROUNDDOWN(☆入力!AB41*☆入力!X41,0) -> 0 | AK29: =ROUNDDOWN(☆入力!AB41*☆入力!AD41,0) -> 0
Q30: 27 | S30: =IFERROR(VLOOKUP(☆入力!$G42,選定!$C$1:$AG$100,8,FALSE),"0") -> 0 | T30: =S30*☆入力!L42 -> 0 | U30: =☆入力!AE42*☆入力!L42 -> 0 | V30: =ROUNDDOWN((T30+U30),0) -> 0 | X30: =IFERROR((代理店入力用!$D$5/☆入力!$AH$14)*☆入力!$AH42,"0") -> 0 | Y30: =X30/54 -> 0 | AH30: AA | AI30: =ROUNDDOWN(☆入力!W42*☆入力!X42,0) -> 0 | AJ30: =ROUNDDOWN(☆入力!AB42*☆入力!X42,0) -> 0 | AK30: =ROUNDDOWN(☆入力!AB42*☆入力!AD42,0) -> 0
D31: =②前a!AS41-③後a!AS41 -> 0 | H31: 削減金額 | Q31: 28 | S31: =IFERROR(VLOOKUP(☆入力!$G43,選定!$C$1:$AG$100,8,FALSE),"0") -> 0 | T31: =S31*☆入力!L43 -> 0 | U31: =☆入力!AE43*☆入力!L43 -> 0 | V31: =ROUNDDOWN((T31+U31),0) -> 0 | X31: =IFERROR((代理店入力用!$D$5/☆入力!$AH$14)*☆入力!$AH43,"0") -> 0 | Y31: =X31/54 -> 0 | AH31: AB | AI31: =ROUNDDOWN(☆入力!W43*☆入力!X43,0) -> 0 | AJ31: =ROUNDDOWN(☆入力!AB43*☆入力!X43,0) -> 0 | AK31: =ROUNDDOWN(☆入力!AB43*☆入力!AD43,0) -> 0
B32: =ROUNDDOWN((☆入力!AL14)*(100%-☆入力!AR11)+代理店入力用!D5,0) -> 0 | H32: リース代 | J32: ='⑧-bｼﾐｭ'!R7 -> 0 | M32: =VLOOKUP(☆入力!B14,N32:O33,2,) -> 試算エリア | N32: 1棟のみ | O32: 試算エリア | Q32: 29 | S32: =IFERROR(VLOOKUP(☆入力!$G44,選定!$C$1:$AG$100,8,FALSE),"0") -> 0 | T32: =S32*☆入力!L44 -> 0 | U32: =☆入力!AE44*☆入力!L44 -> 0 | V32: =ROUNDDOWN((T32+U32),0) -> 0 | X32: =IFERROR((代理店入力用!$D$5/☆入力!$AH$14)*☆入力!$AH44,"0") -> 0 | Y32: =X32/54 -> 0 | AH32: AC | AI32: =ROUNDDOWN(☆入力!W44*☆入力!X44,0) -> 0 | AJ32: =ROUNDDOWN(☆入力!AB44*☆入力!X44,0) -> 0 | AK32: =ROUNDDOWN(☆入力!AB44*☆入力!AD44,0) -> 0
B33: =(B32/(100%-☆入力!AR11))*(100%-☆入力!AR11-☆入力!AR12) -> 0 | D33: =☆入力!AR11 -> 0 | H33: 交換コスト | I33: =I20 -> 0 | J33: =J20 -> 0 | K33: =K20 -> 0 | N33: 複数棟 | O33: 物件名 | Q33: 30 | S33: =IFERROR(VLOOKUP(☆入力!$G45,選定!$C$1:$AG$100,8,FALSE),"0") -> 0 | T33: =S33*☆入力!L45 -> 0 | U33: =☆入力!AE45*☆入力!L45 -> 0 | V33: =ROUNDDOWN((T33+U33),0) -> 0 | X33: =IFERROR((代理店入力用!$D$5/☆入力!$AH$14)*☆入力!$AH45,"0") -> 0 | Y33: =X33/54 -> 0 | AH33: AD | AI33: =ROUNDDOWN(☆入力!W45*☆入力!X45,0) -> 0 | AJ33: =ROUNDDOWN(☆入力!AB45*☆入力!X45,0) -> 0 | AK33: =ROUNDDOWN(☆入力!AB45*☆入力!AD45,0) -> 0
H34: 電気代 | I34: =I21 -> 0 | J34: =J21 -> 0 | K34: =K21 -> 0
H35: 合計 | I35: =SUM(I32:I34) -> 0 | J35: =SUM(J32:J34) -> 0 | K35: =SUM(K32:K34) -> 0
C36: 特殊工事 | J36: =INT(I35-J35) -> 0 | K36: =INT(I35-K35) -> 0 | M36: 通常施工 | N36: 3000 | O36: =SUMIFS(☆入力!$L$16:$L$45,☆入力!$AE$16:$AE$45,N36) -> 0
C37: 高所作業費用 | M37: 非常灯別置 | N37: 5000 | O37: =SUMIFS(☆入力!$L$16:$L$45,☆入力!$AE$16:$AE$45,N37) -> 0
C38: 庭園灯作業 | M38: 配線直結 | O38: =SUMIFS(☆入力!$L$16:$L$45,☆入力!$AE$16:$AE$45,N38) -> 0
C39: 新設配線費用 | M39: ランプ交換 | O39: =SUMIFS(☆入力!$L$16:$L$45,☆入力!$AE$16:$AE$45,N39) -> 0
C40: EEセンサー交換費用
A42: 非常灯なし
B43: =☆入力!AG16 -> 0 | G43: =☆入力!AG17 -> 0 | L43: =☆入力!AG18 -> 0 | Q43: =☆入力!AG19 -> 0
C44: 現状 | D44: 5年間 | E44: 5年後 | H44: 現状 | I44: 5年間 | J44: 5年後 | M44: 現状 | N44: 5年間 | O44: 5年後 | R44: 現状 | S44: 5年間 | T44: 5年後
B45: リース代 | D45: =☆入力!AR16 -> 0 | G45: リース代 | I45: =☆入力!AR17 -> 0 | L45: リース代 | N45: =☆入力!AR18 -> 0 | Q45: リース代 | S45: =☆入力!AR19 -> 0
B46: 交換コスト | C46: =K66 -> 0 | G46: 交換コスト | H46: =K67 -> 0 | L46: 交換コスト | M46: =K68 -> 0 | Q46: 交換コスト | R46: =K69 -> 0
B47: 電気代 | C47: =C66 -> 0 | D47: =D66 -> 0 | E47: =D66 -> 0 | G47: 電気代 | H47: =C67 -> 0 | I47: =D67 -> 0 | J47: =D67 -> 0 | L47: 電気代 | M47: =C68 -> 0 | N47: =D68 -> 0 | O47: =D68 -> 0 | Q47: 電気代 | R47: =C69 -> 0 | S47: =D69 -> 0 | T47: =D69 -> 0
B48: 合計 | C48: =SUM(C45:C47) -> 0 | D48: =SUM(D45:D47) -> 0 | E48: =SUM(E45:E47) -> 0 | G48: 合計 | H48: =SUM(H45:H47) -> 0 | I48: =SUM(I45:I47) -> 0 | J48: =SUM(J45:J47) -> 0 | L48: 合計 | M48: =SUM(M45:M47) -> 0 | N48: =SUM(N45:N47) -> 0 | O48: =SUM(O45:O47) -> 0 | Q48: 合計 | R48: =SUM(R45:R47) -> 0 | S48: =SUM(S45:S47) -> 0 | T48: =SUM(T45:T47) -> 0
B49: 差額 | D49: =C48-D48 -> 0 | E49: =C48-E48 -> 0 | G49: 差額 | I49: =H48-I48 -> 0 | J49: =H48-J48 -> 0 | L49: 差額 | N49: =M48-N48 -> 0 | O49: =M48-O48 -> 0 | Q49: 差額 | S49: =R48-S48 -> 0 | T49: =R48-T48 -> 0
B50: ① | C50: =(C48-D48)*60 -> 0 | H50: =(H48-I48)*60 -> 0 | M50: =(M48-N48)*60 -> 0 | R50: =(R48-S48)*60 -> 0
B51: ② | C51: =(C48-E48)*60 -> 0 | H51: =(H48-J48)*60 -> 0 | M51: =(M48-O48)*60 -> 0 | R51: =(R48-T48)*60 -> 0
B52: ③ | C52: =C50+C51 -> 0 | H52: =H50+H51 -> 0 | M52: =M50+M51 -> 0 | R52: =R50+R51 -> 0
A53: 非常灯あり
B54: =B43 -> 0 | G54: =G43 -> 0 | L54: =L43 -> 0 | Q54: =Q43 -> 0
C55: 現状 | D55: 5年間 | E55: 5年後 | H55: 現状 | I55: 5年間 | J55: 5年後 | M55: 現状 | N55: 5年間 | O55: 5年後 | R55: 現状 | S55: 5年間 | T55: 5年後
B56: リース代 | D56: =D45 -> 0 | G56: リース代 | I56: =I45 -> 0 | L56: リース代 | N56: =N45 -> 0 | Q56: リース代 | S56: =S45 -> 0
B57: 交換コスト | C57: =P66 -> 0 | D57: =O66 -> 0 | E57: =O66 -> 0 | G57: 交換コスト | H57: =P67 -> 0 | I57: =O67 -> 0 | J57: =O67 -> 0 | L57: 交換コスト | M57: =P68 -> 0 | N57: =O68 -> 0 | O57: =O68 -> 0 | Q57: 交換コスト | R57: =P69 -> 0 | S57: =O69 -> 0 | T57: =O69 -> 0
B58: 電気代 | C58: =C47 -> 0 | D58: =D47 -> 0 | E58: =E47 -> 0 | G58: 電気代 | H58: =H47 -> 0 | I58: =I47 -> 0 | J58: =J47 -> 0 | L58: 電気代 | M58: =M47 -> 0 | N58: =N47 -> 0 | O58: =O47 -> 0 | Q58: 電気代 | R58: =R47 -> 0 | S58: =S47 -> 0 | T58: =T47 -> 0
B59: 合計 | C59: =SUM(C56:C58) -> 0 | D59: =SUM(D56:D58) -> 0 | E59: =SUM(E56:E58) -> 0 | G59: 合計 | H59: =SUM(H56:H58) -> 0 | I59: =SUM(I56:I58) -> 0 | J59: =SUM(J56:J58) -> 0 | L59: 合計 | M59: =SUM(M56:M58) -> 0 | N59: =SUM(N56:N58) -> 0 | O59: =SUM(O56:O58) -> 0 | Q59: 合計 | R59: =SUM(R56:R58) -> 0 | S59: =SUM(S56:S58) -> 0 | T59: =SUM(T56:T58) -> 0
B60: 差額 | D60: =C59-D59 -> 0 | E60: =C59-E59 -> 0 | G60: 差額 | I60: =H59-I59 -> 0 | J60: =H59-J59 -> 0 | L60: 差額 | N60: =M59-N59 -> 0 | O60: =M59-O59 -> 0 | Q60: 差額 | S60: =R59-S59 -> 0 | T60: =R59-T59 -> 0
B61: ① | C61: =(C59-D59)*60 -> 0 | H61: =(H59-I59)*60 -> 0 | M61: =(M59-N59)*60 -> 0 | R61: =(R59-S59)*60 -> 0
B62: ② | C62: =(C59-E59)*60 -> 0 | H62: =(H59-J59)*60 -> 0 | M62: =(M59-O59)*60 -> 0 | R62: =(R59-T59)*60 -> 0
B63: ③ | C63: =C61+C62 -> 0 | H63: =H61+H62 -> 0 | M63: =M61+M62 -> 0 | R63: =R61+R62 -> 0
C65: 導入前 | D65: LED後 | E65: 360 | F65: 720 | G65: 交換360 | H65: 交換720 | I65: 交換非常灯 | J65: 交換合計 | L65: LED交換 | M65: 非常灯 | N65: LED後合計
B66: =☆入力!AG16 -> 0 | C66: =SUMIF(☆入力!$B$16:$B$45,☆入力!$AG16,☆入力!$Y$16:$Y$45) -> 0 | D66: =SUMIF(☆入力!$B$16:$B$45,☆入力!$AG16,☆入力!$AC$16:$AC$45) -> 0 | E66: =SUMIFS(☆入力!$L$16:$L$45,☆入力!$H$16:$H$45,$E$65,☆入力!$B$16:$B$45,☆入力!$AG16) -> 0 | F66: =SUMIFS(☆入力!$L$16:$L$45,☆入力!$H$16:$H$45,$F$65,☆入力!$B$16:$B$45,☆入力!$AG16) -> 0 | G66: =☆入力!$AR$9*$E66*7 -> 0 | H66: =☆入力!$AR$9*$F66*15 -> 0 | I66: =☆入力!$M$12*10000*2 -> 0 | J66: =SUM(G66:H66) -> 0 | K66: =J66/120 -> 0 | L66: =F66*3000*1 -> 0 | M66: =☆入力!$M$12*8000*2 -> 0 | N66: =SUM(L66:M66) -> 0 | O66: =N66/120 -> 0 | P66: =(J66+I66)/120 -> 0
B67: =☆入力!AG17 -> 0 | C67: =SUMIF(☆入力!$B$16:$B$45,☆入力!$AG17,☆入力!$Y$16:$Y$45) -> 0 | D67: =SUMIF(☆入力!$B$16:$B$45,☆入力!$AG17,☆入力!$AC$16:$AC$45) -> 0 | E67: =SUMIFS(☆入力!$L$16:$L$45,☆入力!$H$16:$H$45,$E$65,☆入力!$B$16:$B$45,☆入力!$AG17) -> 0 | F67: =SUMIFS(☆入力!$L$16:$L$45,☆入力!$H$16:$H$45,$F$65,☆入力!$B$16:$B$45,☆入力!$AG17) -> 0 | G67: =☆入力!$AR$9*$E67*7 -> 0 | H67: =☆入力!$AR$9*$F67*15 -> 0 | I67: =☆入力!$N$12*10000*2 -> 0 | J67: =SUM(G67:H67) -> 0 | K67: =J67/120 -> 0 | L67: =F67*3000*1 -> 0 | M67: =☆入力!$N$12*8000*2 -> 0 | N67: =SUM(L67:M67) -> 0 | O67: =N67/120 -> 0 | P67: =(J67+I67)/120 -> 0
B68: =☆入力!AG18 -> 0 | C68: =SUMIF(☆入力!$B$16:$B$45,☆入力!$AG18,☆入力!$Y$16:$Y$45) -> 0 | D68: =SUMIF(☆入力!$B$16:$B$45,☆入力!$AG18,☆入力!$AC$16:$AC$45) -> 0 | E68: =SUMIFS(☆入力!$L$16:$L$45,☆入力!$H$16:$H$45,$E$65,☆入力!$B$16:$B$45,☆入力!$AG18) -> 0 | F68: =SUMIFS(☆入力!$L$16:$L$45,☆入力!$H$16:$H$45,$F$65,☆入力!$B$16:$B$45,☆入力!$AG18) -> 0 | G68: =☆入力!$AR$9*$E68*7 -> 0 | H68: =☆入力!$AR$9*$F68*15 -> 0 | I68: =☆入力!$O$12*10000*2 -> 0 | J68: =SUM(G68:H68) -> 0 | K68: =J68/120 -> 0 | L68: =F68*3000*1 -> 0 | M68: =☆入力!$O$12*8000*2 -> 0 | N68: =SUM(L68:M68) -> 0 | O68: =N68/120 -> 0 | P68: =(J68+I68)/120 -> 0
B69: =☆入力!AG19 -> 0 | C69: =SUMIF(☆入力!$B$16:$B$45,☆入力!$AG19,☆入力!$Y$16:$Y$45) -> 0 | D69: =SUMIF(☆入力!$B$16:$B$45,☆入力!$AG19,☆入力!$AC$16:$AC$45) -> 0 | E69: =SUMIFS(☆入力!$L$16:$L$45,☆入力!$H$16:$H$45,$E$65,☆入力!$B$16:$B$45,☆入力!$AG19) -> 0 | F69: =SUMIFS(☆入力!$L$16:$L$45,☆入力!$H$16:$H$45,$F$65,☆入力!$B$16:$B$45,☆入力!$AG19) -> 0 | G69: =☆入力!$AR$9*$E69*7 -> 0 | H69: =☆入力!$AR$9*$F69*15 -> 0 | I69: =☆入力!$P$12*10000*2 -> 0 | J69: =SUM(G69:H69) -> 0 | K69: =J69/120 -> 0 | L69: =F69*3000*1 -> 0 | M69: =☆入力!$P$12*8000*2 -> 0 | N69: =SUM(L69:M69) -> 0 | O69: =N69/120 -> 0 | P69: =(J69+I69)/120 -> 0
C70: =SUM(C66:C69) -> 0 | D70: =SUM(D66:D69) -> 0 | G70: =SUM(G66:G69) -> 0 | I70: =SUM(I66:I69) -> 0 | K70: =SUM(K66:K69) -> 0 | O70: =SUM(O66:O69) -> 0 | P70: =SUM(P66:P69) -> 0
A74: 物件名 | B74: =☆入力!AG16 -> 0 | E74: 12 | F74: 12 | G74: 12 | H74: 12 | I74: 12 | J74: 12 | K74: 12 | L74: 12 | M74: 12 | N74: 12 | O74: 12 | P74: 月数
B75: LED導入費用 | C75: 毎月の電気代 | D75: 交換コスト | E75: 0 | F75: 1 | G75: 2 | H75: 3 | I75: 4 | J75: 5 | K75: 6 | L75: 7 | M75: 8 | N75: 9 | O75: 10 | P75: 年数
C76: =C66 -> 0 | D76: =K66 -> 0 | E76: =($C76+$D76)*E$75*E$74 -> 0 | F76: =($C$76+$D$76)*F$75*F$74 -> 0 | G76: =($C$76+$D$76)*G$75*G$74 -> 0 | H76: =($C$76+$D$76)*H$75*H$74 -> 0 | I76: =($C$76+$D$76)*I$75*I$74 -> 0 | J76: =($C$76+$D$76)*J$75*J$74 -> 0 | K76: =($C$76+$D$76)*K$75*K$74 -> 0 | L76: =($C$76+$D$76)*L$75*L$74 -> 0 | M76: =($C$76+$D$76)*M$75*M$74 -> 0 | ... O76: =($C$76+$D$76)*O$75*O$74 -> 0 | P76: 現状 | Q76: 非常灯無し
C77: =C66 -> 0 | D77: =P66 -> 0 | E77: =($C77+$D77)*E$75*E$74 -> 0 | F77: =($C77+$D77)*F$75*F$74 -> 0 | G77: =($C77+$D77)*G$75*G$74 -> 0 | H77: =($C77+$D77)*H$75*H$74 -> 0 | I77: =($C77+$D77)*I$75*I$74 -> 0 | J77: =($C77+$D77)*J$75*J$74 -> 0 | K77: =($C77+$D77)*K$75*K$74 -> 0 | L77: =($C77+$D77)*L$75*L$74 -> 0 | ... O77: =($C77+$D77)*O$75*O$74 -> 0 | P77: 現状 | Q77: 非常灯あり
B78: =☆入力!AO16 -> 0 | C78: =D66 -> 0 | D78: 0 | E78: =(($C78+$D78)*E$75*E$74)+$B78 -> 0 | F78: =(($C78+$D78)*F$75*F$74)+$B78 -> 0 | G78: =(($C78+$D78)*G$75*G$74)+$B78 -> 0 | H78: =(($C78+$D78)*H$75*H$74)+$B78 -> 0 | I78: =(($C78+$D78)*I$75*I$74)+$B78 -> 0 | J78: =(($C78+$D78)*J$75*J$74)+$B78 -> 0 | K78: =(($C78+$D78)*K$75*K$74)+$B78 -> 0 | L78: =(($C78+$D78)*L$75*L$74)+$B78 -> 0 | ... O78: =(($C78+$D78)*O$75*O$74)+$B78 -> 0 | P78: LED | Q78: 非常灯無し
B79: =☆入力!AO16 -> 0 | C79: =D66 -> 0 | D79: =O66 -> 0 | E79: =(($C79+$D79)*E$75*E$74)+$B79 -> 0 | F79: =(($C79+$D79)*F$75*F$74)+$B79 -> 0 | G79: =(($C79+$D79)*G$75*G$74)+$B79 -> 0 | H79: =(($C79+$D79)*H$75*H$74)+$B79 -> 0 | I79: =(($C79+$D79)*I$75*I$74)+$B79 -> 0 | J79: =(($C79+$D79)*J$75*J$74)+$B79 -> 0 | K79: =(($C79+$D79)*K$75*K$74)+$B79 -> 0 | L79: =(($C79+$D79)*L$75*L$74)+$B79 -> 0 | ... O79: =(($C79+$D79)*O$75*O$74)+$B79 -> 0 | P79: LED | Q79: 非常灯あり
A82: 物件名 | B82: =B67 -> 0 | E82: 12 | F82: 12 | G82: 12 | H82: 12 | I82: 12 | J82: 12 | K82: 12 | L82: 12 | M82: 12 | N82: 12 | O82: 12 | P82: 月数
B83: LED導入費用 | C83: 毎月の電気代 | D83: 交換コスト | E83: 0 | F83: 1 | G83: 2 | H83: 3 | I83: 4 | J83: 5 | K83: 6 | L83: 7 | M83: 8 | N83: 9 | O83: 10 | P83: 年数
C84: =C67 -> 0 | D84: =K67 -> 0 | E84: =($C84+$D84)*E$75*E$74 -> 0 | F84: =($C84+$D84)*F$75*F$74 -> 0 | G84: =($C84+$D84)*G$75*G$74 -> 0 | H84: =($C84+$D84)*H$75*H$74 -> 0 | I84: =($C84+$D84)*I$75*I$74 -> 0 | J84: =($C84+$D84)*J$75*J$74 -> 0 | K84: =($C84+$D84)*K$75*K$74 -> 0 | L84: =($C84+$D84)*L$75*L$74 -> 0 | ... O84: =($C84+$D84)*O$75*O$74 -> 0 | P84: 現状 | Q84: 非常灯無し
C85: =C67 -> 0 | D85: =P67 -> 0 | E85: =($C85+$D85)*E$75*E$74 -> 0 | F85: =($C85+$D85)*F$75*F$74 -> 0 | G85: =($C85+$D85)*G$75*G$74 -> 0 | H85: =($C85+$D85)*H$75*H$74 -> 0 | I85: =($C85+$D85)*I$75*I$74 -> 0 | J85: =($C85+$D85)*J$75*J$74 -> 0 | K85: =($C85+$D85)*K$75*K$74 -> 0 | L85: =($C85+$D85)*L$75*L$74 -> 0 | ... O85: =($C85+$D85)*O$75*O$74 -> 0 | P85: 現状 | Q85: 非常灯あり
B86: =☆入力!AO17 -> 0 | C86: =D67 -> 0 | D86: 0 | E86: =(($C86+$D86)*E$75*E$74)+$B86 -> 0 | F86: =(($C86+$D86)*F$75*F$74)+$B86 -> 0 | G86: =(($C86+$D86)*G$75*G$74)+$B86 -> 0 | H86: =(($C86+$D86)*H$75*H$74)+$B86 -> 0 | I86: =(($C86+$D86)*I$75*I$74)+$B86 -> 0 | J86: =(($C86+$D86)*J$75*J$74)+$B86 -> 0 | K86: =(($C86+$D86)*K$75*K$74)+$B86 -> 0 | L86: =(($C86+$D86)*L$75*L$74)+$B86 -> 0 | ... O86: =(($C86+$D86)*O$75*O$74)+$B86 -> 0 | P86: LED | Q86: 非常灯無し
B87: =☆入力!AO17 -> 0 | C87: =D67 -> 0 | D87: =O67 -> 0 | E87: =(($C87+$D87)*E$75*E$74)+$B87 -> 0 | F87: =(($C87+$D87)*F$75*F$74)+$B87 -> 0 | G87: =(($C87+$D87)*G$75*G$74)+$B87 -> 0 | H87: =(($C87+$D87)*H$75*H$74)+$B87 -> 0 | I87: =(($C87+$D87)*I$75*I$74)+$B87 -> 0 | J87: =(($C87+$D87)*J$75*J$74)+$B87 -> 0 | K87: =(($C87+$D87)*K$75*K$74)+$B87 -> 0 | L87: =(($C87+$D87)*L$75*L$74)+$B87 -> 0 | ... O87: =(($C87+$D87)*O$75*O$74)+$B87 -> 0 | P87: LED | Q87: 非常灯あり
A90: 物件名 | B90: =B68 -> 0 | E90: 12 | F90: 12 | G90: 12 | H90: 12 | I90: 12 | J90: 12 | K90: 12 | L90: 12 | M90: 12 | N90: 12 | O90: 12 | P90: 月数
B91: LED導入費用 | C91: 毎月の電気代 | D91: 交換コスト | E91: 0 | F91: 1 | G91: 2 | H91: 3 | I91: 4 | J91: 5 | K91: 6 | L91: 7 | M91: 8 | N91: 9 | O91: 10 | P91: 年数
C92: =C68 -> 0 | D92: =K68 -> 0 | E92: =($C92+$D92)*E$75*E$74 -> 0 | F92: =($C92+$D92)*F$75*F$74 -> 0 | G92: =($C92+$D92)*G$75*G$74 -> 0 | H92: =($C92+$D92)*H$75*H$74 -> 0 | I92: =($C92+$D92)*I$75*I$74 -> 0 | J92: =($C92+$D92)*J$75*J$74 -> 0 | K92: =($C92+$D92)*K$75*K$74 -> 0 | L92: =($C92+$D92)*L$75*L$74 -> 0 | ... O92: =($C92+$D92)*O$75*O$74 -> 0 | P92: 現状 | Q92: 非常灯無し
C93: =C68 -> 0 | D93: =P68 -> 0 | E93: =($C93+$D93)*E$75*E$74 -> 0 | F93: =($C93+$D93)*F$75*F$74 -> 0 | G93: =($C93+$D93)*G$75*G$74 -> 0 | H93: =($C93+$D93)*H$75*H$74 -> 0 | I93: =($C93+$D93)*I$75*I$74 -> 0 | J93: =($C93+$D93)*J$75*J$74 -> 0 | K93: =($C93+$D93)*K$75*K$74 -> 0 | L93: =($C93+$D93)*L$75*L$74 -> 0 | ... O93: =($C93+$D93)*O$75*O$74 -> 0 | P93: 現状 | Q93: 非常灯あり
B94: =☆入力!AO18 -> 0 | C94: =D68 -> 0 | D94: 0 | E94: =(($C94+$D94)*E$75*E$74)+$B94 -> 0 | F94: =(($C94+$D94)*F$75*F$74)+$B94 -> 0 | G94: =(($C94+$D94)*G$75*G$74)+$B94 -> 0 | H94: =(($C94+$D94)*H$75*H$74)+$B94 -> 0 | I94: =(($C94+$D94)*I$75*I$74)+$B94 -> 0 | J94: =(($C94+$D94)*J$75*J$74)+$B94 -> 0 | K94: =(($C94+$D94)*K$75*K$74)+$B94 -> 0 | L94: =(($C94+$D94)*L$75*L$74)+$B94 -> 0 | ... O94: =(($C94+$D94)*O$75*O$74)+$B94 -> 0 | P94: LED | Q94: 非常灯無し
B95: =☆入力!AO18 -> 0 | C95: =D68 -> 0 | D95: =O68 -> 0 | E95: =(($C95+$D95)*E$75*E$74)+$B95 -> 0 | F95: =(($C95+$D95)*F$75*F$74)+$B95 -> 0 | G95: =(($C95+$D95)*G$75*G$74)+$B95 -> 0 | H95: =(($C95+$D95)*H$75*H$74)+$B95 -> 0 | I95: =(($C95+$D95)*I$75*I$74)+$B95 -> 0 | J95: =(($C95+$D95)*J$75*J$74)+$B95 -> 0 | K95: =(($C95+$D95)*K$75*K$74)+$B95 -> 0 | L95: =(($C95+$D95)*L$75*L$74)+$B95 -> 0 | ... O95: =(($C95+$D95)*O$75*O$74)+$B95 -> 0 | P95: LED | Q95: 非常灯あり
A98: 物件名 | B98: =B69 -> 0 | E98: 12 | F98: 12 | G98: 12 | H98: 12 | I98: 12 | J98: 12 | K98: 12 | L98: 12 | M98: 12 | N98: 12 | O98: 12 | P98: 月数
B99: LED導入費用 | C99: 毎月の電気代 | D99: 交換コスト | E99: 0 | F99: 1 | G99: 2 | H99: 3 | I99: 4 | J99: 5 | K99: 6 | L99: 7 | M99: 8 | N99: 9 | O99: 10 | P99: 年数
C100: =C69 -> 0 | D100: =K69 -> 0 | E100: =($C100+$D100)*E$75*E$74 -> 0 | F100: =($C100+$D100)*F$75*F$74 -> 0 | G100: =($C100+$D100)*G$75*G$74 -> 0 | H100: =($C100+$D100)*H$75*H$74 -> 0 | I100: =($C100+$D100)*I$75*I$74 -> 0 | J100: =($C100+$D100)*J$75*J$74 -> 0 | K100: =($C100+$D100)*K$75*K$74 -> 0 | L100: =($C100+$D100)*L$75*L$74 -> 0 | ... O100: =($C100+$D100)*O$75*O$74 -> 0 | P100: 現状 | Q100: 非常灯無し
C101: =C69 -> 0 | D101: =P69 -> 0 | E101: =($C101+$D101)*E$75*E$74 -> 0 | F101: =($C101+$D101)*F$75*F$74 -> 0 | G101: =($C101+$D101)*G$75*G$74 -> 0 | H101: =($C101+$D101)*H$75*H$74 -> 0 | I101: =($C101+$D101)*I$75*I$74 -> 0 | J101: =($C101+$D101)*J$75*J$74 -> 0 | K101: =($C101+$D101)*K$75*K$74 -> 0 | L101: =($C101+$D101)*L$75*L$74 -> 0 | ... O101: =($C101+$D101)*O$75*O$74 -> 0 | P101: 現状 | Q101: 非常灯あり
B102: =☆入力!AO19 -> 0 | C102: =D69 -> 0 | D102: 0 | E102: =(($C102+$D102)*E$75*E$74)+$B102 -> 0 | F102: =(($C102+$D102)*F$75*F$74)+$B102 -> 0 | G102: =(($C102+$D102)*G$75*G$74)+$B102 -> 0 | H102: =(($C102+$D102)*H$75*H$74)+$B102 -> 0 | I102: =(($C102+$D102)*I$75*I$74)+$B102 -> 0 | J102: =(($C102+$D102)*J$75*J$74)+$B102 -> 0 | K102: =(($C102+$D102)*K$75*K$74)+$B102 -> 0 | L102: =(($C102+$D102)*L$75*L$74)+$B102 -> 0 | ... O102: =(($C102+$D102)*O$75*O$74)+$B102 -> 0 | P102: LED | Q102: 非常灯無し
B103: =☆入力!AO19 -> 0 | C103: =D69 -> 0 | D103: =O69 -> 0 | E103: =(($C103+$D103)*E$75*E$74)+$B103 -> 0 | F103: =(($C103+$D103)*F$75*F$74)+$B103 -> 0 | G103: =(($C103+$D103)*G$75*G$74)+$B103 -> 0 | H103: =(($C103+$D103)*H$75*H$74)+$B103 -> 0 | I103: =(($C103+$D103)*I$75*I$74)+$B103 -> 0 | J103: =(($C103+$D103)*J$75*J$74)+$B103 -> 0 | K103: =(($C103+$D103)*K$75*K$74)+$B103 -> 0 | L103: =(($C103+$D103)*L$75*L$74)+$B103 -> 0 | ... O103: =(($C103+$D103)*O$75*O$74)+$B103 -> 0 | P103: LED | Q103: 非常灯あり

Sheet 選定
A1: 写真① | B1: 写真② | C1: 電球種別 | D1: 照明色 | E1: 器具色 | F1: 器具サイズ （設置面） | G1: 消費 電力 | H1: 全光束 | I1: 合算 定価 | J1: 合算 仕入 | K1: 防滴 | L1: 電球種別 | M1: メーカー | N1: W相当 | O1: 器具型番 | P1: 定価 | Q1: 仕入れ | R1: 型番② | S1: 定価② | T1: 仕入② | U1: 型番③ | V1: 定価③ | W1: 仕入③ | X1: 型番④ | Y1: 定価③ | Z1: 仕入③ | AA1: 消費電力 | AB1: 全光束 | AC1: 器具素材 | AD1: 器具色 選択肢 | AE1: 照明色 選択肢 | AF1: 定格 寿命 | AG1: 交換 方法 | AH1: 口金 | AI1: HP | AJ1: 備考
A2: 0 | B2: 0 | C2: 1 | D2: 2 | E2: 3 | F2: 4 | G2: 5 | H2: 6 | I2: 7 | J2: 8 | K2: 9 | L2: 10 | M2: 11 | N2: 12 | O2: 13 | P2: 14 | Q2: 15 | R2: 16 | S2: 17 | T2: 18 | U2: 19 | V2: 20 | W2: 21 | X2: 22 | Y2: 23 | Z2: 24 | AA2: 25 | AB2: 26 | AC2: 27 | AD2: 28 | AE2: 29 | AF2: 30 | AG2: 31 | AH2: 32 | AI2: 33 | AJ2: 34
C7: ************************
C8: ************************
C9: ************************
C10: ************************
C11: ************************
C12: ************************
C13: ************************
C14: ************************
C15: ************************
C16: ************************
C17: ************************
C18: ************************
... C40: ************************

Sheet ☆入力
B1: 受注額 | C1: 仕入額 | D1: 粗利益 | E1: リース代 | F1: 紹介料 | G1: 紹介斡旋料 | I1: ↓ここに数量表を貼り付け | X1: ↓「備考」・・・シート【前後】の『備考』へ反映
B2: =AO14 -> 0 | C2: =AP14 -> 0 | D2: =AQ14 -> 0 | E2: =AR14 -> 0 | F2: =AS14 -> 0 | G2: =AT14 -> 0 | M2: 【安定器が存在する電球は、全て「＋2W」で計上】 | AH2: ↓下記への入力は見積書に反映、
A3: ※電力を付帯しない場合には、電力割引を0%に変更してください | AH3: 備考(LED済みの箇所などを記載)：
M4: ↓安定器がある照明リスト | AH4: 生産終了品などがあった場合、同メーカーもしくは他メーカーの同等品に変更される場合がございます。
A5: 物件名： | M5: 直管蛍光灯（FL） | AH5: 新しい照明器具が、既設よりも一回り小さくなるケースがあり、その際は外壁塗装面が露出する
A6: 物件住所： | M6: サークライン（FCL） | AH6: 可能性がございます。
A7: 解錠番号： | M7: コンパクト蛍光灯（FDL、FHT、FPL、FML）
A8: 分電盤場所： | M8: ※水銀灯も安定器が存在するが、例外としてそのまま計上 | AR8: ※代理店案件の場合には、「代理店入力シート」にて金額変更
A9: 【工事依頼特記事項】 | M9: （例）20形蛍光灯・・・20W→22W | AQ9: 電球交換費 | AR9: =代理店入力用!D8 -> 0
AL10: 合計
M11: ① | N11: ② | O11: ③ | P11: ④ | Q11: ※複数棟合算の場合は | AH11: 【特殊工事】 | AJ11: 金額 | AL11: 1球売価 | AM11: 1球粗利 | AN11: 回収期間 | AQ11: 複数棟割引： | AS11: 紹介料：
J12: 非常灯・誘導灯の数→ | L12: =SUM(M12:P12) -> 0 | Q12: 個別に非常灯の数を入力 | AL12: =IFERROR(AO14/AH14,"0") -> 0 | AM12: =IFERROR(AQ14/AH14,"0") -> 0 | AN12: =⑨シミュレーション!AQ32 -> 0 | AQ12: 電力割引： | AR12: 0.05 | AS12: 斡旋料： | AT12: 0.03
AY13: 工事依頼・完了報告書
B14: 1棟のみ | C14: ←選択する | G14: ※選択制 | L14: =SUM(L16:L45) -> 0 | W14: =SUM(W16:W45) -> 0 | Y14: =SUM(Y16:Y45) -> 0 | AB14: =SUM(AB16:AB45) -> 0 | AC14: =SUM(AC16:AC45) -> 0 | AE14: ※手打可能 | AH14: =SUM(AH16:AH45) -> 0 | AI14: =SUM(AI16:AI45) -> 0 | AJ14: =SUM(AJ16:AJ45)+AJ12 -> 0 | AK14: =AL14/54 -> 0 | AL14: =SUM(AL16:AL45)+AJ12 -> 0 | AM14: =SUM(AM16:AM45) -> 0 | AO14: =SUM(AO16:AO45) -> 0 | AP14: =SUM(AP16:AP45) -> 0 | AQ14: =SUM(AQ16:AQ45) -> 0 | AR14: =SUM(AR16:AR45) -> 0 | AS14: =SUM(AS16:AS45) -> 0 | AT14: =SUM(AT16:AT45) -> 0 | AU14: ↓【5％】選択
B15: 物件名 | C15: 試算エリア | D15: 照明種別 | E15: 現調備考 | F15: 工事備考 | G15: 器具分類② | H15: 月間点灯 | I15: 一日点灯 | J15: 稼働日数 | K15: 消費電力 | L15: 電球数 | M15: 1階 | N15: 2階 | O15: 3階 | P15: 4階 | Q15: 5階 | R15: 6階 | S15: 7階 | T15: 8階 | U15: 9階 | V15: 10階 | W15: kWh | X15: 現状電気単価 | Y15: 電気代 | Z15: ⇒ | AA15: 消費電力 | AB15: kWh | AC15: 電気代 | AD15: 変更電気単価 | AE15: 工事単価 | AG15: 物件名 | AH15: 数量 | AI15: 商品原価 | AJ15: 工事費 | AK15: リース代 | AL15: 一括売価 | AM15: 粗利予測 | AN15: 利益率 | AO15: 受注額 | AP15: 仕入額 | AQ15: 粗利益 | AR15: 月額リース料 | AS15: 紹介料 | AT15: 紹介斡旋料 | AU15: 新電力割引 | AV15: 1球売価 | AW15: 1球粗利 | AY15: 交換方法 | AZ15: 試算エリア | BA15: 既存照明種別 | BB15: メーカー | BC15: 器具型番 | BD15: 器具型番② | BE15: 器具型番③ | BF15: 器具型番④ | BG15: 数量
A16: A | B16: =IF(C16="","",$C$5) | H16: =PRODUCT(I16,J16) -> 0 | J16: =IF(I16<>"",30,"") | L16: =SUM(M16:V16) -> 0 | W16: =($L16*$K16*$H16)/1000 -> 0 | X16: 30 | Y16: =ROUNDDOWN($W16*$X16,0) -> 0 | AA16: =IFERROR(VLOOKUP($G16,選定!$C$3:$AG$100,5,FALSE),0) -> 0 | AB16: =($AA16*$L16*$H16)/1000 -> 0 | AC16: =ROUNDDOWN($AB16*$AD16,0) -> 0 | AD16: 30 | AE16: 3000 | AF16: 1 | AG16: =C5 -> 0 | AH16: =SUMIF($B$16:$B$45,$AG16,$L$16:$L$45) -> 0 | AI16: =SUMIF($B$16:$B$45,$AG16,LED計算式!$T$4:$T$33) -> 0 | AJ16: =SUMIF($B$16:$B$45,$AG16,LED計算式!$U$4) -> 0 | AK16: =IFERROR(AL16*LED計算式!$AC$2,"") -> 0 | AL16: =ROUNDDOWN((AI16+AJ16)/(100%-$AN16),-3) -> 0 | AM16: =IFERROR($AL16-$AI16-$AJ16,"") -> 0 | AN16: 0.4 | AO16: =IFERROR(ROUNDDOWN($AL16*(100%-($AR$11+AU16)),-3),"") -> 0 | AP16: =AI16+AJ16 -> 0 | AQ16: =IFERROR(AO16-AI16-AJ16-AS16-AT16,"") -> 0 | AR16: =ROUNDDOWN(AO16*LED計算式!$AC$2,0) -> 0 | AS16: =IFERROR(AO16*$AT$11,"") -> 0 | AT16: =AO16*$AT$12 -> 0 | AV16: =IFERROR(AO16/AH16,0) -> 0 | AW16: =IFERROR(AQ16/AH16,0) -> 0 | AY16: =IFERROR(VLOOKUP(G16,選定!$C$3:$AG$100,28,FALSE),"0") -> 0 | AZ16: =C16 -> 0 | BA16: =D16 -> 0 | BB16: =IFERROR(VLOOKUP(G16,選定!$C$2:$AG$100,11,FALSE),"0") -> 0 | BC16: =IFERROR(VLOOKUP(G16,選定!$C$2:$AG$100,13,FALSE),"") | BD16: =IFERROR(VLOOKUP(G16,選定!$C$2:$AG$100,16,FALSE),"") | BE16: =IFERROR(VLOOKUP(G16,選定!$C$2:$AG$100,19,FALSE),"") | BF16: =IFERROR(VLOOKUP(G16,選定!$C$2:$AG$100,22,FALSE),"") | BG16: =L16 -> 0
A17: B | B17: =IF(C17="","",$C$5) | H17: =PRODUCT(I17,J17) -> 0 | J17: =IF(I17<>"",30,"") | L17: =SUM(M17:V17) -> 0 | W17: =($L17*$K17*$H17)/1000 -> 0 | X17: =$X$16 -> 30 | Y17: =ROUNDDOWN($W17*$X17,0) -> 0 | AA17: =IFERROR(VLOOKUP($G17,選定!$C$3:$AG$100,5,FALSE),0) -> 0 | AB17: =($AA17*$L17*$H17)/1000 -> 0 | AC17: =ROUNDDOWN($AB17*$AD17,0) -> 0 | AD17: =$AD$16 -> 30 | AE17: 3000 | AF17: 2 | AH17: =SUMIF($B$16:$B$45,$AG17,$L$16:$L$45) -> 0 | AI17: =SUMIF($B$16:$B$45,$AG17,LED計算式!$T$4:$T$33) -> 0 | AJ17: =SUMIF($B$16:$B$45,$AG17,LED計算式!$U$4) -> 0 | AK17: =IFERROR(AL17*LED計算式!$AC$2,"") -> 0 | AL17: =ROUNDDOWN((AI17+AJ17)/(100%-$AN17),-3) -> 0 | AM17: =IFERROR($AL17-$AI17-$AJ17,"") -> 0 | AN17: =$AN$16 -> 0.4 | AO17: =IFERROR(ROUNDDOWN($AL17*(100%-($AR$11+AU17)),-3),"") -> 0 | AP17: =AI17+AJ17 -> 0 | AQ17: =IFERROR(AO17-AI17-AJ17-AS17-AT17,"") -> 0 | AR17: =ROUNDDOWN(AO17*LED計算式!$AC$2,0) -> 0 | AS17: =IFERROR(AO17*$AT$11,"") -> 0 | AT17: =AO17*$AT$12 -> 0 | AV17: =IFERROR(AO17/AH17,0) -> 0 | AW17: =IFERROR(AQ17/AH17,0) -> 0 | AY17: =IFERROR(VLOOKUP(G17,選定!$C$3:$AG$100,28,FALSE),"0") -> 0 | AZ17: =C17 -> 0 | BA17: =D17 -> 0 | BB17: =IFERROR(VLOOKUP(G17,選定!$C$2:$AG$100,11,FALSE),"0") -> 0 | BC17: =IFERROR(VLOOKUP(G17,選定!$C$2:$AG$100,13,FALSE),"") | BD17: =IFERROR(VLOOKUP(G17,選定!$C$2:$AG$100,16,FALSE),"") | BE17: =IFERROR(VLOOKUP(G17,選定!$C$2:$AG$100,19,FALSE),"") | BF17: =IFERROR(VLOOKUP(G17,選定!$C$2:$AG$100,22,FALSE),"") | BG17: =L17 -> 0
A18: C | B18: =IF(C18="","",$C$5) | H18: =PRODUCT(I18,J18) -> 0 | J18: =IF(I18<>"",30,"") | L18: =SUM(M18:V18) -> 0 | W18: =($L18*$K18*$H18)/1000 -> 0 | X18: =$X$16 -> 30 | Y18: =ROUNDDOWN($W18*$X18,0) -> 0 | AA18: =IFERROR(VLOOKUP($G18,選定!$C$3:$AG$100,5,FALSE),0) -> 0 | AB18: =($AA18*$L18*$H18)/1000 -> 0 | AC18: =ROUNDDOWN($AB18*$AD18,0) -> 0 | AD18: =$AD$16 -> 30 | AE18: 3000 | AF18: 3 | AH18: =SUMIF($B$16:$B$45,$AG18,$L$16:$L$45) -> 0 | AI18: =SUMIF($B$16:$B$45,$AG18,LED計算式!$T$4:$T$33) -> 0 | AJ18: =SUMIF($B$16:$B$45,$AG18,LED計算式!$U$4) -> 0 | AK18: =IFERROR(AL18*LED計算式!$AC$2,"") -> 0 | AL18: =ROUNDDOWN((AI18+AJ18)/(100%-$AN18),-3) -> 0 | AM18: =IFERROR($AL18-$AI18-$AJ18,"") -> 0 | AN18: =$AN$16 -> 0.4 | AO18: =IFERROR(ROUNDDOWN($AL18*(100%-($AR$11+AU18)),-3),"") -> 0 | AP18: =AI18+AJ18 -> 0 | AQ18: =IFERROR(AO18-AI18-AJ18-AS18-AT18,"") -> 0 | AR18: =ROUNDDOWN(AO18*LED計算式!$AC$2,0) -> 0 | AS18: =IFERROR(AO18*$AT$11,"") -> 0 | AT18: =AO18*$AT$12 -> 0 | AV18: =IFERROR(AO18/AH18,0) -> 0 | AW18: =IFERROR(AQ18/AH18,0) -> 0 | AY18: =IFERROR(VLOOKUP(G18,選定!$C$3:$AG$100,28,FALSE),"0") -> 0 | AZ18: =C18 -> 0 | BA18: =D18 -> 0 | BB18: =IFERROR(VLOOKUP(G18,選定!$C$2:$AG$100,11,FALSE),"0") -> 0 | BC18: =IFERROR(VLOOKUP(G18,選定!$C$2:$AG$100,13,FALSE),"") | BD18: =IFERROR(VLOOKUP(G18,選定!$C$2:$AG$100,16,FALSE),"") | BE18: =IFERROR(VLOOKUP(G18,選定!$C$2:$AG$100,19,FALSE),"") | BF18: =IFERROR(VLOOKUP(G18,選定!$C$2:$AG$100,22,FALSE),"") | BG18: =L18 -> 0
A19: D | B19: =IF(C19="","",$C$5) | H19: =PRODUCT(I19,J19) -> 0 | J19: =IF(I19<>"",30,"") | L19: =SUM(M19:V19) -> 0 | W19: =($L19*$K19*$H19)/1000 -> 0 | X19: =$X$16 -> 30 | Y19: =ROUNDDOWN($W19*$X19,0) -> 0 | AA19: =IFERROR(VLOOKUP($G19,選定!$C$3:$AG$100,5,FALSE),0) -> 0 | AB19: =($AA19*$L19*$H19)/1000 -> 0 | AC19: =ROUNDDOWN($AB19*$AD19,0) -> 0 | AD19: =$AD$16 -> 30 | AE19: 3000 | AF19: 4 | AH19: =SUMIF($B$16:$B$45,$AG19,$L$16:$L$45) -> 0 | AI19: =SUMIF($B$16:$B$45,$AG19,LED計算式!$T$4:$T$33) -> 0 | AJ19: =SUMIF($B$16:$B$45,$AG19,LED計算式!$U$4) -> 0 | AK19: =IFERROR(AL19*LED計算式!$AC$2,"") -> 0 | AL19: =ROUNDDOWN((AI19+AJ19)/(100%-$AN19),-3) -> 0 | AM19: =IFERROR($AL19-$AI19-$AJ19,"") -> 0 | AN19: =$AN$16 -> 0.4 | AO19: =IFERROR(ROUNDDOWN($AL19*(100%-($AR$11+AU19)),-3),"") -> 0 | AP19: =AI19+AJ19 -> 0 | AQ19: =IFERROR(AO19-AI19-AJ19-AS19-AT19,"") -> 0 | AR19: =ROUNDDOWN(AO19*LED計算式!$AC$2,0) -> 0 | AS19: =IFERROR(AO19*$AT$11,"") -> 0 | AT19: =AO19*$AT$12 -> 0 | AV19: =IFERROR(AO19/AH19,0) -> 0 | AW19: =IFERROR(AQ19/AH19,0) -> 0 | AY19: =IFERROR(VLOOKUP(G19,選定!$C$3:$AG$100,28,FALSE),"0") -> 0 | AZ19: =C19 -> 0 | BA19: =D19 -> 0 | BB19: =IFERROR(VLOOKUP(G19,選定!$C$2:$AG$100,11,FALSE),"0") -> 0 | BC19: =IFERROR(VLOOKUP(G19,選定!$C$2:$AG$100,13,FALSE),"") | BD19: =IFERROR(VLOOKUP(G19,選定!$C$2:$AG$100,16,FALSE),"") | BE19: =IFERROR(VLOOKUP(G19,選定!$C$2:$AG$100,19,FALSE),"") | BF19: =IFERROR(VLOOKUP(G19,選定!$C$2:$AG$100,22,FALSE),"") | BG19: =L19 -> 0
A20: E | B20: =IF(C20="","",$C$5) | H20: =PRODUCT(I20,J20) -> 0 | J20: =IF(I20<>"",30,"") | L20: =SUM(M20:V20) -> 0 | W20: =($L20*$K20*$H20)/1000 -> 0 | X20: =$X$16 -> 30 | Y20: =ROUNDDOWN($W20*$X20,0) -> 0 | AA20: =IFERROR(VLOOKUP($G20,選定!$C$3:$AG$100,5,FALSE),0) -> 0 | AB20: =($AA20*$L20*$H20)/1000 -> 0 | AC20: =ROUNDDOWN($AB20*$AD20,0) -> 0 | AD20: =$AD$16 -> 30 | AE20: 3000 | AF20: 5 | AH20: =SUMIF($B$16:$B$45,$AG20,$L$16:$L$45) -> 0 | AI20: =SUMIF($B$16:$B$45,$AG20,LED計算式!$T$4:$T$33) -> 0 | AJ20: =SUMIF($B$16:$B$45,$AG20,LED計算式!$U$4) -> 0 | AK20: =IFERROR(AL20/54,"") -> 0 | AL20: =ROUNDDOWN((AI20+AJ20)/(100%-$AN20),0) -> 0 | AM20: =IFERROR($AL20-$AI20-$AJ20,"") -> 0 | AN20: =$AN$16 -> 0.4 | AO20: =IFERROR(ROUNDDOWN($AL20*(100%-($AR$11+AU20)),0),"") -> 0 | AP20: =AI20+AJ20 -> 0 | AQ20: =IFERROR(AO20-AI20-AJ20-AS20-AT20,"") -> 0 | AR20: =ROUNDDOWN(AO20/54,0) -> 0 | AS20: =IFERROR(AO20*$AT$11,"") -> 0 | AT20: =AO20*$AT$12 -> 0 | AV20: =IFERROR(AO20/AH20,0) -> 0 | AW20: =IFERROR(AQ20/AH20,0) -> 0 | AY20: =IFERROR(VLOOKUP(G20,選定!$C$3:$AG$100,28,FALSE),"0") -> 0 | AZ20: =C20 -> 0 | BA20: =D20 -> 0 | BB20: =IFERROR(VLOOKUP(G20,選定!$C$2:$AG$100,11,FALSE),"0") -> 0 | BC20: =IFERROR(VLOOKUP(G20,選定!$C$2:$AG$100,13,FALSE),"") | BD20: =IFERROR(VLOOKUP(G20,選定!$C$2:$AG$100,16,FALSE),"") | BE20: =IFERROR(VLOOKUP(G20,選定!$C$2:$AG$100,19,FALSE),"") | BF20: =IFERROR(VLOOKUP(G20,選定!$C$2:$AG$100,22,FALSE),"") | BG20: =L20 -> 0
A21: F | B21: =IF(C21="","",$C$5) | H21: =PRODUCT(I21,J21) -> 0 | J21: =IF(I21<>"",30,"") | L21: =SUM(M21:V21) -> 0 | W21: =($L21*$K21*$H21)/1000 -> 0 | X21: =$X$16 -> 30 | Y21: =ROUNDDOWN($W21*$X21,0) -> 0 | AA21: =IFERROR(VLOOKUP($G21,選定!$C$3:$AG$100,5,FALSE),0) -> 0 | AB21: =($AA21*$L21*$H21)/1000 -> 0 | AC21: =ROUNDDOWN($AB21*$AD21,0) -> 0 | AD21: =$AD$16 -> 30 | AE21: 3000 | AF21: 6 | AH21: =SUMIF($B$16:$B$45,$AG21,$L$16:$L$45) -> 0 | AI21: =SUMIF($B$16:$B$45,$AG21,LED計算式!$T$4:$T$33) -> 0 | AJ21: =SUMIF($B$16:$B$45,$AG21,LED計算式!$U$4) -> 0 | AK21: =IFERROR(AL21/54,"") -> 0 | AL21: =ROUNDDOWN((AI21+AJ21)/(100%-$AN21),0) -> 0 | AM21: =IFERROR($AL21-$AI21-$AJ21,"") -> 0 | AN21: =$AN$16 -> 0.4 | AO21: =IFERROR(ROUNDDOWN($AL21*(100%-($AR$11+AU21)),0),"") -> 0 | AP21: =AI21+AJ21 -> 0 | AQ21: =IFERROR(AO21-AI21-AJ21-AS21-AT21,"") -> 0 | AR21: =ROUNDDOWN(AO21/54,0) -> 0 | AS21: =IFERROR(AO21*$AT$11,"") -> 0 | AT21: =AO21*$AT$12 -> 0 | AV21: =IFERROR(AO21/AH21,0) -> 0 | AW21: =IFERROR(AQ21/AH21,0) -> 0 | AY21: =IFERROR(VLOOKUP(G21,選定!$C$3:$AG$100,28,FALSE),"0") -> 0 | AZ21: =C21 -> 0 | BA21: =D21 -> 0 | BB21: =IFERROR(VLOOKUP(G21,選定!$C$2:$AG$100,11,FALSE),"0") -> 0 | BC21: =IFERROR(VLOOKUP(G21,選定!$C$2:$AG$100,13,FALSE),"") | BD21: =IFERROR(VLOOKUP(G21,選定!$C$2:$AG$100,16,FALSE),"") | BE21: =IFERROR(VLOOKUP(G21,選定!$C$2:$AG$100,19,FALSE),"") | BF21: =IFERROR(VLOOKUP(G21,選定!$C$2:$AG$100,22,FALSE),"") | BG21: =L21 -> 0
A22: G | B22: =IF(C22="","",$C$5) | H22: =PRODUCT(I22,J22) -> 0 | J22: =IF(I22<>"",30,"") | L22: =SUM(M22:V22) -> 0 | W22: =($L22*$K22*$H22)/1000 -> 0 | X22: =$X$16 -> 30 | Y22: =ROUNDDOWN($W22*$X22,0) -> 0 | AA22: =IFERROR(VLOOKUP($G22,選定!$C$3:$AG$100,5,FALSE),0) -> 0 | AB22: =($AA22*$L22*$H22)/1000 -> 0 | AC22: =ROUNDDOWN($AB22*$AD22,0) -> 0 | AD22: =$AD$16 -> 30 | AE22: 3000 | AF22: 7 | AH22: =SUMIF($B$16:$B$45,$AG22,$L$16:$L$45) -> 0 | AI22: =SUMIF($B$16:$B$45,$AG22,LED計算式!$T$4:$T$33) -> 0 | AJ22: =SUMIF($B$16:$B$45,$AG22,LED計算式!$U$4) -> 0 | AK22: =IFERROR(AL22/54,"") -> 0 | AL22: =ROUNDDOWN((AI22+AJ22)/(100%-$AN22),0) -> 0 | AM22: =IFERROR($AL22-$AI22-$AJ22,"") -> 0 | AN22: =$AN$16 -> 0.4 | AO22: =IFERROR(ROUNDDOWN($AL22*(100%-($AR$11+AU22)),0),"") -> 0 | AP22: =AI22+AJ22 -> 0 | AQ22: =IFERROR(AO22-AI22-AJ22-AS22-AT22,"") -> 0 | AR22: =ROUNDDOWN(AO22/54,0) -> 0 | AS22: =IFERROR(AO22*$AT$11,"") -> 0 | AT22: =AO22*$AT$12 -> 0 | AV22: =IFERROR(AO22/AH22,0) -> 0 | AW22: =IFERROR(AQ22/AH22,0) -> 0 | AY22: =IFERROR(VLOOKUP(G22,選定!$C$3:$AG$100,28,FALSE),"0") -> 0 | AZ22: =C22 -> 0 | BA22: =D22 -> 0 | BB22: =IFERROR(VLOOKUP(G22,選定!$C$2:$AG$100,11,FALSE),"0") -> 0 | BC22: =IFERROR(VLOOKUP(G22,選定!$C$2:$AG$100,13,FALSE),"") | BD22: =IFERROR(VLOOKUP(G22,選定!$C$2:$AG$100,16,FALSE),"") | BE22: =IFERROR(VLOOKUP(G22,選定!$C$2:$AG$100,19,FALSE),"") | BF22: =IFERROR(VLOOKUP(G22,選定!$C$2:$AG$100,22,FALSE),"") | BG22: =L22 -> 0
A23: H | B23: =IF(C23="","",$C$5) | H23: =PRODUCT(I23,J23) -> 0 | J23: =IF(I23<>"",30,"") | L23: =SUM(M23:V23) -> 0 | W23: =($L23*$K23*$H23)/1000 -> 0 | X23: =$X$16 -> 30 | Y23: =ROUNDDOWN($W23*$X23,0) -> 0 | AA23: =IFERROR(VLOOKUP($G23,選定!$C$3:$AG$100,5,FALSE),0) -> 0 | AB23: =($AA23*$L23*$H23)/1000 -> 0 | AC23: =ROUNDDOWN($AB23*$AD23,0) -> 0 | AD23: =$AD$16 -> 30 | AE23: 3000 | AF23: 8 | AH23: =SUMIF($B$16:$B$45,$AG23,$L$16:$L$45) -> 0 | AI23: =SUMIF($B$16:$B$45,$AG23,LED計算式!$T$4:$T$33) -> 0 | AJ23: =SUMIF($B$16:$B$45,$AG23,LED計算式!$U$4) -> 0 | AK23: =IFERROR(AL23/54,"") -> 0 | AL23: =ROUNDDOWN((AI23+AJ23)/(100%-$AN23),0) -> 0 | AM23: =IFERROR($AL23-$AI23-$AJ23,"") -> 0 | AN23: =$AN$16 -> 0.4 | AO23: =IFERROR(ROUNDDOWN($AL23*(100%-($AR$11+AU23)),0),"") -> 0 | AP23: =AI23+AJ23 -> 0 | AQ23: =IFERROR(AO23-AI23-AJ23-AS23-AT23,"") -> 0 | AR23: =ROUNDDOWN(AO23/54,0) -> 0 | AS23: =IFERROR(AO23*$AT$11,"") -> 0 | AT23: =AO23*$AT$12 -> 0 | AV23: =IFERROR(AO23/AH23,0) -> 0 | AW23: =IFERROR(AQ23/AH23,0) -> 0 | AY23: =IFERROR(VLOOKUP(G23,選定!$C$3:$AG$100,28,FALSE),"0") -> 0 | AZ23: =C23 -> 0 | BA23: =D23 -> 0 | BB23: =IFERROR(VLOOKUP(G23,選定!$C$2:$AG$100,11,FALSE),"0") -> 0 | BC23: =IFERROR(VLOOKUP(G23,選定!$C$2:$AG$100,13,FALSE),"") | BD23: =IFERROR(VLOOKUP(G23,選定!$C$2:$AG$100,16,FALSE),"") | BE23: =IFERROR(VLOOKUP(G23,選定!$C$2:$AG$100,19,FALSE),"") | BF23: =IFERROR(VLOOKUP(G23,選定!$C$2:$AG$100,22,FALSE),"") | BG23: =L23 -> 0
A24: I | B24: =IF(C24="","",$C$5) | H24: =PRODUCT(I24,J24) -> 0 | J24: =IF(I24<>"",30,"") | L24: =SUM(M24:V24) -> 0 | W24: =($L24*$K24*$H24)/1000 -> 0 | X24: =$X$16 -> 30 | Y24: =ROUNDDOWN($W24*$X24,0) -> 0 | AA24: =IFERROR(VLOOKUP($G24,選定!$C$3:$AG$100,5,FALSE),0) -> 0 | AB24: =($AA24*$L24*$H24)/1000 -> 0 | AC24: =ROUNDDOWN($AB24*$AD24,0) -> 0 | AD24: =$AD$16 -> 30 | AE24: 3000 | AF24: 9 | AH24: =SUMIF($B$16:$B$45,$AG24,$L$16:$L$45) -> 0 | AI24: =SUMIF($B$16:$B$45,$AG24,LED計算式!$T$4:$T$33) -> 0 | AJ24: =SUMIF($B$16:$B$45,$AG24,LED計算式!$U$4) -> 0 | AK24: =IFERROR(AL24/54,"") -> 0 | AL24: =ROUNDDOWN((AI24+AJ24)/(100%-$AN24),0) -> 0 | AM24: =IFERROR($AL24-$AI24-$AJ24,"") -> 0 | AN24: =$AN$16 -> 0.4 | AO24: =IFERROR(ROUNDDOWN($AL24*(100%-($AR$11+AU24)),0),"") -> 0 | AP24: =AI24+AJ24 -> 0 | AQ24: =IFERROR(AO24-AI24-AJ24-AS24-AT24,"") -> 0 | AR24: =ROUNDDOWN(AO24/54,0) -> 0 | AS24: =IFERROR(AO24*$AT$11,"") -> 0 | AT24: =AO24*$AT$12 -> 0 | AV24: =IFERROR(AO24/AH24,0) -> 0 | AW24: =IFERROR(AQ24/AH24,0) -> 0 | AY24: =IFERROR(VLOOKUP(G24,選定!$C$3:$AG$100,28,FALSE),"0") -> 0 | AZ24: =C24 -> 0 | BA24: =D24 -> 0 | BB24: =IFERROR(VLOOKUP(G24,選定!$C$2:$AG$100,11,FALSE),"0") -> 0 | BC24: =IFERROR(VLOOKUP(G24,選定!$C$2:$AG$100,13,FALSE),"") | BD24: =IFERROR(VLOOKUP(G24,選定!$C$2:$AG$100,16,FALSE),"") | BE24: =IFERROR(VLOOKUP(G24,選定!$C$2:$AG$100,19,FALSE),"") | BF24: =IFERROR(VLOOKUP(G24,選定!$C$2:$AG$100,22,FALSE),"") | BG24: =L24 -> 0
A25: J | B25: =IF(C25="","",$C$5) | H25: =PRODUCT(I25,J25) -> 0 | J25: =IF(I25<>"",30,"") | L25: =SUM(M25:V25) -> 0 | W25: =($L25*$K25*$H25)/1000 -> 0 | X25: =$X$16 -> 30 | Y25: =ROUNDDOWN($W25*$X25,0) -> 0 | AA25: =IFERROR(VLOOKUP($G25,選定!$C$3:$AG$100,5,FALSE),0) -> 0 | AB25: =($AA25*$L25*$H25)/1000 -> 0 | AC25: =ROUNDDOWN($AB25*$AD25,0) -> 0 | AD25: =$AD$16 -> 30 | AE25: 3000 | AF25: 10 | AH25: =SUMIF($B$16:$B$45,$AG25,$L$16:$L$45) -> 0 | AI25: =SUMIF($B$16:$B$45,$AG25,LED計算式!$T$4:$T$33) -> 0 | AJ25: =SUMIF($B$16:$B$45,$AG25,LED計算式!$U$4) -> 0 | AK25: =IFERROR(AL25/54,"") -> 0 | AL25: =ROUNDDOWN((AI25+AJ25)/(100%-$AN25),0) -> 0 | AM25: =IFERROR($AL25-$AI25-$AJ25,"") -> 0 | AN25: =$AN$16 -> 0.4 | AO25: =IFERROR(ROUNDDOWN($AL25*(100%-($AR$11+AU25)),0),"") -> 0 | AP25: =AI25+AJ25 -> 0 | AQ25: =IFERROR(AO25-AI25-AJ25-AS25-AT25,"") -> 0 | AR25: =ROUNDDOWN(AO25/54,0) -> 0 | AS25: =IFERROR(AO25*$AT$11,"") -> 0 | AT25: =AO25*$AT$12 -> 0 | AV25: =IFERROR(AO25/AH25,0) -> 0 | AW25: =IFERROR(AQ25/AH25,0) -> 0 | AY25: =IFERROR(VLOOKUP(G25,選定!$C$3:$AG$100,28,FALSE),"0") -> 0 | AZ25: =C25 -> 0 | BA25: =D25 -> 0 | BB25: =IFERROR(VLOOKUP(G25,選定!$C$2:$AG$100,11,FALSE),"0") -> 0 | BC25: =IFERROR(VLOOKUP(G25,選定!$C$2:$AG$100,13,FALSE),"") | BD25: =IFERROR(VLOOKUP(G25,選定!$C$2:$AG$100,16,FALSE),"") | BE25: =IFERROR(VLOOKUP(G25,選定!$C$2:$AG$100,19,FALSE),"") | BF25: =IFERROR(VLOOKUP(G25,選定!$C$2:$AG$100,22,FALSE),"") | BG25: =L25 -> 0
A26: K | B26: =IF(C26="","",$C$5) | H26: =PRODUCT(I26,J26) -> 0 | J26: =IF(I26<>"",30,"") | L26: =SUM(M26:V26) -> 0 | W26: =($L26*$K26*$H26)/1000 -> 0 | X26: =$X$16 -> 30 | Y26: =ROUNDDOWN($W26*$X26,0) -> 0 | AA26: =IFERROR(VLOOKUP($G26,選定!$C$3:$AG$100,5,FALSE),0) -> 0 | AB26: =($AA26*$L26*$H26)/1000 -> 0 | AC26: =ROUNDDOWN($AB26*$AD26,0) -> 0 | AD26: =$AD$16 -> 30 | AE26: 3000 | AF26: 11 | AH26: =SUMIF($B$16:$B$45,$AG26,$L$16:$L$45) -> 0 | AI26: =SUMIF($B$16:$B$45,$AG26,LED計算式!$T$4:$T$33) -> 0 | AJ26: =SUMIF($B$16:$B$45,$AG26,LED計算式!$U$4) -> 0 | AK26: =IFERROR(AL26/54,"") -> 0 | AL26: =ROUNDDOWN((AI26+AJ26)/(100%-$AN26),0) -> 0 | AM26: =IFERROR($AL26-$AI26-$AJ26,"") -> 0 | AN26: =$AN$16 -> 0.4 | AO26: =IFERROR(ROUNDDOWN($AL26*(100%-($AR$11+AU26)),0),"") -> 0 | AP26: =AI26+AJ26 -> 0 | AQ26: =IFERROR(AO26-AI26-AJ26-AS26-AT26,"") -> 0 | AR26: =ROUNDDOWN(AO26/54,0) -> 0 | AS26: =IFERROR(AO26*$AT$11,"") -> 0 | AT26: =AO26*$AT$12 -> 0 | AV26: =IFERROR(AO26/AH26,0) -> 0 | AW26: =IFERROR(AQ26/AH26,0) -> 0 | AY26: =IFERROR(VLOOKUP(G26,選定!$C$3:$AG$100,28,FALSE),"0") -> 0 | AZ26: =C26 -> 0 | BA26: =D26 -> 0 | BB26: =IFERROR(VLOOKUP(G26,選定!$C$2:$AG$100,11,FALSE),"0") -> 0 | BC26: =IFERROR(VLOOKUP(G26,選定!$C$2:$AG$100,13,FALSE),"") | BD26: =IFERROR(VLOOKUP(G26,選定!$C$2:$AG$100,16,FALSE),"") | BE26: =IFERROR(VLOOKUP(G26,選定!$C$2:$AG$100,19,FALSE),"") | BF26: =IFERROR(VLOOKUP(G26,選定!$C$2:$AG$100,22,FALSE),"") | BG26: =L26 -> 0
A27: L | B27: =IF(C27="","",$C$5) | H27: =PRODUCT(I27,J27) -> 0 | J27: =IF(I27<>"",30,"") | L27: =SUM(M27:V27) -> 0 | W27: =($L27*$K27*$H27)/1000 -> 0 | X27: =$X$16 -> 30 | Y27: =ROUNDDOWN($W27*$X27,0) -> 0 | AA27: =IFERROR(VLOOKUP($G27,選定!$C$3:$AG$100,5,FALSE),0) -> 0 | AB27: =($AA27*$L27*$H27)/1000 -> 0 | AC27: =ROUNDDOWN($AB27*$AD27,0) -> 0 | AD27: =$AD$16 -> 30 | AE27: 3000 | AF27: 12 | AH27: =SUMIF($B$16:$B$45,$AG27,$L$16:$L$45) -> 0 | AI27: =SUMIF($B$16:$B$45,$AG27,LED計算式!$T$4:$T$33) -> 0 | AJ27: =SUMIF($B$16:$B$45,$AG27,LED計算式!$U$4) -> 0 | AK27: =IFERROR(AL27/54,"") -> 0 | AL27: =ROUNDDOWN((AI27+AJ27)/(100%-$AN27),0) -> 0 | AM27: =IFERROR($AL27-$AI27-$AJ27,"") -> 0 | AN27: =$AN$16 -> 0.4 | AO27: =IFERROR(ROUNDDOWN($AL27*(100%-($AR$11+AU27)),0),"") -> 0 | AP27: =AI27+AJ27 -> 0 | AQ27: =IFERROR(AO27-AI27-AJ27-AS27-AT27,"") -> 0 | AR27: =ROUNDDOWN(AO27/54,0) -> 0 | AS27: =IFERROR(AO27*$AT$11,"") -> 0 | AT27: =AO27*$AT$12 -> 0 | AV27: =IFERROR(AO27/AH27,0) -> 0 | AW27: =IFERROR(AQ27/AH27,0) -> 0 | AY27: =IFERROR(VLOOKUP(G27,選定!$C$3:$AG$100,28,FALSE),"0") -> 0 | AZ27: =C27 -> 0 | BA27: =D27 -> 0 | BB27: =IFERROR(VLOOKUP(G27,選定!$C$2:$AG$100,11,FALSE),"0") -> 0 | BC27: =IFERROR(VLOOKUP(G27,選定!$C$2:$AG$100,13,FALSE),"") | BD27: =IFERROR(VLOOKUP(G27,選定!$C$2:$AG$100,16,FALSE),"") | BE27: =IFERROR(VLOOKUP(G27,選定!$C$2:$AG$100,19,FALSE),"") | BF27: =IFERROR(VLOOKUP(G27,選定!$C$2:$AG$100,22,FALSE),"") | BG27: =L27 -> 0
A28: M | B28: =IF(C28="","",$C$5) | H28: =PRODUCT(I28,J28) -> 0 | J28: =IF(I28<>"",30,"") | L28: =SUM(M28:V28) -> 0 | W28: =($L28*$K28*$H28)/1000 -> 0 | X28: =$X$16 -> 30 | Y28: =ROUNDDOWN($W28*$X28,0) -> 0 | AA28: =IFERROR(VLOOKUP($G28,選定!$C$3:$AG$100,5,FALSE),0) -> 0 | AB28: =($AA28*$L28*$H28)/1000 -> 0 | AC28: =ROUNDDOWN($AB28*$AD28,0) -> 0 | AD28: =$AD$16 -> 30 | AE28: 3000 | AF28: 13 | AH28: =SUMIF($B$16:$B$45,$AG28,$L$16:$L$45) -> 0 | AI28: =SUMIF($B$16:$B$45,$AG28,LED計算式!$T$4:$T$33) -> 0 | AJ28: =SUMIF($B$16:$B$45,$AG28,LED計算式!$U$4) -> 0 | AK28: =IFERROR(AL28/54,"") -> 0 | AL28: =ROUNDDOWN((AI28+AJ28)/(100%-$AN28),0) -> 0 | AM28: =IFERROR($AL28-$AI28-$AJ28,"") -> 0 | AN28: =$AN$16 -> 0.4 | AO28: =IFERROR(ROUNDDOWN($AL28*(100%-($AR$11+AU28)),0),"") -> 0 | AP28: =AI28+AJ28 -> 0 | AQ28: =IFERROR(AO28-AI28-AJ28-AS28-AT28,"") -> 0 | AR28: =ROUNDDOWN(AO28/54,0) -> 0 | AS28: =IFERROR(AO28*$AT$11,"") -> 0 | AT28: =AO28*$AT$12 -> 0 | AV28: =IFERROR(AO28/AH28,0) -> 0 | AW28: =IFERROR(AQ28/AH28,0) -> 0 | AY28: =IFERROR(VLOOKUP(G28,選定!$C$3:$AG$100,28,FALSE),"0") -> 0 | AZ28: =C28 -> 0 | BA28: =D28 -> 0 | BB28: =IFERROR(VLOOKUP(G28,選定!$C$2:$AG$100,11,FALSE),"0") -> 0 | BC28: =IFERROR(VLOOKUP(G28,選定!$C$2:$AG$100,13,FALSE),"") | BD28: =IFERROR(VLOOKUP(G28,選定!$C$2:$AG$100,16,FALSE),"") | BE28: =IFERROR(VLOOKUP(G28,選定!$C$2:$AG$100,19,FALSE),"") | BF28: =IFERROR(VLOOKUP(G28,選定!$C$2:$AG$100,22,FALSE),"") | BG28: =L28 -> 0
A29: N | B29: =IF(C29="","",$C$5) | H29: =PRODUCT(I29,J29) -> 0 | J29: =IF(I29<>"",30,"") | L29: =SUM(M29:V29) -> 0 | W29: =($L29*$K29*$H29)/1000 -> 0 | X29: =$X$16 -> 30 | Y29: =ROUNDDOWN($W29*$X29,0) -> 0 | AA29: =IFERROR(VLOOKUP($G29,選定!$C$3:$AG$100,5,FALSE),0) -> 0 | AB29: =($AA29*$L29*$H29)/1000 -> 0 | AC29: =ROUNDDOWN($AB29*$AD29,0) -> 0 | AD29: =$AD$16 -> 30 | AE29: 3000 | AF29: 14 | AH29: =SUMIF($B$16:$B$45,$AG29,$L$16:$L$45) -> 0 | AI29: =SUMIF($B$16:$B$45,$AG29,LED計算式!$T$4:$T$33) -> 0 | AJ29: =SUMIF($B$16:$B$45,$AG29,LED計算式!$U$4) -> 0 | AK29: =IFERROR(AL29/54,"") -> 0 | AL29: =ROUNDDOWN((AI29+AJ29)/(100%-$AN29),0) -> 0 | AM29: =IFERROR($AL29-$AI29-$AJ29,"") -> 0 | AN29: =$AN$16 -> 0.4 | AO29: =IFERROR(ROUNDDOWN($AL29*(100%-($AR$11+AU29)),0),"") -> 0 | AP29: =AI29+AJ29 -> 0 | AQ29: =IFERROR(AO29-AI29-AJ29-AS29-AT29,"") -> 0 | AR29: =ROUNDDOWN(AO29/54,0) -> 0 | AS29: =IFERROR(AO29*$AT$11,"") -> 0 | AT29: =AO29*$AT$12 -> 0 | AV29: =IFERROR(AO29/AH29,0) -> 0 | AW29: =IFERROR(AQ29/AH29,0) -> 0 | AY29: =IFERROR(VLOOKUP(G29,選定!$C$3:$AG$100,28,FALSE),"0") -> 0 | AZ29: =C29 -> 0 | BA29: =D29 -> 0 | BB29: =IFERROR(VLOOKUP(G29,選定!$C$2:$AG$100,11,FALSE),"0") -> 0 | BC29: =IFERROR(VLOOKUP(G29,選定!$C$2:$AG$100,13,FALSE),"") | BD29: =IFERROR(VLOOKUP(G29,選定!$C$2:$AG$100,16,FALSE),"") | BE29: =IFERROR(VLOOKUP(G29,選定!$C$2:$AG$100,19,FALSE),"") | BF29: =IFERROR(VLOOKUP(G29,選定!$C$2:$AG$100,22,FALSE),"") | BG29: =L29 -> 0
A30: O | B30: =IF(C30="","",$C$5) | H30: =PRODUCT(I30,J30) -> 0 | J30: =IF(I30<>"",30,"") | L30: =SUM(M30:V30) -> 0 | W30: =($L30*$K30*$H30)/1000 -> 0 | X30: =$X$16 -> 30 | Y30: =ROUNDDOWN($W30*$X30,0) -> 0 | AA30: =IFERROR(VLOOKUP($G30,選定!$C$3:$AG$100,5,FALSE),0) -> 0 | AB30: =($AA30*$L30*$H30)/1000 -> 0 | AC30: =ROUNDDOWN($AB30*$AD30,0) -> 0 | AD30: =$AD$16 -> 30 | AE30: 3000 | AF30: 15 | AH30: =SUMIF($B$16:$B$45,$AG30,$L$16:$L$45) -> 0 | AI30: =SUMIF($B$16:$B$45,$AG30,LED計算式!$T$4:$T$33) -> 0 | AJ30: =SUMIF($B$16:$B$45,$AG30,LED計算式!$U$4) -> 0 | AK30: =IFERROR(AL30/54,"") -> 0 | AL30: =ROUNDDOWN((AI30+AJ30)/(100%-$AN30),0) -> 0 | AM30: =IFERROR($AL30-$AI30-$AJ30,"") -> 0 | AN30: =$AN$16 -> 0.4 | AO30: =IFERROR(ROUNDDOWN($AL30*(100%-($AR$11+AU30)),0),"") -> 0 | AP30: =AI30+AJ30 -> 0 | AQ30: =IFERROR(AO30-AI30-AJ30-AS30-AT30,"") -> 0 | AR30: =ROUNDDOWN(AO30/54,0) -> 0 | AS30: =IFERROR(AO30*$AT$11,"") -> 0 | AT30: =AO30*$AT$12 -> 0 | AV30: =IFERROR(AO30/AH30,0) -> 0 | AW30: =IFERROR(AQ30/AH30,0) -> 0 | AY30: =IFERROR(VLOOKUP(G30,選定!$C$3:$AG$100,28,FALSE),"0") -> 0 | AZ30: =C30 -> 0 | BA30: =D30 -> 0 | BB30: =IFERROR(VLOOKUP(G30,選定!$C$2:$AG$100,11,FALSE),"0") -> 0 | BC30: =IFERROR(VLOOKUP(G30,選定!$C$2:$AG$100,13,FALSE),"") | BD30: =IFERROR(VLOOKUP(G30,選定!$C$2:$AG$100,16,FALSE),"") | BE30: =IFERROR(VLOOKUP(G30,選定!$C$2:$AG$100,19,FALSE),"") | BF30: =IFERROR(VLOOKUP(G30,選定!$C$2:$AG$100,22,FALSE),"") | BG30: =L30 -> 0
A31: P | B31: =IF(C31="","",$C$5) | H31: =PRODUCT(I31,J31) -> 0 | J31: =IF(I31<>"",30,"") | L31: =SUM(M31:V31) -> 0 | W31: =($L31*$K31*$H31)/1000 -> 0 | X31: =$X$16 -> 30 | Y31: =ROUNDDOWN($W31*$X31,0) -> 0 | AA31: =IFERROR(VLOOKUP($G31,選定!$C$3:$AG$100,5,FALSE),0) -> 0 | AB31: =($AA31*$L31*$H31)/1000 -> 0 | AC31: =ROUNDDOWN($AB31*$AD31,0) -> 0 | AD31: =$AD$16 -> 30 | AE31: 3000 | AF31: 16 | AH31: =SUMIF($B$16:$B$45,$AG31,$L$16:$L$45) -> 0 | AI31: =SUMIF($B$16:$B$45,$AG31,LED計算式!$T$4:$T$33) -> 0 | AJ31: =SUMIF($B$16:$B$45,$AG31,LED計算式!$U$4) -> 0 | AK31: =IFERROR(AL31/54,"") -> 0 | AL31: =ROUNDDOWN((AI31+AJ31)/(100%-$AN31),0) -> 0 | AM31: =IFERROR($AL31-$AI31-$AJ31,"") -> 0 | AN31: =$AN$16 -> 0.4 | AO31: =IFERROR(ROUNDDOWN($AL31*(100%-($AR$11+AU31)),0),"") -> 0 | AP31: =AI31+AJ31 -> 0 | AQ31: =IFERROR(AO31-AI31-AJ31-AS31-AT31,"") -> 0 | AR31: =ROUNDDOWN(AO31/54,0) -> 0 | AS31: =IFERROR(AO31*$AT$11,"") -> 0 | AT31: =AO31*$AT$12 -> 0 | AV31: =IFERROR(AO31/AH31,0) -> 0 | AW31: =IFERROR(AQ31/AH31,0) -> 0 | AY31: =IFERROR(VLOOKUP(G31,選定!$C$3:$AG$100,28,FALSE),"0") -> 0 | AZ31: =C31 -> 0 | BA31: =D31 -> 0 | BB31: =IFERROR(VLOOKUP(G31,選定!$C$2:$AG$100,11,FALSE),"0") -> 0 | BC31: =IFERROR(VLOOKUP(G31,選定!$C$2:$AG$100,13,FALSE),"") | BD31: =IFERROR(VLOOKUP(G31,選定!$C$2:$AG$100,16,FALSE),"") | BE31: =IFERROR(VLOOKUP(G31,選定!$C$2:$AG$100,19,FALSE),"") | BF31: =IFERROR(VLOOKUP(G31,選定!$C$2:$AG$100,22,FALSE),"") | BG31: =L31 -> 0
... A45: AD | B45: =IF(C45="","",$C$5) | H45: =PRODUCT(I45,J45) -> 0 | J45: =IF(I45<>"",30,"") | L45: =SUM(M45:V45) -> 0 | W45: =($L45*$K45*$H45)/1000 -> 0 | X45: =$X$16 -> 30 | Y45: =ROUNDDOWN($W45*$X45,0) -> 0 | AA45: =IFERROR(VLOOKUP($G45,選定!$C$3:$AG$100,5,FALSE),0) -> 0 | AB45: =($AA45*$L45*$H45)/1000 -> 0 | AC45: =ROUNDDOWN($AB45*$AD45,0) -> 0 | AD45: =$AD$16 -> 30 | AE45: 3000 | AF45: 30 | AH45: =SUMIF($B$16:$B$45,$AG45,$L$16:$L$45) -> 0 | AI45: =SUMIF($B$16:$B$45,$AG45,LED計算式!$T$4:$T$33) -> 0 | AJ45: =SUMIF($B$16:$B$45,$AG45,LED計算式!$U$4) -> 0 | AK45: =IFERROR(AL45/54,"") -> 0 | AL45: =ROUNDDOWN((AI45+AJ45)/(100%-$AN45),0) -> 0 | AM45: =IFERROR($AL45-$AI45-$AJ45,"") -> 0 | AN45: =$AN$16 -> 0.4 | AO45: =IFERROR(ROUNDDOWN($AL45*(100%-($AR$11+AU45)),0),"") -> 0 | AP45: =AI45+AJ45 -> 0 | AQ45: =IFERROR(AO45-AI45-AJ45-AS45-AT45,"") -> 0 | AR45: =ROUNDDOWN(AO45/54,0) -> 0 | AS45: =IFERROR(AO45*$AT$11,"") -> 0 | AT45: =AO45*$AT$12 -> 0 | AV45: =IFERROR(AO45/AH45,0) -> 0 | AW45: =IFERROR(AQ45/AH45,0) -> 0 | AY45: =IFERROR(VLOOKUP(G45,選定!$C$3:$AG$100,28,FALSE),"0") -> 0 | AZ45: =C45 -> 0 | BA45: =D45 -> 0 | BB45: =IFERROR(VLOOKUP(G45,選定!$C$2:$AG$100,11,FALSE),"0") -> 0 | BC45: =IFERROR(VLOOKUP(G45,選定!$C$2:$AG$100,13,FALSE),"") | BD45: =IFERROR(VLOOKUP(G45,選定!$C$2:$AG$100,16,FALSE),"") | BE45: =IFERROR(VLOOKUP(G45,選定!$C$2:$AG$100,19,FALSE),"") | BF45: =IFERROR(VLOOKUP(G45,選定!$C$2:$AG$100,22,FALSE),"") | BG45: =L45 -> 0
B47: 【LED済み箇所】
B48: 物件名 | C48: 試算エリア | D48: 照明種別 | E48: 現調備考 | L48: 電球数 | M48: 1階 | N48: 2階 | O48: 3階 | P48: 4階 | Q48: 5階 | R48: 6階 | S48: 7階 | T48: 8階 | U48: 9階 | V48: 10階 | W48: 除外理由 | AC48: アドバイス
A49: 1 | B49: =IF(C49="","",$C$5) | L49: =SUM(M49:V49) -> 0
A50: 2 | B50: =IF(C50="","",$C$5) | L50: =SUM(M50:V50) -> 0
A51: 3 | B51: =IF(C51="","",$C$5) | L51: =SUM(M51:V51) -> 0
A52: 4 | B52: =IF(C52="","",$C$5) | L52: =SUM(M52:V52) -> 0
A53: 5 | B53: =IF(C53="","",$C$5) | L53: =SUM(M53:V53) -> 0
A54: 6 | B54: =IF(C54="","",$C$5) | L54: =SUM(M54:V54) -> 0
A55: 7 | B55: =IF(C55="","",$C$5) | L55: =SUM(M55:V55) -> 0
A56: 8 | B56: =IF(C56="","",$C$5) | L56: =SUM(M56:V56) -> 0
A57: 9 | B57: =IF(C57="","",$C$5) | L57: =SUM(M57:V57) -> 0
A58: 10 | B58: =IF(C58="","",$C$5) | L58: =SUM(M58:V58) -> 0
A59: 11 | B59: =IF(C59="","",$C$5) | L59: =SUM(M59:V59) -> 0
A60: 12 | B60: =IF(C60="","",$C$5) | L60: =SUM(M60:V60) -> 0
W62: 【テンプレ】 | AC62: 【テンプレ】
W63: 通常時不点灯で電気代削減が見込めないため除外
W64: LED照明器具を導入済みのため除外
W65: 管球のみLED照明に交換済み、削減効率が悪いため除外 | AC65: 器具劣化が激しいため、交換をご希望の場合は要相談
W66: 特殊器具のため一度見積より除外 | AC66: 商談時にご説明させて頂きます
AC67: 器具自体が古いため、器具交換を推奨します。ご希望の場合は要相談

Sheet 見積チェック
A1: LED見積作成チェックシート
A3: ✓ | B3: No. | C3: チェック項目 | D3: 備考
B4: 1 | C4: ◎ 器具の大きさ
B5: 2 | C5: ◎ 防滴か否か確認
B6: 3 | C6: ◎ 色温度
B7: 4 | C7: ◎ 見積書のシートの別置作業がない場合非表示
B8: 5 | C8: 消費電力を入れてない
B9: 6 | C9: 高所作業か否か
B10: 7 | C10: 照明種別が多い時(15個以上)見積反映
B11: 8 | C11: 除外理由記入漏れ
B12: 9 | C12: 表紙の確認(連名などの確認)
B13: 10 | C13: 工事の特記事項の記入→現調シートの内容を反映
B14: 11 | C14: W数(安定器が入ってないケースが多い)
B15: 12 | C15: L19とAH14がイコールか(数量の確認)
A17: ✕ チェックを全削除
A18: ※ チェックボックスを手動でクリアして次の案件へ

Sheet ①表紙
A2: =☆入力!C5 -> 0
A25: =代理店入力用!N3 -> 株式会社ニッショー | I25: バズエリア株式会社
A26: =代理店入力用!N4&代理店入力用!N5 | I26: 〒151-0071 東京都渋谷区本町2-6-3 D'sVARIE初台ビル3F
A27: ="TEL： "&代理店入力用!N6 -> TEL： 管理担当営業所へお問い合わせ下さい。 | I27: TEL：03-4586-6561 FAX：03-6812-9253
A28: ="担当："&代理店入力用!N7 -> 担当：物件担当者 | N28: 1

Sheet ②LEDをいま検討しないといけない理由
A1: ～LEDをいま検討しないといけない理由～
B2: ①蛍光灯・白熱電球がなくなってしまう為
C6: 電力量料金（円）＝消費電力（kW）×点灯時間（時間）×電力量単価（円kW）
C8: ◇電力量単価は、頂いた電力明細に準ずる単価で計算しておりますが、ご提出頂けていない場合には地域電力の単価を基にして概算にて算出しております。
B10: 2、交換コストの算出方法
C12: 管理会社からの電球が切れた場合の1球あたりの交換費用を基に算出しております。
C13: ◇本シミュレーションでは、1球あたり、 | M13: =☆入力!AR9 -> 0 | P13: にて計算しております。管理会社に確認出来ていない場合には2,500円/球にて算出しております。
C14: ※全国不動産管理会社様の相場は2,000円～3,000円、高い会社で5,000円となっております。
B16: 3、導入パターン
C18: 一括購入 | Q18: or | Z18: リース
B21: ②蛍光灯→品薄、LED→原材料高騰・円安でそれぞれ値上がり続けている為
B24: 4、非常用専用照明に関して
C26: 弊社のご提案では、コストメリットを出して利回りを良くすることを重視して作成しておりますので、非常用専用照明（非常時にか点灯しない照明）は基本的に見積から除外をしております。
C27: ただ、非常用専用照明も消防法上定期的なバッテリー交換が必要で、各メーカーLEDに切り替えがなされておりますので次回交換時にはLED化が必須となります。
C28: 交換をする場合には別途、御見積を致しますのでお申しつけください。
B30: 5、器具デザインカスタマイズに関して
AY32: 2

Sheet ③LED導入のメリット
B2: LED照明導入のメリット
O31: 3

Sheet ②前a
A1: ～現地調査結果および既存照明にかかる10年間のランニングコスト～
R3: 既存照明の場合 | AF3: 既存照明に対してかかっている10年間のランニングコスト
A6: No | C6: =LED計算式!M32 -> 試算エリア | G6: 照明種別 | L6: 月間点灯 | P6: 数量 | R6: 消費電力 | U6: 電力量 | Y6: 使用料(月) | AF6: ①10年間でかかる電気料金の総額＝ | AS6: =Y39*120 -> 0
A8: 1 | C8: =IF($C$6=☆入力!$B$15,☆入力!$B16,☆入力!$C16) -> 0 | G8: =☆入力!D16 -> 0 | L8: =☆入力!H16 -> 0 | P8: =☆入力!L16 -> 0 | R8: =☆入力!K16 -> 0 | U8: =☆入力!W16 -> 0 | Y8: =☆入力!Y16 -> 0 | AG8: 計算式：毎月の電気料金 | AO8: =Y39 -> 0 | AS8: ×10年間（120ヵ月）
A9: 2 | C9: =IF($C$6=☆入力!$B$15,☆入力!$B17,☆入力!$C17) -> 0 | G9: =☆入力!D17 -> 0 | L9: =☆入力!H17 -> 0 | P9: =☆入力!L17 -> 0 | R9: =☆入力!K17 -> 0 | U9: =☆入力!W17 -> 0 | Y9: =☆入力!Y17 -> 0 | AS9: +
A10: 3 | C10: =IF($C$6=☆入力!$B$15,☆入力!$B18,☆入力!$C18) -> 0 | G10: =☆入力!D18 -> 0 | L10: =☆入力!H18 -> 0 | P10: =☆入力!L18 -> 0 | R10: =☆入力!K18 -> 0 | U10: =☆入力!W18 -> 0 | Y10: =☆入力!Y18 -> 0
A11: 4 | C11: =IF($C$6=☆入力!$B$15,☆入力!$B19,☆入力!$C19) -> 0 | G11: =☆入力!D19 -> 0 | L11: =☆入力!H19 -> 0 | P11: =☆入力!L19 -> 0 | R11: =☆入力!K19 -> 0 | U11: =☆入力!W19 -> 0 | Y11: =☆入力!Y19 -> 0 | AF11: ②10年間でかかる白熱球の交換コストの総額＝
A12: 5 | C12: =IF($C$6=☆入力!$B$15,☆入力!$B20,☆入力!$C20) -> 0 | G12: =☆入力!D20 -> 0 | L12: =☆入力!H20 -> 0 | P12: =☆入力!L20 -> 0 | R12: =☆入力!K20 -> 0 | U12: =☆入力!W20 -> 0 | Y12: =☆入力!Y20 -> 0
A13: 6 | C13: =IF($C$6=☆入力!$B$15,☆入力!$B21,☆入力!$C21) -> 0 | G13: =☆入力!D21 -> 0 | L13: =☆入力!H21 -> 0 | P13: =☆入力!L21 -> 0 | R13: =☆入力!K21 -> 0 | U13: =☆入力!W21 -> 0 | Y13: =☆入力!Y21 -> 0 | AS13: =(AN15*☆入力!AR9*7)+(AN16*☆入力!AR9*15) -> 0
A14: 7 | C14: =IF($C$6=☆入力!$B$15,☆入力!$B22,☆入力!$C22) -> 0 | G14: =☆入力!D22 -> 0 | L14: =☆入力!H22 -> 0 | P14: =☆入力!L22 -> 0 | R14: =☆入力!K22 -> 0 | U14: =☆入力!W22 -> 0 | Y14: =☆入力!Y22 -> 0
A15: 8 | C15: =IF($C$6=☆入力!$B$15,☆入力!$B23,☆入力!$C23) -> 0 | G15: =☆入力!D23 -> 0 | L15: =☆入力!H23 -> 0 | P15: =☆入力!L23 -> 0 | R15: =☆入力!K23 -> 0 | U15: =☆入力!W23 -> 0 | Y15: =☆入力!Y23 -> 0 | AG15: 月間点灯360hの場合： | AN15: =LED計算式!N16 -> 0 | AQ15: ="× "&TEXT(☆入力!AR9,"#,#00")&"円（※1）× 7回（※2）" -> × 00円（※1）× 7回（※2）
A16: 9 | C16: =IF($C$6=☆入力!$B$15,☆入力!$B24,☆入力!$C24) -> 0 | G16: =☆入力!D24 -> 0 | L16: =☆入力!H24 -> 0 | P16: =☆入力!L24 -> 0 | R16: =☆入力!K24 -> 0 | U16: =☆入力!W24 -> 0 | Y16: =☆入力!Y24 -> 0 | AG16: 月間点灯720hの場合： | AN16: =LED計算式!N17 -> 0 | AQ16: ="× "&TEXT(☆入力!AR9,"#,#00")&"円（※1）× 15回（※3）" -> × 00円（※1）× 15回（※3）
A17: 10 | C17: =IF($C$6=☆入力!$B$15,☆入力!$B25,☆入力!$C25) -> 0 | G17: =☆入力!D25 -> 0 | L17: =☆入力!H25 -> 0 | P17: =☆入力!L25 -> 0 | R17: =☆入力!K25 -> 0 | U17: =☆入力!W25 -> 0 | Y17: =☆入力!Y25 -> 0 | AG17: ="(※1)白熱球の1球あたりの交換費用⇒"&TEXT(☆入力!AR9,"#,#00")&"円で計算(管理会社に委託している場合の平均)" -> (※1)白熱球の1球あたりの交換費用⇒00円で計算(管理会社に委託している場合の平均)
A18: 11 | C18: =IF($C$6=☆入力!$B$15,☆入力!$B26,☆入力!$C26) -> 0 | G18: =☆入力!D26 -> 0 | L18: =☆入力!H26 -> 0 | P18: =☆入力!L26 -> 0 | R18: =☆入力!K26 -> 0 | U18: =☆入力!W26 -> 0 | Y18: =☆入力!Y26 -> 0 | AG18: (※2)月間点灯360時間の場合⇒電球寿命を1年5ヵ月として10年間で7回の交換を想定して算出
A19: 12 | C19: =IF($C$6=☆入力!$B$15,☆入力!$B27,☆入力!$C27) -> 0 | G19: =☆入力!D27 -> 0 | L19: =☆入力!H27 -> 0 | P19: =☆入力!L27 -> 0 | R19: =☆入力!K27 -> 0 | U19: =☆入力!W27 -> 0 | Y19: =☆入力!Y27 -> 0 | AG19: (※3)月間点灯720時間の場合⇒電球寿命を8ヵ月として10年間で15回の交換を想定して算出
A20: 13 | C20: =IF($C$6=☆入力!$B$15,☆入力!$B28,☆入力!$C28) -> 0 | G20: =☆入力!D28 -> 0 | L20: =☆入力!H28 -> 0 | P20: =☆入力!L28 -> 0 | R20: =☆入力!K28 -> 0 | U20: =☆入力!W28 -> 0 | Y20: =☆入力!Y28 -> 0 | AS20: +
A21: 14 | C21: =IF($C$6=☆入力!$B$15,☆入力!$B29,☆入力!$C29) -> 0 | G21: =☆入力!D29 -> 0 | L21: =☆入力!H29 -> 0 | P21: =☆入力!L29 -> 0 | R21: =☆入力!K29 -> 0 | U21: =☆入力!W29 -> 0 | Y21: =☆入力!Y29 -> 0
A22: 15 | C22: =IF($C$6=☆入力!$B$15,☆入力!$B30,☆入力!$C30) -> 0 | G22: =☆入力!D30 -> 0 | L22: =☆入力!H30 -> 0 | P22: =☆入力!L30 -> 0 | R22: =☆入力!K30 -> 0 | U22: =☆入力!W30 -> 0 | Y22: =☆入力!Y30 -> 0 | AF22: ③10年間でかかる非常灯のバッテリー交換コストの総額＝
A23: 16 | C23: =IF($C$6=☆入力!$B$15,☆入力!$B31,☆入力!$C31) -> 0 | G23: =☆入力!D31 -> 0 | L23: =☆入力!H31 -> 0 | P23: =☆入力!L31 -> 0 | R23: =☆入力!K31 -> 0 | U23: =☆入力!W31 -> 0 | Y23: =☆入力!Y31 -> 0
A24: 17 | C24: =IF($C$6=☆入力!$B$15,☆入力!$B32,☆入力!$C32) -> 0 | G24: =☆入力!D32 -> 0 | L24: =☆入力!H32 -> 0 | P24: =☆入力!L32 -> 0 | R24: =☆入力!K32 -> 0 | U24: =☆入力!W32 -> 0 | Y24: =☆入力!Y32 -> 0 | AS24: =☆入力!L12*10000*2 -> 0
A25: 18 | C25: =IF($C$6=☆入力!$B$15,☆入力!$B33,☆入力!$C33) -> 0 | G25: =☆入力!D33 -> 0 | L25: =☆入力!H33 -> 0 | P25: =☆入力!L33 -> 0 | R25: =☆入力!K33 -> 0 | U25: =☆入力!W33 -> 0 | Y25: =☆入力!Y33 -> 0
A26: 19 | C26: =IF($C$6=☆入力!$B$15,☆入力!$B34,☆入力!$C34) -> 0 | G26: =☆入力!D34 -> 0 | L26: =☆入力!H34 -> 0 | P26: =☆入力!L34 -> 0 | R26: =☆入力!K34 -> 0 | U26: =☆入力!W34 -> 0 | Y26: =☆入力!Y34 -> 0 | AG26: 計算式：非常照明の総数 | AO26: =☆入力!L12 -> 0 | AR26: ×10,000円（※4）×2回（※5）
A27: 20 | C27: =IF($C$6=☆入力!$B$15,☆入力!$B35,☆入力!$C35) -> 0 | G27: =☆入力!D35 -> 0 | L27: =☆入力!H35 -> 0 | P27: =☆入力!L35 -> 0 | R27: =☆入力!K35 -> 0 | U27: =☆入力!W35 -> 0 | Y27: =☆入力!Y35 -> 0
A28: 21 | C28: =IF($C$6=☆入力!$B$15,☆入力!$B36,☆入力!$C36) -> 0 | G28: =☆入力!D36 -> 0 | L28: =☆入力!H36 -> 0 | P28: =☆入力!L36 -> 0 | R28: =☆入力!K36 -> 0 | U28: =☆入力!W36 -> 0 | Y28: =☆入力!Y36 -> 0 | AG28: (※4)非常灯のバッテリー交換費用⇒10,000円で計算(管理会社に委託している場合の平均)
A29: 22 | C29: =IF($C$6=☆入力!$B$15,☆入力!$B37,☆入力!$C37) -> 0 | G29: =☆入力!D37 -> 0 | L29: =☆入力!H37 -> 0 | P29: =☆入力!L37 -> 0 | R29: =☆入力!K37 -> 0 | U29: =☆入力!W37 -> 0 | Y29: =☆入力!Y37 -> 0 | AG29: (※5)内蔵バッテリーの寿命⇒5年として10年間で2回交換することを想定して算出
A30: 23 | C30: =IF($C$6=☆入力!$B$15,☆入力!$B38,☆入力!$C38) -> 0 | G30: =☆入力!D38 -> 0 | L30: =☆入力!H38 -> 0 | P30: =☆入力!L38 -> 0 | R30: =☆入力!K38 -> 0 | U30: =☆入力!W38 -> 0 | Y30: =☆入力!Y38 -> 0
A31: 24 | C31: =IF($C$6=☆入力!$B$15,☆入力!$B39,☆入力!$C39) -> 0 | G31: =☆入力!D39 -> 0 | L31: =☆入力!H39 -> 0 | P31: =☆入力!L39 -> 0 | R31: =☆入力!K39 -> 0 | U31: =☆入力!W39 -> 0 | Y31: =☆入力!Y39 -> 0
A32: 25 | C32: =IF($C$6=☆入力!$B$15,☆入力!$B40,☆入力!$C40) -> 0 | G32: =☆入力!D40 -> 0 | L32: =☆入力!H40 -> 0 | P32: =☆入力!L40 -> 0 | R32: =☆入力!K40 -> 0 | U32: =☆入力!W40 -> 0 | Y32: =☆入力!Y40 -> 0
A33: 26 | C33: =IF($C$6=☆入力!$B$15,☆入力!$B41,☆入力!$C41) -> 0 | G33: =☆入力!D41 -> 0 | L33: =☆入力!H41 -> 0 | P33: =☆入力!L41 -> 0 | R33: =☆入力!K41 -> 0 | U33: =☆入力!W41 -> 0 | Y33: =☆入力!Y41 -> 0
A34: 27 | C34: =IF($C$6=☆入力!$B$15,☆入力!$B42,☆入力!$C42) -> 0 | G34: =☆入力!D42 -> 0 | L34: =☆入力!H42 -> 0 | P34: =☆入力!L42 -> 0 | R34: =☆入力!K42 -> 0 | U34: =☆入力!W42 -> 0 | Y34: =☆入力!Y42 -> 0
A35: 28 | C35: =IF($C$6=☆入力!$B$15,☆入力!$B43,☆入力!$C43) -> 0 | G35: =☆入力!D43 -> 0 | L35: =☆入力!H43 -> 0 | P35: =☆入力!L43 -> 0 | R35: =☆入力!K43 -> 0 | U35: =☆入力!W43 -> 0 | Y35: =☆入力!Y43 -> 0
A36: 29 | C36: =IF($C$6=☆入力!$B$15,☆入力!$B44,☆入力!$C44) -> 0 | G36: =☆入力!D44 -> 0 | L36: =☆入力!H44 -> 0 | P36: =☆入力!L44 -> 0 | R36: =☆入力!K44 -> 0 | U36: =☆入力!W44 -> 0 | Y36: =☆入力!Y44 -> 0
A37: 30 | C37: =IF($C$6=☆入力!$B$15,☆入力!$B45,☆入力!$C45) -> 0 | G37: =☆入力!D45 -> 0 | L37: =☆入力!H45 -> 0 | P37: =☆入力!L45 -> 0 | R37: =☆入力!K45 -> 0 | U37: =☆入力!W45 -> 0 | Y37: =☆入力!Y45 -> 0
K38: ※電気代の中で「照明にかかっている電気代」のみを算出しております
K39: 合計 | P39: =SUM(P8:Q37) -> 0 | R39: - | U39: =SUM(U8:X37) -> 0 | Y39: =SUM(Y8:AB37) -> 0 | AF39: ★10年間で既存照明に対してかかるランニングコストの総額＝
AS41: =AS6+AS13+AS24 -> 0
BD44: 3

Sheet ③後a
A1: ～LED照明導入後の削減費用および10年間のランニングコスト～
R3: LED照明交換後 | AF3: LED照明に交換した場合の10年間のランニングコスト
A6: No | C6: =LED計算式!M32 -> 試算エリア | G6: 照明種別 | L6: 月間点灯 | P6: 数量 | R6: 消費電力 | U6: 電力量 | Y6: 使用料(月) | AF6: ①10年間でかかる電気料金の総額＝ | AS6: =Y39*120 -> 0
A8: 1 | C8: =IF($C$6=☆入力!$B$15,☆入力!$B16,☆入力!$C16) -> 0 | G8: =☆入力!D16 -> 0 | L8: =☆入力!H16 -> 0 | P8: =☆入力!L16 -> 0 | R8: =☆入力!AA16 -> 0 | U8: =☆入力!AB16 -> 0 | Y8: =☆入力!AC16 -> 0 | AG8: 計算式：毎月の電気料金 | AO8: =Y39 -> 0 | AS8: ×10年間（120ヵ月）
A9: 2 | C9: =IF($C$6=☆入力!$B$15,☆入力!$B17,☆入力!$C17) -> 0 | G9: =☆入力!D17 -> 0 | L9: =☆入力!H17 -> 0 | P9: =☆入力!L17 -> 0 | R9: =☆入力!AA17 -> 0 | U9: =☆入力!AB17 -> 0 | Y9: =☆入力!AC17 -> 0 | AS9: +
A10: 3 | C10: =IF($C$6=☆入力!$B$15,☆入力!$B18,☆入力!$C18) -> 0 | G10: =☆入力!D18 -> 0 | L10: =☆入力!H18 -> 0 | P10: =☆入力!L18 -> 0 | R10: =☆入力!AA18 -> 0 | U10: =☆入力!AB18 -> 0 | Y10: =☆入力!AC18 -> 0 | BF10: ※②が「0円」場合には左に移動してください
A11: 4 | C11: =IF($C$6=☆入力!$B$15,☆入力!$B19,☆入力!$C19) -> 0 | G11: =☆入力!D19 -> 0 | L11: =☆入力!H19 -> 0 | P11: =☆入力!L19 -> 0 | R11: =☆入力!AA19 -> 0 | U11: =☆入力!AB19 -> 0 | Y11: =☆入力!AC19 -> 0 | AF11: ②10年間でかかるLED照明の交換コストの総額＝
A12: 5 | C12: =IF($C$6=☆入力!$B$15,☆入力!$B20,☆入力!$C20) -> 0 | G12: =☆入力!D20 -> 0 | L12: =☆入力!H20 -> 0 | P12: =☆入力!L20 -> 0 | R12: =☆入力!AA20 -> 0 | U12: =☆入力!AB20 -> 0 | Y12: =☆入力!AC20 -> 0
A13: 6 | C13: =IF($C$6=☆入力!$B$15,☆入力!$B21,☆入力!$C21) -> 0 | G13: =☆入力!D21 -> 0 | L13: =☆入力!H21 -> 0 | P13: =☆入力!L21 -> 0 | R13: =☆入力!AA21 -> 0 | U13: =☆入力!AB21 -> 0 | Y13: =☆入力!AC21 -> 0 | AS13: =AN16*3000*1 -> 0
A14: 7 | C14: =IF($C$6=☆入力!$B$15,☆入力!$B22,☆入力!$C22) -> 0 | G14: =☆入力!D22 -> 0 | L14: =☆入力!H22 -> 0 | P14: =☆入力!L22 -> 0 | R14: =☆入力!AA22 -> 0 | U14: =☆入力!AB22 -> 0 | Y14: =☆入力!AC22 -> 0
A15: 8 | C15: =IF($C$6=☆入力!$B$15,☆入力!$B23,☆入力!$C23) -> 0 | G15: =☆入力!D23 -> 0 | L15: =☆入力!H23 -> 0 | P15: =☆入力!L23 -> 0 | R15: =☆入力!AA23 -> 0 | U15: =☆入力!AB23 -> 0 | Y15: =☆入力!AC23 -> 0 | AG15: 月間点灯360hの場合： | AN15: =LED計算式!N16 -> 0 | AQ15: ="× "&TEXT(☆入力!AR9,"#,#00")&"円（※1）× 0回（※2）" -> × 00円（※1）× 0回（※2）
A16: 9 | C16: =IF($C$6=☆入力!$B$15,☆入力!$B24,☆入力!$C24) -> 0 | G16: =☆入力!D24 -> 0 | L16: =☆入力!H24 -> 0 | P16: =☆入力!L24 -> 0 | R16: =☆入力!AA24 -> 0 | U16: =☆入力!AB24 -> 0 | Y16: =☆入力!AC24 -> 0 | AG16: 月間点灯720hの場合： | AN16: =LED計算式!N17 -> 0 | AQ16: × 3,000円（※1）× 1回（※3）
A17: 10 | C17: =IF($C$6=☆入力!$B$15,☆入力!$B25,☆入力!$C25) -> 0 | G17: =☆入力!D25 -> 0 | L17: =☆入力!H25 -> 0 | P17: =☆入力!L25 -> 0 | R17: =☆入力!AA25 -> 0 | U17: =☆入力!AB25 -> 0 | Y17: =☆入力!AC25 -> 0 | AG17: (※1)月間点灯720時間の場合、光源部分の交換を3,000円/球として算出
A18: 11 | C18: =IF($C$6=☆入力!$B$15,☆入力!$B26,☆入力!$C26) -> 0 | G18: =☆入力!D26 -> 0 | L18: =☆入力!H26 -> 0 | P18: =☆入力!L26 -> 0 | R18: =☆入力!AA26 -> 0 | U18: =☆入力!AB26 -> 0 | Y18: =☆入力!AC26 -> 0 | AG18: (※3)月間点灯720時間の場合、10年間で1回の光源部分交換を想定して算出
A19: 12 | C19: =IF($C$6=☆入力!$B$15,☆入力!$B27,☆入力!$C27) -> 0 | G19: =☆入力!D27 -> 0 | L19: =☆入力!H27 -> 0 | P19: =☆入力!L27 -> 0 | R19: =☆入力!AA27 -> 0 | U19: =☆入力!AB27 -> 0 | Y19: =☆入力!AC27 -> 0
A20: 13 | C20: =IF($C$6=☆入力!$B$15,☆入力!$B28,☆入力!$C28) -> 0 | G20: =☆入力!D28 -> 0 | L20: =☆入力!H28 -> 0 | P20: =☆入力!L28 -> 0 | R20: =☆入力!AA28 -> 0 | U20: =☆入力!AB28 -> 0 | Y20: =☆入力!AC28 -> 0 | AS20: +
A21: 14 | C21: =IF($C$6=☆入力!$B$15,☆入力!$B29,☆入力!$C29) -> 0 | G21: =☆入力!D29 -> 0 | L21: =☆入力!H29 -> 0 | P21: =☆入力!L29 -> 0 | R21: =☆入力!AA29 -> 0 | U21: =☆入力!AB29 -> 0 | Y21: =☆入力!AC29 -> 0
A22: 15 | C22: =IF($C$6=☆入力!$B$15,☆入力!$B30,☆入力!$C30) -> 0 | G22: =☆入力!D30 -> 0 | L22: =☆入力!H30 -> 0 | P22: =☆入力!L30 -> 0 | R22: =☆入力!AA30 -> 0 | U22: =☆入力!AB30 -> 0 | Y22: =☆入力!AC30 -> 0 | AF22: ③10年間でかかる非常灯のバッテリー交換コストの総額＝
A23: 16 | C23: =IF($C$6=☆入力!$B$15,☆入力!$B31,☆入力!$C31) -> 0 | G23: =☆入力!D31 -> 0 | L23: =☆入力!H31 -> 0 | P23: =☆入力!L31 -> 0 | R23: =☆入力!AA31 -> 0 | U23: =☆入力!AB31 -> 0 | Y23: =☆入力!AC31 -> 0
A24: 17 | C24: =IF($C$6=☆入力!$B$15,☆入力!$B32,☆入力!$C32) -> 0 | G24: =☆入力!D32 -> 0 | L24: =☆入力!H32 -> 0 | P24: =☆入力!L32 -> 0 | R24: =☆入力!AA32 -> 0 | U24: =☆入力!AB32 -> 0 | Y24: =☆入力!AC32 -> 0 | AS24: =☆入力!L12*8000*2 -> 0
A25: 18 | C25: =IF($C$6=☆入力!$B$15,☆入力!$B33,☆入力!$C33) -> 0 | G25: =☆入力!D33 -> 0 | L25: =☆入力!H33 -> 0 | P25: =☆入力!L33 -> 0 | R25: =☆入力!AA33 -> 0 | U25: =☆入力!AB33 -> 0 | Y25: =☆入力!AC33 -> 0
A26: 19 | C26: =IF($C$6=☆入力!$B$15,☆入力!$B34,☆入力!$C34) -> 0 | G26: =☆入力!D34 -> 0 | L26: =☆入力!H34 -> 0 | P26: =☆入力!L34 -> 0 | R26: =☆入力!AA34 -> 0 | U26: =☆入力!AB34 -> 0 | Y26: =☆入力!AC34 -> 0 | AG26: 計算式：非常照明の総数 | AO26: =☆入力!L12 -> 0 | AR26: ×8,000円（※4）×2回（※5）
A27: 20 | C27: =IF($C$6=☆入力!$B$15,☆入力!$B35,☆入力!$C35) -> 0 | G27: =☆入力!D35 -> 0 | L27: =☆入力!H35 -> 0 | P27: =☆入力!L35 -> 0 | R27: =☆入力!AA35 -> 0 | U27: =☆入力!AB35 -> 0 | Y27: =☆入力!AC35 -> 0
A28: 21 | C28: =IF($C$6=☆入力!$B$15,☆入力!$B36,☆入力!$C36) -> 0 | G28: =☆入力!D36 -> 0 | L28: =☆入力!H36 -> 0 | P28: =☆入力!L36 -> 0 | R28: =☆入力!AA36 -> 0 | U28: =☆入力!AB36 -> 0 | Y28: =☆入力!AC36 -> 0 | AG28: (※4)非常灯のバッテリー交換費用⇒8,000円で計算(管理会社に委託している場合の平均)
A29: 22 | C29: =IF($C$6=☆入力!$B$15,☆入力!$B37,☆入力!$C37) -> 0 | G29: =☆入力!D37 -> 0 | L29: =☆入力!H37 -> 0 | P29: =☆入力!L37 -> 0 | R29: =☆入力!AA37 -> 0 | U29: =☆入力!AB37 -> 0 | Y29: =☆入力!AC37 -> 0 | AG29: (※5)内蔵バッテリーの寿命⇒5年として10年間で2回交換することを想定して算出
A30: 23 | C30: =IF($C$6=☆入力!$B$15,☆入力!$B38,☆入力!$C38) -> 0 | G30: =☆入力!D38 -> 0 | L30: =☆入力!H38 -> 0 | P30: =☆入力!L38 -> 0 | R30: =☆入力!AA38 -> 0 | U30: =☆入力!AB38 -> 0 | Y30: =☆入力!AC38 -> 0
A31: 24 | C31: =IF($C$6=☆入力!$B$15,☆入力!$B39,☆入力!$C39) -> 0 | G31: =☆入力!D39 -> 0 | L31: =☆入力!H39 -> 0 | P31: =☆入力!L39 -> 0 | R31: =☆入力!AA39 -> 0 | U31: =☆入力!AB39 -> 0 | Y31: =☆入力!AC39 -> 0
A32: 25 | C32: =IF($C$6=☆入力!$B$15,☆入力!$B40,☆入力!$C40) -> 0 | G32: =☆入力!D40 -> 0 | L32: =☆入力!H40 -> 0 | P32: =☆入力!L40 -> 0 | R32: =☆入力!AA40 -> 0 | U32: =☆入力!AB40 -> 0 | Y32: =☆入力!AC40 -> 0
A33: 26 | C33: =IF($C$6=☆入力!$B$15,☆入力!$B41,☆入力!$C41) -> 0 | G33: =☆入力!D41 -> 0 | L33: =☆入力!H41 -> 0 | P33: =☆入力!L41 -> 0 | R33: =☆入力!AA41 -> 0 | U33: =☆入力!AB41 -> 0 | Y33: =☆入力!AC41 -> 0
A34: 27 | C34: =IF($C$6=☆入力!$B$15,☆入力!$B42,☆入力!$C42) -> 0 | G34: =☆入力!D42 -> 0 | L34: =☆入力!H42 -> 0 | P34: =☆入力!L42 -> 0 | R34: =☆入力!AA42 -> 0 | U34: =☆入力!AB42 -> 0 | Y34: =☆入力!AC42 -> 0
A35: 28 | C35: =IF($C$6=☆入力!$B$15,☆入力!$B43,☆入力!$C43) -> 0 | G35: =☆入力!D43 -> 0 | L35: =☆入力!H43 -> 0 | P35: =☆入力!L43 -> 0 | R35: =☆入力!AA43 -> 0 | U35: =☆入力!AB43 -> 0 | Y35: =☆入力!AC43 -> 0
A36: 29 | C36: =IF($C$6=☆入力!$B$15,☆入力!$B44,☆入力!$C44) -> 0 | G36: =☆入力!D44 -> 0 | L36: =☆入力!H44 -> 0 | P36: =☆入力!L44 -> 0 | R36: =☆入力!AA44 -> 0 | U36: =☆入力!AB44 -> 0 | Y36: =☆入力!AC44 -> 0
A37: 30 | C37: =IF($C$6=☆入力!$B$15,☆入力!$B45,☆入力!$C45) -> 0 | G37: =☆入力!D45 -> 0 | L37: =☆入力!H45 -> 0 | P37: =☆入力!L45 -> 0 | R37: =☆入力!AA45 -> 0 | U37: =☆入力!AB45 -> 0 | Y37: =☆入力!AC45 -> 0
K38: ※電気代の中で「照明にかかっている電気代」のみを算出しております
K39: 合計 | P39: =SUM(P8:Q37) -> 0 | R39: - | U39: =SUM(U8:X37) -> 0 | Y39: =SUM(Y8:AB37) -> 0 | AF39: ★10年間で既存照明に対してかかるランニングコストの総額＝
AS41: =AS6+AS13+AS24 -> 0
BD44: 4

Sheet ④前後a
A1: ～既存照明とLED照明の10年間のランニングコスト比較～
K3: 既存照明 | Q3: LED照明 | AA3: 既存照明の場合 | AN3: LED照明交換後 | BA3: 導入前後の差額
A5: No | C5: =LED計算式!M32 -> 試算エリア | G5: 照明種別 | K5: 使用料(月) | Q5: 使用料(月) | U5: 削減率 | AA5: ①電気料金の比較
A7: 1 | C7: =IF($C$5=☆入力!$B$15,☆入力!$B16,☆入力!$C16) -> 0 | G7: =☆入力!D16 -> 0 | K7: =☆入力!Y16 -> 0 | O7: ➡ | Q7: =☆入力!AC16 -> 0 | U7: =IFERROR(100%-(Q7/K7),"") | AA7: =②前a!$AS$6 -> 0 | AJ7: ー | AN7: =③後a!AS6 -> 0 | AW7: ＝ | BA7: =AA7-AN7 -> 0
A8: 2 | C8: =IF($C$5=☆入力!$B$15,☆入力!$B17,☆入力!$C17) -> 0 | G8: =☆入力!D17 -> 0 | K8: =☆入力!Y17 -> 0 | O8: ➡ | Q8: =☆入力!AC17 -> 0 | U8: =IFERROR(100%-(Q8/K8),"")
A9: 3 | C9: =IF($C$5=☆入力!$B$15,☆入力!$B18,☆入力!$C18) -> 0 | G9: =☆入力!D18 -> 0 | K9: =☆入力!Y18 -> 0 | O9: ➡ | Q9: =☆入力!AC18 -> 0 | U9: =IFERROR(100%-(Q9/K9),"") | AA9: + | AN9: + | BA9: +
A10: 4 | C10: =IF($C$5=☆入力!$B$15,☆入力!$B19,☆入力!$C19) -> 0 | G10: =☆入力!D19 -> 0 | K10: =☆入力!Y19 -> 0 | O10: ➡ | Q10: =☆入力!AC19 -> 0 | U10: =IFERROR(100%-(Q10/K10),"")
A11: 5 | C11: =IF($C$5=☆入力!$B$15,☆入力!$B20,☆入力!$C20) -> 0 | G11: =☆入力!D20 -> 0 | K11: =☆入力!Y20 -> 0 | O11: ➡ | Q11: =☆入力!AC20 -> 0 | U11: =IFERROR(100%-(Q11/K11),"") | AA11: ②白熱球とLED照明の交換コストの比較
A12: 6 | C12: =IF($C$5=☆入力!$B$15,☆入力!$B21,☆入力!$C21) -> 0 | G12: =☆入力!D21 -> 0 | K12: =☆入力!Y21 -> 0 | O12: ➡ | Q12: =☆入力!AC21 -> 0 | U12: =IFERROR(100%-(Q12/K12),"")
A13: 7 | C13: =IF($C$5=☆入力!$B$15,☆入力!$B22,☆入力!$C22) -> 0 | G13: =☆入力!D22 -> 0 | K13: =☆入力!Y22 -> 0 | O13: ➡ | Q13: =☆入力!AC22 -> 0 | U13: =IFERROR(100%-(Q13/K13),"") | AA13: =②前a!$AS$13 -> 0 | AJ13: ー | AN13: =③後a!AS13 -> 0 | AW13: ＝ | BA13: =AA13-AN13 -> 0
A14: 8 | C14: =IF($C$5=☆入力!$B$15,☆入力!$B23,☆入力!$C23) -> 0 | G14: =☆入力!D23 -> 0 | K14: =☆入力!Y23 -> 0 | O14: ➡ | Q14: =☆入力!AC23 -> 0 | U14: =IFERROR(100%-(Q14/K14),"")
A15: 9 | C15: =IF($C$5=☆入力!$B$15,☆入力!$B24,☆入力!$C24) -> 0 | G15: =☆入力!D24 -> 0 | K15: =☆入力!Y24 -> 0 | O15: ➡ | Q15: =☆入力!AC24 -> 0 | U15: =IFERROR(100%-(Q15/K15),"") | AA15: + | AN15: + | BA15: +
A16: 10 | C16: =IF($C$5=☆入力!$B$15,☆入力!$B25,☆入力!$C25) -> 0 | G16: =☆入力!D25 -> 0 | K16: =☆入力!Y25 -> 0 | O16: ➡ | Q16: =☆入力!AC25 -> 0 | U16: =IFERROR(100%-(Q16/K16),"")
A17: 11 | C17: =IF($C$5=☆入力!$B$15,☆入力!$B26,☆入力!$C26) -> 0 | G17: =☆入力!D26 -> 0 | K17: =☆入力!Y26 -> 0 | O17: ➡ | Q17: =☆入力!AC26 -> 0 | U17: =IFERROR(100%-(Q17/K17),"") | AA17: ③非常灯のバッテリー交換コストの比較
A18: 12 | C18: =IF($C$5=☆入力!$B$15,☆入力!$B27,☆入力!$C27) -> 0 | G18: =☆入力!D27 -> 0 | K18: =☆入力!Y27 -> 0 | O18: ➡ | Q18: =☆入力!AC27 -> 0 | U18: =IFERROR(100%-(Q18/K18),"")
A19: 13 | C19: =IF($C$5=☆入力!$B$15,☆入力!$B28,☆入力!$C28) -> 0 | G19: =☆入力!D28 -> 0 | K19: =☆入力!Y28 -> 0 | O19: ➡ | Q19: =☆入力!AC28 -> 0 | U19: =IFERROR(100%-(Q19/K19),"") | AA19: =②前a!$AS$24 -> 0 | AJ19: ー | AN19: =③後a!AS24 -> 0 | AW19: ＝ | BA19: =AA19-AN19 -> 0
A20: 14 | C20: =IF($C$5=☆入力!$B$15,☆入力!$B29,☆入力!$C29) -> 0 | G20: =☆入力!D29 -> 0 | K20: =☆入力!Y29 -> 0 | O20: ➡ | Q20: =☆入力!AC29 -> 0 | U20: =IFERROR(100%-(Q20/K20),"")
A21: 15 | C21: =IF($C$5=☆入力!$B$15,☆入力!$B30,☆入力!$C30) -> 0 | G21: =☆入力!D30 -> 0 | K21: =☆入力!Y30 -> 0 | O21: ➡ | Q21: =☆入力!AC30 -> 0 | U21: =IFERROR(100%-(Q21/K21),"")
A22: 16 | C22: =IF($C$5=☆入力!$B$15,☆入力!$B31,☆入力!$C31) -> 0 | G22: =☆入力!D31 -> 0 | K22: =☆入力!Y31 -> 0 | O22: ➡ | Q22: =☆入力!AC31 -> 0 | U22: =IFERROR(100%-(Q22/K22),"")
A23: 17 | C23: =IF($C$5=☆入力!$B$15,☆入力!$B32,☆入力!$C32) -> 0 | G23: =☆入力!D32 -> 0 | K23: =☆入力!Y32 -> 0 | O23: ➡ | Q23: =☆入力!AC32 -> 0 | U23: =IFERROR(100%-(Q23/K23),"")
A24: 18 | C24: =IF($C$5=☆入力!$B$15,☆入力!$B33,☆入力!$C33) -> 0 | G24: =☆入力!D33 -> 0 | K24: =☆入力!Y33 -> 0 | O24: ➡ | Q24: =☆入力!AC33 -> 0 | U24: =IFERROR(100%-(Q24/K24),"")
A25: 19 | C25: =IF($C$5=☆入力!$B$15,☆入力!$B34,☆入力!$C34) -> 0 | G25: =☆入力!D34 -> 0 | K25: =☆入力!Y34 -> 0 | O25: ➡ | Q25: =☆入力!AC34 -> 0 | U25: =IFERROR(100%-(Q25/K25),"")
A26: 20 | C26: =IF($C$5=☆入力!$B$15,☆入力!$B35,☆入力!$C35) -> 0 | G26: =☆入力!D35 -> 0 | K26: =☆入力!Y35 -> 0 | O26: ➡ | Q26: =☆入力!AC35 -> 0 | U26: =IFERROR(100%-(Q26/K26),"")
A27: 21 | C27: =IF($C$5=☆入力!$B$15,☆入力!$B36,☆入力!$C36) -> 0 | G27: =☆入力!D36 -> 0 | K27: =☆入力!Y36 -> 0 | O27: ➡ | Q27: =☆入力!AC36 -> 0 | U27: =IFERROR(100%-(Q27/K27),"") | AA27: ★既存照明とLED照明の10年間のランニングコスト比較
A28: 22 | C28: =IF($C$5=☆入力!$B$15,☆入力!$B37,☆入力!$C37) -> 0 | G28: =☆入力!D37 -> 0 | K28: =☆入力!Y37 -> 0 | O28: ➡ | Q28: =☆入力!AC37 -> 0 | U28: =IFERROR(100%-(Q28/K28),"")
A29: 23 | C29: =IF($C$5=☆入力!$B$15,☆入力!$B38,☆入力!$C38) -> 0 | G29: =☆入力!D38 -> 0 | K29: =☆入力!Y38 -> 0 | O29: ➡ | Q29: =☆入力!AC38 -> 0 | U29: =IFERROR(100%-(Q29/K29),"") | AA29: =AA7+AA13+AA19 -> 0 | AJ29: ー | AN29: =AN7+AN13+AN19 -> 0 | AW29: ＝ | BA29: =AA29-AN29 -> 0
A30: 24 | C30: =IF($C$5=☆入力!$B$15,☆入力!$B39,☆入力!$C39) -> 0 | G30: =☆入力!D39 -> 0 | K30: =☆入力!Y39 -> 0 | O30: ➡ | Q30: =☆入力!AC39 -> 0 | U30: =IFERROR(100%-(Q30/K30),"")
A31: 25 | C31: =IF($C$5=☆入力!$B$15,☆入力!$B40,☆入力!$C40) -> 0 | G31: =☆入力!D40 -> 0 | K31: =☆入力!Y40 -> 0 | O31: ➡ | Q31: =☆入力!AC40 -> 0 | U31: =IFERROR(100%-(Q31/K31),"")
A32: 26 | C32: =IF($C$5=☆入力!$B$15,☆入力!$B41,☆入力!$C41) -> 0 | G32: =☆入力!D41 -> 0 | K32: =☆入力!Y41 -> 0 | O32: ➡ | Q32: =☆入力!AC41 -> 0 | U32: =IFERROR(100%-(Q32/K32),"") | Z32: 備考：
A33: 27 | C33: =IF($C$5=☆入力!$B$15,☆入力!$B42,☆入力!$C42) -> 0 | G33: =☆入力!D42 -> 0 | K33: =☆入力!Y42 -> 0 | O33: ➡ | Q33: =☆入力!AC42 -> 0 | U33: =IFERROR(100%-(Q33/K33),"") | Z33: =☆入力!X2 -> 0
A34: 28 | C34: =IF($C$5=☆入力!$B$15,☆入力!$B43,☆入力!$C43) -> 0 | G34: =☆入力!D43 -> 0 | K34: =☆入力!Y43 -> 0 | O34: ➡ | Q34: =☆入力!AC43 -> 0 | U34: =IFERROR(100%-(Q34/K34),"") | Z34: =☆入力!X3 -> 0
A35: 29 | C35: =IF($C$5=☆入力!$B$15,☆入力!$B44,☆入力!$C44) -> 0 | G35: =☆入力!D44 -> 0 | K35: =☆入力!Y44 -> 0 | O35: ➡ | Q35: =☆入力!AC44 -> 0 | U35: =IFERROR(100%-(Q35/K35),"") | Z35: =☆入力!X4 -> 0
A36: 30 | C36: =IF($C$5=☆入力!$B$15,☆入力!$B45,☆入力!$C45) -> 0 | G36: =☆入力!D45 -> 0 | K36: =☆入力!Y45 -> 0 | O36: ➡ | Q36: =☆入力!AC45 -> 0 | U36: =IFERROR(100%-(Q36/K36),"") | Z36: =☆入力!X5 -> 0
Z37: =☆入力!X6 -> 0
K38: =SUM(K7:N36) -> 0 | O38: ➡ | Q38: =SUM(Q7:T36) -> 0 | U38: =IFERROR(100%-(Q38/K38),"") | Z38: =☆入力!X7 -> 0
Z39: =☆入力!X8 -> 0
Z40: =☆入力!X9 -> 0
A41: ★電気代だけでみた毎月の削減金額・・・・ | Q41: =K38-Q38 -> 0 | Z41: =☆入力!X10 -> 0
Z42: =☆入力!X11 -> 0
A44: 【免責】本資料に記載された内容は、一定条件下における試算結果であり数値等を保証するものでは御座いません。 | BI44: 5

Sheet ④照明の交換方法
B2: 照明の交換方法
O31: 4

Sheet ⑤前
A1: ～現地調査結果および既存照明にかかる10年間のランニングコスト～
R3: 既存照明の場合 | AF3: 既存照明に対してかかっている10年間のランニングコスト
A6: No | C6: =LED計算式!M32 -> 試算エリア | G6: 照明種別 | L6: 月間点灯 | P6: 数量 | R6: 消費電力 | U6: 電力量 | Y6: 使用料(月)
AF7: ①10年間でかかる電気料金の総額＝ | AS7: =Y39*120 -> 0
A8: 1 | C8: =IF($C$6=☆入力!$B$15,☆入力!$B16,☆入力!$C16) -> 0 | G8: =☆入力!D16 -> 0 | L8: =☆入力!H16 -> 0 | P8: =☆入力!L16 -> 0 | R8: =☆入力!K16 -> 0 | U8: =☆入力!W16 -> 0 | Y8: =☆入力!Y16 -> 0
A9: 2 | C9: =IF($C$6=☆入力!$B$15,☆入力!$B17,☆入力!$C17) -> 0 | G9: =☆入力!D17 -> 0 | L9: =☆入力!H17 -> 0 | P9: =☆入力!L17 -> 0 | R9: =☆入力!K17 -> 0 | U9: =☆入力!W17 -> 0 | Y9: =☆入力!Y17 -> 0
A10: 3 | C10: =IF($C$6=☆入力!$B$15,☆入力!$B18,☆入力!$C18) -> 0 | G10: =☆入力!D18 -> 0 | L10: =☆入力!H18 -> 0 | P10: =☆入力!L18 -> 0 | R10: =☆入力!K18 -> 0 | U10: =☆入力!W18 -> 0 | Y10: =☆入力!Y18 -> 0 | AG10: 計算式：毎月の電気料金 | AO10: =Y39 -> 0 | AS10: ×10年間（120ヵ月）
A11: 4 | C11: =IF($C$6=☆入力!$B$15,☆入力!$B19,☆入力!$C19) -> 0 | G11: =☆入力!D19 -> 0 | L11: =☆入力!H19 -> 0 | P11: =☆入力!L19 -> 0 | R11: =☆入力!K19 -> 0 | U11: =☆入力!W19 -> 0 | Y11: =☆入力!Y19 -> 0
A12: 5 | C12: =IF($C$6=☆入力!$B$15,☆入力!$B20,☆入力!$C20) -> 0 | G12: =☆入力!D20 -> 0 | L12: =☆入力!H20 -> 0 | P12: =☆入力!L20 -> 0 | R12: =☆入力!K20 -> 0 | U12: =☆入力!W20 -> 0 | Y12: =☆入力!Y20 -> 0
A13: 6 | C13: =IF($C$6=☆入力!$B$15,☆入力!$B21,☆入力!$C21) -> 0 | G13: =☆入力!D21 -> 0 | L13: =☆入力!H21 -> 0 | P13: =☆入力!L21 -> 0 | R13: =☆入力!K21 -> 0 | U13: =☆入力!W21 -> 0 | Y13: =☆入力!Y21 -> 0 | AS13: +
A14: 7 | C14: =IF($C$6=☆入力!$B$15,☆入力!$B22,☆入力!$C22) -> 0 | G14: =☆入力!D22 -> 0 | L14: =☆入力!H22 -> 0 | P14: =☆入力!L22 -> 0 | R14: =☆入力!K22 -> 0 | U14: =☆入力!W22 -> 0 | Y14: =☆入力!Y22 -> 0
A15: 8 | C15: =IF($C$6=☆入力!$B$15,☆入力!$B23,☆入力!$C23) -> 0 | G15: =☆入力!D23 -> 0 | L15: =☆入力!H23 -> 0 | P15: =☆入力!L23 -> 0 | R15: =☆入力!K23 -> 0 | U15: =☆入力!W23 -> 0 | Y15: =☆入力!Y23 -> 0
A16: 9 | C16: =IF($C$6=☆入力!$B$15,☆入力!$B24,☆入力!$C24) -> 0 | G16: =☆入力!D24 -> 0 | L16: =☆入力!H24 -> 0 | P16: =☆入力!L24 -> 0 | R16: =☆入力!K24 -> 0 | U16: =☆入力!W24 -> 0 | Y16: =☆入力!Y24 -> 0 | AF16: ②10年間でかかる白熱球の交換コストの総額＝
A17: 10 | C17: =IF($C$6=☆入力!$B$15,☆入力!$B25,☆入力!$C25) -> 0 | G17: =☆入力!D25 -> 0 | L17: =☆入力!H25 -> 0 | P17: =☆入力!L25 -> 0 | R17: =☆入力!K25 -> 0 | U17: =☆入力!W25 -> 0 | Y17: =☆入力!Y25 -> 0
A18: 11 | C18: =IF($C$6=☆入力!$B$15,☆入力!$B26,☆入力!$C26) -> 0 | G18: =☆入力!D26 -> 0 | L18: =☆入力!H26 -> 0 | P18: =☆入力!L26 -> 0 | R18: =☆入力!K26 -> 0 | U18: =☆入力!W26 -> 0 | Y18: =☆入力!Y26 -> 0
A19: 12 | C19: =IF($C$6=☆入力!$B$15,☆入力!$B27,☆入力!$C27) -> 0 | G19: =☆入力!D27 -> 0 | L19: =☆入力!H27 -> 0 | P19: =☆入力!L27 -> 0 | R19: =☆入力!K27 -> 0 | U19: =☆入力!W27 -> 0 | Y19: =☆入力!Y27 -> 0 | AS19: =(AN22*☆入力!AR9*7)+(AN23*☆入力!AR9*15) -> 0
A20: 13 | C20: =IF($C$6=☆入力!$B$15,☆入力!$B28,☆入力!$C28) -> 0 | G20: =☆入力!D28 -> 0 | L20: =☆入力!H28 -> 0 | P20: =☆入力!L28 -> 0 | R20: =☆入力!K28 -> 0 | U20: =☆入力!W28 -> 0 | Y20: =☆入力!Y28 -> 0
A21: 14 | C21: =IF($C$6=☆入力!$B$15,☆入力!$B29,☆入力!$C29) -> 0 | G21: =☆入力!D29 -> 0 | L21: =☆入力!H29 -> 0 | P21: =☆入力!L29 -> 0 | R21: =☆入力!K29 -> 0 | U21: =☆入力!W29 -> 0 | Y21: =☆入力!Y29 -> 0
A22: 15 | C22: =IF($C$6=☆入力!$B$15,☆入力!$B30,☆入力!$C30) -> 0 | G22: =☆入力!D30 -> 0 | L22: =☆入力!H30 -> 0 | P22: =☆入力!L30 -> 0 | R22: =☆入力!K30 -> 0 | U22: =☆入力!W30 -> 0 | Y22: =☆入力!Y30 -> 0 | AG22: 月間点灯360hの場合： | AN22: =LED計算式!N16 -> 0 | AQ22: ="× "&TEXT(☆入力!AR9,"#,#00")&"円（※1）× 7回（※2）" -> × 00円（※1）× 7回（※2）
A23: 16 | C23: =IF($C$6=☆入力!$B$15,☆入力!$B31,☆入力!$C31) -> 0 | G23: =☆入力!D31 -> 0 | L23: =☆入力!H31 -> 0 | P23: =☆入力!L31 -> 0 | R23: =☆入力!K31 -> 0 | U23: =☆入力!W31 -> 0 | Y23: =☆入力!Y31 -> 0 | AG23: 月間点灯720hの場合： | AN23: =LED計算式!N17 -> 0 | AQ23: ="× "&TEXT(☆入力!AR9,"#,#00")&"円（※1）× 15回（※3）" -> × 00円（※1）× 15回（※3）
A24: 17 | C24: =IF($C$6=☆入力!$B$15,☆入力!$B32,☆入力!$C32) -> 0 | G24: =☆入力!D32 -> 0 | L24: =☆入力!H32 -> 0 | P24: =☆入力!L32 -> 0 | R24: =☆入力!K32 -> 0 | U24: =☆入力!W32 -> 0 | Y24: =☆入力!Y32 -> 0
A25: 18 | C25: =IF($C$6=☆入力!$B$15,☆入力!$B33,☆入力!$C33) -> 0 | G25: =☆入力!D33 -> 0 | L25: =☆入力!H33 -> 0 | P25: =☆入力!L33 -> 0 | R25: =☆入力!K33 -> 0 | U25: =☆入力!W33 -> 0 | Y25: =☆入力!Y33 -> 0 | AG25: ="(※1)白熱球の1球あたりの交換費用⇒"&TEXT(☆入力!AR9,"#,#00")&"円で計算(管理会社に委託している場合の平均)" -> (※1)白熱球の1球あたりの交換費用⇒00円で計算(管理会社に委託している場合の平均)
A26: 19 | C26: =IF($C$6=☆入力!$B$15,☆入力!$B34,☆入力!$C34) -> 0 | G26: =☆入力!D34 -> 0 | L26: =☆入力!H34 -> 0 | P26: =☆入力!L34 -> 0 | R26: =☆入力!K34 -> 0 | U26: =☆入力!W34 -> 0 | Y26: =☆入力!Y34 -> 0 | AG26: (※2)月間点灯360時間の場合⇒電球寿命を1年5ヵ月として10年間で7回の交換を想定して算出
A27: 20 | C27: =IF($C$6=☆入力!$B$15,☆入力!$B35,☆入力!$C35) -> 0 | G27: =☆入力!D35 -> 0 | L27: =☆入力!H35 -> 0 | P27: =☆入力!L35 -> 0 | R27: =☆入力!K35 -> 0 | U27: =☆入力!W35 -> 0 | Y27: =☆入力!Y35 -> 0 | AG27: (※3)月間点灯720時間の場合⇒電球寿命を8ヵ月として10年間で15回の交換を想定して算出
A28: 21 | C28: =IF($C$6=☆入力!$B$15,☆入力!$B36,☆入力!$C36) -> 0 | G28: =☆入力!D36 -> 0 | L28: =☆入力!H36 -> 0 | P28: =☆入力!L36 -> 0 | R28: =☆入力!K36 -> 0 | U28: =☆入力!W36 -> 0 | Y28: =☆入力!Y36 -> 0
A29: 22 | C29: =IF($C$6=☆入力!$B$15,☆入力!$B37,☆入力!$C37) -> 0 | G29: =☆入力!D37 -> 0 | L29: =☆入力!H37 -> 0 | P29: =☆入力!L37 -> 0 | R29: =☆入力!K37 -> 0 | U29: =☆入力!W37 -> 0 | Y29: =☆入力!Y37 -> 0
A30: 23 | C30: =IF($C$6=☆入力!$B$15,☆入力!$B38,☆入力!$C38) -> 0 | G30: =☆入力!D38 -> 0 | L30: =☆入力!H38 -> 0 | P30: =☆入力!L38 -> 0 | R30: =☆入力!K38 -> 0 | U30: =☆入力!W38 -> 0 | Y30: =☆入力!Y38 -> 0
A31: 24 | C31: =IF($C$6=☆入力!$B$15,☆入力!$B39,☆入力!$C39) -> 0 | G31: =☆入力!D39 -> 0 | L31: =☆入力!H39 -> 0 | P31: =☆入力!L39 -> 0 | R31: =☆入力!K39 -> 0 | U31: =☆入力!W39 -> 0 | Y31: =☆入力!Y39 -> 0
A32: 25 | C32: =IF($C$6=☆入力!$B$15,☆入力!$B40,☆入力!$C40) -> 0 | G32: =☆入力!D40 -> 0 | L32: =☆入力!H40 -> 0 | P32: =☆入力!L40 -> 0 | R32: =☆入力!K40 -> 0 | U32: =☆入力!W40 -> 0 | Y32: =☆入力!Y40 -> 0
A33: 26 | C33: =IF($C$6=☆入力!$B$15,☆入力!$B41,☆入力!$C41) -> 0 | G33: =☆入力!D41 -> 0 | L33: =☆入力!H41 -> 0 | P33: =☆入力!L41 -> 0 | R33: =☆入力!K41 -> 0 | U33: =☆入力!W41 -> 0 | Y33: =☆入力!Y41 -> 0
A34: 27 | C34: =IF($C$6=☆入力!$B$15,☆入力!$B42,☆入力!$C42) -> 0 | G34: =☆入力!D42 -> 0 | L34: =☆入力!H42 -> 0 | P34: =☆入力!L42 -> 0 | R34: =☆入力!K42 -> 0 | U34: =☆入力!W42 -> 0 | Y34: =☆入力!Y42 -> 0
A35: 28 | C35: =IF($C$6=☆入力!$B$15,☆入力!$B43,☆入力!$C43) -> 0 | G35: =☆入力!D43 -> 0 | L35: =☆入力!H43 -> 0 | P35: =☆入力!L43 -> 0 | R35: =☆入力!K43 -> 0 | U35: =☆入力!W43 -> 0 | Y35: =☆入力!Y43 -> 0
A36: 29 | C36: =IF($C$6=☆入力!$B$15,☆入力!$B44,☆入力!$C44) -> 0 | G36: =☆入力!D44 -> 0 | L36: =☆入力!H44 -> 0 | P36: =☆入力!L44 -> 0 | R36: =☆入力!K44 -> 0 | U36: =☆入力!W44 -> 0 | Y36: =☆入力!Y44 -> 0
A37: 30 | C37: =IF($C$6=☆入力!$B$15,☆入力!$B45,☆入力!$C45) -> 0 | G37: =☆入力!D45 -> 0 | L37: =☆入力!H45 -> 0 | P37: =☆入力!L45 -> 0 | R37: =☆入力!K45 -> 0 | U37: =☆入力!W45 -> 0 | Y37: =☆入力!Y45 -> 0
K38: ※電気代の中で「照明にかかっている電気代」のみを算出しております
K39: 合計 | P39: =SUM(P8:Q37) -> 0 | R39: - | U39: =SUM(U8:X37) -> 0 | Y39: =SUM(Y8:AB37) -> 0 | AF39: ★10年間で既存照明に対してかかるランニングコストの総額＝
AS41: =AS7+AS19+AS24 -> 0
BD44: 5

Sheet ⑥後
A1: ～LED照明導入後の削減費用および10年間のランニングコスト～
R3: LED照明交換後 | AF3: LED照明に交換した場合の10年間のランニングコスト
A6: No | C6: =LED計算式!M32 -> 試算エリア | G6: 照明種別 | L6: 月間点灯 | P6: 数量 | R6: 消費電力 | U6: 電力量 | Y6: 使用料(月)
AF7: ①10年間でかかる電気料金の総額＝ | AS7: =Y39*120 -> 0
A8: 1 | C8: =IF($C$6=☆入力!$B$15,☆入力!$B16,☆入力!$C16) -> 0 | G8: =☆入力!D16 -> 0 | L8: =☆入力!H16 -> 0 | P8: =☆入力!L16 -> 0 | R8: =☆入力!AA16 -> 0 | U8: =☆入力!AB16 -> 0 | Y8: =☆入力!AC16 -> 0
A9: 2 | C9: =IF($C$6=☆入力!$B$15,☆入力!$B17,☆入力!$C17) -> 0 | G9: =☆入力!D17 -> 0 | L9: =☆入力!H17 -> 0 | P9: =☆入力!L17 -> 0 | R9: =☆入力!AA17 -> 0 | U9: =☆入力!AB17 -> 0 | Y9: =☆入力!AC17 -> 0
A10: 3 | C10: =IF($C$6=☆入力!$B$15,☆入力!$B18,☆入力!$C18) -> 0 | G10: =☆入力!D18 -> 0 | L10: =☆入力!H18 -> 0 | P10: =☆入力!L18 -> 0 | R10: =☆入力!AA18 -> 0 | U10: =☆入力!AB18 -> 0 | Y10: =☆入力!AC18 -> 0 | AG10: 計算式：毎月の電気料金 | AO10: =Y39 -> 0 | AS10: ×10年間（120ヵ月）
A11: 4 | C11: =IF($C$6=☆入力!$B$15,☆入力!$B19,☆入力!$C19) -> 0 | G11: =☆入力!D19 -> 0 | L11: =☆入力!H19 -> 0 | P11: =☆入力!L19 -> 0 | R11: =☆入力!AA19 -> 0 | U11: =☆入力!AB19 -> 0 | Y11: =☆入力!AC19 -> 0
A12: 5 | C12: =IF($C$6=☆入力!$B$15,☆入力!$B20,☆入力!$C20) -> 0 | G12: =☆入力!D20 -> 0 | L12: =☆入力!H20 -> 0 | P12: =☆入力!L20 -> 0 | R12: =☆入力!AA20 -> 0 | U12: =☆入力!AB20 -> 0 | Y12: =☆入力!AC20 -> 0
A13: 6 | C13: =IF($C$6=☆入力!$B$15,☆入力!$B21,☆入力!$C21) -> 0 | G13: =☆入力!D21 -> 0 | L13: =☆入力!H21 -> 0 | P13: =☆入力!L21 -> 0 | R13: =☆入力!AA21 -> 0 | U13: =☆入力!AB21 -> 0 | Y13: =☆入力!AC21 -> 0 | AS13: +
A14: 7 | C14: =IF($C$6=☆入力!$B$15,☆入力!$B22,☆入力!$C22) -> 0 | G14: =☆入力!D22 -> 0 | L14: =☆入力!H22 -> 0 | P14: =☆入力!L22 -> 0 | R14: =☆入力!AA22 -> 0 | U14: =☆入力!AB22 -> 0 | Y14: =☆入力!AC22 -> 0
A15: 8 | C15: =IF($C$6=☆入力!$B$15,☆入力!$B23,☆入力!$C23) -> 0 | G15: =☆入力!D23 -> 0 | L15: =☆入力!H23 -> 0 | P15: =☆入力!L23 -> 0 | R15: =☆入力!AA23 -> 0 | U15: =☆入力!AB23 -> 0 | Y15: =☆入力!AC23 -> 0
A16: 9 | C16: =IF($C$6=☆入力!$B$15,☆入力!$B24,☆入力!$C24) -> 0 | G16: =☆入力!D24 -> 0 | L16: =☆入力!H24 -> 0 | P16: =☆入力!L24 -> 0 | R16: =☆入力!AA24 -> 0 | U16: =☆入力!AB24 -> 0 | Y16: =☆入力!AC24 -> 0 | AF16: ②10年間でかかるLED照明の交換コストの総額＝
A17: 10 | C17: =IF($C$6=☆入力!$B$15,☆入力!$B25,☆入力!$C25) -> 0 | G17: =☆入力!D25 -> 0 | L17: =☆入力!H25 -> 0 | P17: =☆入力!L25 -> 0 | R17: =☆入力!AA25 -> 0 | U17: =☆入力!AB25 -> 0 | Y17: =☆入力!AC25 -> 0
A18: 11 | C18: =IF($C$6=☆入力!$B$15,☆入力!$B26,☆入力!$C26) -> 0 | G18: =☆入力!D26 -> 0 | L18: =☆入力!H26 -> 0 | P18: =☆入力!L26 -> 0 | R18: =☆入力!AA26 -> 0 | U18: =☆入力!AB26 -> 0 | Y18: =☆入力!AC26 -> 0
A19: 12 | C19: =IF($C$6=☆入力!$B$15,☆入力!$B27,☆入力!$C27) -> 0 | G19: =☆入力!D27 -> 0 | L19: =☆入力!H27 -> 0 | P19: =☆入力!L27 -> 0 | R19: =☆入力!AA27 -> 0 | U19: =☆入力!AB27 -> 0 | Y19: =☆入力!AC27 -> 0 | AS19: =AN23*3000*1 -> 0
A20: 13 | C20: =IF($C$6=☆入力!$B$15,☆入力!$B28,☆入力!$C28) -> 0 | G20: =☆入力!D28 -> 0 | L20: =☆入力!H28 -> 0 | P20: =☆入力!L28 -> 0 | R20: =☆入力!AA28 -> 0 | U20: =☆入力!AB28 -> 0 | Y20: =☆入力!AC28 -> 0
A21: 14 | C21: =IF($C$6=☆入力!$B$15,☆入力!$B29,☆入力!$C29) -> 0 | G21: =☆入力!D29 -> 0 | L21: =☆入力!H29 -> 0 | P21: =☆入力!L29 -> 0 | R21: =☆入力!AA29 -> 0 | U21: =☆入力!AB29 -> 0 | Y21: =☆入力!AC29 -> 0
A22: 15 | C22: =IF($C$6=☆入力!$B$15,☆入力!$B30,☆入力!$C30) -> 0 | G22: =☆入力!D30 -> 0 | L22: =☆入力!H30 -> 0 | P22: =☆入力!L30 -> 0 | R22: =☆入力!AA30 -> 0 | U22: =☆入力!AB30 -> 0 | Y22: =☆入力!AC30 -> 0 | AG22: 月間点灯360hの場合： | AN22: =LED計算式!N16 -> 0 | AQ22: ="× "&TEXT(☆入力!AR9,"#,#00")&"円（※1）× 0回（※2）" -> × 00円（※1）× 0回（※2）
A23: 16 | C23: =IF($C$6=☆入力!$B$15,☆入力!$B31,☆入力!$C31) -> 0 | G23: =☆入力!D31 -> 0 | L23: =☆入力!H31 -> 0 | P23: =☆入力!L31 -> 0 | R23: =☆入力!AA31 -> 0 | U23: =☆入力!AB31 -> 0 | Y23: =☆入力!AC31 -> 0 | AG23: 月間点灯720hの場合： | AN23: =LED計算式!N17 -> 0 | AQ23: × 3,000円（※1）× 1回（※3）
A24: 17 | C24: =IF($C$6=☆入力!$B$15,☆入力!$B32,☆入力!$C32) -> 0 | G24: =☆入力!D32 -> 0 | L24: =☆入力!H32 -> 0 | P24: =☆入力!L32 -> 0 | R24: =☆入力!AA32 -> 0 | U24: =☆入力!AB32 -> 0 | Y24: =☆入力!AC32 -> 0
A25: 18 | C25: =IF($C$6=☆入力!$B$15,☆入力!$B33,☆入力!$C33) -> 0 | G25: =☆入力!D33 -> 0 | L25: =☆入力!H33 -> 0 | P25: =☆入力!L33 -> 0 | R25: =☆入力!AA33 -> 0 | U25: =☆入力!AB33 -> 0 | Y25: =☆入力!AC33 -> 0 | AG25: (※1)月間点灯720時間の場合、光源部分の交換を3,000円/球として算出
A26: 19 | C26: =IF($C$6=☆入力!$B$15,☆入力!$B34,☆入力!$C34) -> 0 | G26: =☆入力!D34 -> 0 | L26: =☆入力!H34 -> 0 | P26: =☆入力!L34 -> 0 | R26: =☆入力!AA34 -> 0 | U26: =☆入力!AB34 -> 0 | Y26: =☆入力!AC34 -> 0
A27: 20 | C27: =IF($C$6=☆入力!$B$15,☆入力!$B35,☆入力!$C35) -> 0 | G27: =☆入力!D35 -> 0 | L27: =☆入力!H35 -> 0 | P27: =☆入力!L35 -> 0 | R27: =☆入力!AA35 -> 0 | U27: =☆入力!AB35 -> 0 | Y27: =☆入力!AC35 -> 0 | AG27: (※3)月間点灯720時間の場合、10年間で1回の光源部分交換を想定して算出
A28: 21 | C28: =IF($C$6=☆入力!$B$15,☆入力!$B36,☆入力!$C36) -> 0 | G28: =☆入力!D36 -> 0 | L28: =☆入力!H36 -> 0 | P28: =☆入力!L36 -> 0 | R28: =☆入力!AA36 -> 0 | U28: =☆入力!AB36 -> 0 | Y28: =☆入力!AC36 -> 0
A29: 22 | C29: =IF($C$6=☆入力!$B$15,☆入力!$B37,☆入力!$C37) -> 0 | G29: =☆入力!D37 -> 0 | L29: =☆入力!H37 -> 0 | P29: =☆入力!L37 -> 0 | R29: =☆入力!AA37 -> 0 | U29: =☆入力!AB37 -> 0 | Y29: =☆入力!AC37 -> 0
A30: 23 | C30: =IF($C$6=☆入力!$B$15,☆入力!$B38,☆入力!$C38) -> 0 | G30: =☆入力!D38 -> 0 | L30: =☆入力!H38 -> 0 | P30: =☆入力!L38 -> 0 | R30: =☆入力!AA38 -> 0 | U30: =☆入力!AB38 -> 0 | Y30: =☆入力!AC38 -> 0
A31: 24 | C31: =IF($C$6=☆入力!$B$15,☆入力!$B39,☆入力!$C39) -> 0 | G31: =☆入力!D39 -> 0 | L31: =☆入力!H39 -> 0 | P31: =☆入力!L39 -> 0 | R31: =☆入力!AA39 -> 0 | U31: =☆入力!AB39 -> 0 | Y31: =☆入力!AC39 -> 0
A32: 25 | C32: =IF($C$6=☆入力!$B$15,☆入力!$B40,☆入力!$C40) -> 0 | G32: =☆入力!D40 -> 0 | L32: =☆入力!H40 -> 0 | P32: =☆入力!L40 -> 0 | R32: =☆入力!AA40 -> 0 | U32: =☆入力!AB40 -> 0 | Y32: =☆入力!AC40 -> 0
A33: 26 | C33: =IF($C$6=☆入力!$B$15,☆入力!$B41,☆入力!$C41) -> 0 | G33: =☆入力!D41 -> 0 | L33: =☆入力!H41 -> 0 | P33: =☆入力!L41 -> 0 | R33: =☆入力!AA41 -> 0 | U33: =☆入力!AB41 -> 0 | Y33: =☆入力!AC41 -> 0
A34: 27 | C34: =IF($C$6=☆入力!$B$15,☆入力!$B42,☆入力!$C42) -> 0 | G34: =☆入力!D42 -> 0 | L34: =☆入力!H42 -> 0 | P34: =☆入力!L42 -> 0 | R34: =☆入力!AA42 -> 0 | U34: =☆入力!AB42 -> 0 | Y34: =☆入力!AC42 -> 0
A35: 28 | C35: =IF($C$6=☆入力!$B$15,☆入力!$B43,☆入力!$C43) -> 0 | G35: =☆入力!D43 -> 0 | L35: =☆入力!H43 -> 0 | P35: =☆入力!L43 -> 0 | R35: =☆入力!AA43 -> 0 | U35: =☆入力!AB43 -> 0 | Y35: =☆入力!AC43 -> 0
A36: 29 | C36: =IF($C$6=☆入力!$B$15,☆入力!$B44,☆入力!$C44) -> 0 | G36: =☆入力!D44 -> 0 | L36: =☆入力!H44 -> 0 | P36: =☆入力!L44 -> 0 | R36: =☆入力!AA44 -> 0 | U36: =☆入力!AB44 -> 0 | Y36: =☆入力!AC44 -> 0
A37: 30 | C37: =IF($C$6=☆入力!$B$15,☆入力!$B45,☆入力!$C45) -> 0 | G37: =☆入力!D45 -> 0 | L37: =☆入力!H45 -> 0 | P37: =☆入力!L45 -> 0 | R37: =☆入力!AA45 -> 0 | U37: =☆入力!AB45 -> 0 | Y37: =☆入力!AC45 -> 0
K38: ※電気代の中で「照明にかかっている電気代」のみを算出しております
K39: 合計 | P39: =SUM(P8:Q37) -> 0 | R39: - | U39: =SUM(U8:X37) -> 0 | Y39: =SUM(Y8:AB37) -> 0 | AF39: ★10年間で既存照明に対してかかるランニングコストの総額＝
AS41: =AS7+AS19+AS24 -> 0
BD44: 6

Sheet ⑦前後
A1: ～既存照明とLED照明の10年間のランニングコスト比較～
K3: 既存照明 | Q3: LED照明 | AA3: 既存照明の場合 | AN3: LED照明交換後 | BA3: 導入前後の差額
A5: No | C5: =LED計算式!M32 -> 試算エリア | G5: 照明種別 | K5: 使用料(月) | Q5: 使用料(月) | U5: 削減率
AA6: ①電気料金の比較
A7: 1 | C7: =IF($C$5=☆入力!$B$15,☆入力!$B16,☆入力!$C16) -> 0 | G7: =☆入力!D16 -> 0 | K7: =☆入力!Y16 -> 0 | O7: ➡ | Q7: =☆入力!AC16 -> 0 | U7: =IFERROR(100%-(Q7/K7),"")
A8: 2 | C8: =IF($C$5=☆入力!$B$15,☆入力!$B17,☆入力!$C17) -> 0 | G8: =☆入力!D17 -> 0 | K8: =☆入力!Y17 -> 0 | O8: ➡ | Q8: =☆入力!AC17 -> 0 | U8: =IFERROR(100%-(Q8/K8),"")
A9: 3 | C9: =IF($C$5=☆入力!$B$15,☆入力!$B18,☆入力!$C18) -> 0 | G9: =☆入力!D18 -> 0 | K9: =☆入力!Y18 -> 0 | O9: ➡ | Q9: =☆入力!AC18 -> 0 | U9: =IFERROR(100%-(Q9/K9),"") | AA9: =②前a!$AS$6 -> 0 | AJ9: ー | AN9: =③後a!AS6 -> 0 | AW9: ＝ | BA9: =AA9-AN9 -> 0
A10: 4 | C10: =IF($C$5=☆入力!$B$15,☆入力!$B19,☆入力!$C19) -> 0 | G10: =☆入力!D19 -> 0 | K10: =☆入力!Y19 -> 0 | O10: ➡ | Q10: =☆入力!AC19 -> 0 | U10: =IFERROR(100%-(Q10/K10),"")
A11: 5 | C11: =IF($C$5=☆入力!$B$15,☆入力!$B20,☆入力!$C20) -> 0 | G11: =☆入力!D20 -> 0 | K11: =☆入力!Y20 -> 0 | O11: ➡ | Q11: =☆入力!AC20 -> 0 | U11: =IFERROR(100%-(Q11/K11),"")
A12: 6 | C12: =IF($C$5=☆入力!$B$15,☆入力!$B21,☆入力!$C21) -> 0 | G12: =☆入力!D21 -> 0 | K12: =☆入力!Y21 -> 0 | O12: ➡ | Q12: =☆入力!AC21 -> 0 | U12: =IFERROR(100%-(Q12/K12),"") | AA12: + | AN12: + | BA12: +
A13: 7 | C13: =IF($C$5=☆入力!$B$15,☆入力!$B22,☆入力!$C22) -> 0 | G13: =☆入力!D22 -> 0 | K13: =☆入力!Y22 -> 0 | O13: ➡ | Q13: =☆入力!AC22 -> 0 | U13: =IFERROR(100%-(Q13/K13),"")
A14: 8 | C14: =IF($C$5=☆入力!$B$15,☆入力!$B23,☆入力!$C23) -> 0 | G14: =☆入力!D23 -> 0 | K14: =☆入力!Y23 -> 0 | O14: ➡ | Q14: =☆入力!AC23 -> 0 | U14: =IFERROR(100%-(Q14/K14),"")
A15: 9 | C15: =IF($C$5=☆入力!$B$15,☆入力!$B24,☆入力!$C24) -> 0 | G15: =☆入力!D24 -> 0 | K15: =☆入力!Y24 -> 0 | O15: ➡ | Q15: =☆入力!AC24 -> 0 | U15: =IFERROR(100%-(Q15/K15),"") | AA15: ②白熱球とLED照明の交換コストの比較
A16: 10 | C16: =IF($C$5=☆入力!$B$15,☆入力!$B25,☆入力!$C25) -> 0 | G16: =☆入力!D25 -> 0 | K16: =☆入力!Y25 -> 0 | O16: ➡ | Q16: =☆入力!AC25 -> 0 | U16: =IFERROR(100%-(Q16/K16),"")
A17: 11 | C17: =IF($C$5=☆入力!$B$15,☆入力!$B26,☆入力!$C26) -> 0 | G17: =☆入力!D26 -> 0 | K17: =☆入力!Y26 -> 0 | O17: ➡ | Q17: =☆入力!AC26 -> 0 | U17: =IFERROR(100%-(Q17/K17),"")
A18: 12 | C18: =IF($C$5=☆入力!$B$15,☆入力!$B27,☆入力!$C27) -> 0 | G18: =☆入力!D27 -> 0 | K18: =☆入力!Y27 -> 0 | O18: ➡ | Q18: =☆入力!AC27 -> 0 | U18: =IFERROR(100%-(Q18/K18),"") | AA18: =②前a!$AS$13 -> 0 | AJ18: ー | AN18: =③後a!AS13 -> 0 | AW18: ＝ | BA18: =AA18-AN18 -> 0
A19: 13 | C19: =IF($C$5=☆入力!$B$15,☆入力!$B28,☆入力!$C28) -> 0 | G19: =☆入力!D28 -> 0 | K19: =☆入力!Y28 -> 0 | O19: ➡ | Q19: =☆入力!AC28 -> 0 | U19: =IFERROR(100%-(Q19/K19),"")
A20: 14 | C20: =IF($C$5=☆入力!$B$15,☆入力!$B29,☆入力!$C29) -> 0 | G20: =☆入力!D29 -> 0 | K20: =☆入力!Y29 -> 0 | O20: ➡ | Q20: =☆入力!AC29 -> 0 | U20: =IFERROR(100%-(Q20/K20),"")
A21: 15 | C21: =IF($C$5=☆入力!$B$15,☆入力!$B30,☆入力!$C30) -> 0 | G21: =☆入力!D30 -> 0 | K21: =☆入力!Y30 -> 0 | O21: ➡ | Q21: =☆入力!AC30 -> 0 | U21: =IFERROR(100%-(Q21/K21),"")
A22: 16 | C22: =IF($C$5=☆入力!$B$15,☆入力!$B31,☆入力!$C31) -> 0 | G22: =☆入力!D31 -> 0 | K22: =☆入力!Y31 -> 0 | O22: ➡ | Q22: =☆入力!AC31 -> 0 | U22: =IFERROR(100%-(Q22/K22),"")
A23: 17 | C23: =IF($C$5=☆入力!$B$15,☆入力!$B32,☆入力!$C32) -> 0 | G23: =☆入力!D32 -> 0 | K23: =☆入力!Y32 -> 0 | O23: ➡ | Q23: =☆入力!AC32 -> 0 | U23: =IFERROR(100%-(Q23/K23),"")
A24: 18 | C24: =IF($C$5=☆入力!$B$15,☆入力!$B33,☆入力!$C33) -> 0 | G24: =☆入力!D33 -> 0 | K24: =☆入力!Y33 -> 0 | O24: ➡ | Q24: =☆入力!AC33 -> 0 | U24: =IFERROR(100%-(Q24/K24),"")
A25: 19 | C25: =IF($C$5=☆入力!$B$15,☆入力!$B34,☆入力!$C34) -> 0 | G25: =☆入力!D34 -> 0 | K25: =☆入力!Y34 -> 0 | O25: ➡ | Q25: =☆入力!AC34 -> 0 | U25: =IFERROR(100%-(Q25/K25),"")
A26: 20 | C26: =IF($C$5=☆入力!$B$15,☆入力!$B35,☆入力!$C35) -> 0 | G26: =☆入力!D35 -> 0 | K26: =☆入力!Y35 -> 0 | O26: ➡ | Q26: =☆入力!AC35 -> 0 | U26: =IFERROR(100%-(Q26/K26),"")
A27: 21 | C27: =IF($C$5=☆入力!$B$15,☆入力!$B36,☆入力!$C36) -> 0 | G27: =☆入力!D36 -> 0 | K27: =☆入力!Y36 -> 0 | O27: ➡ | Q27: =☆入力!AC36 -> 0 | U27: =IFERROR(100%-(Q27/K27),"") | AA27: ★既存照明とLED照明の10年間のランニングコスト比較
A28: 22 | C28: =IF($C$5=☆入力!$B$15,☆入力!$B37,☆入力!$C37) -> 0 | G28: =☆入力!D37 -> 0 | K28: =☆入力!Y37 -> 0 | O28: ➡ | Q28: =☆入力!AC37 -> 0 | U28: =IFERROR(100%-(Q28/K28),"")
A29: 23 | C29: =IF($C$5=☆入力!$B$15,☆入力!$B38,☆入力!$C38) -> 0 | G29: =☆入力!D38 -> 0 | K29: =☆入力!Y38 -> 0 | O29: ➡ | Q29: =☆入力!AC38 -> 0 | U29: =IFERROR(100%-(Q29/K29),"") | AA29: =AA9+AA18 -> 0 | AJ29: ー | AN29: =AN9+AN18 -> 0 | AW29: ＝ | BA29: =AA29-AN29 -> 0
A30: 24 | C30: =IF($C$5=☆入力!$B$15,☆入力!$B39,☆入力!$C39) -> 0 | G30: =☆入力!D39 -> 0 | K30: =☆入力!Y39 -> 0 | O30: ➡ | Q30: =☆入力!AC39 -> 0 | U30: =IFERROR(100%-(Q30/K30),"")
A31: 25 | C31: =IF($C$5=☆入力!$B$15,☆入力!$B40,☆入力!$C40) -> 0 | G31: =☆入力!D40 -> 0 | K31: =☆入力!Y40 -> 0 | O31: ➡ | Q31: =☆入力!AC40 -> 0 | U31: =IFERROR(100%-(Q31/K31),"")
A32: 26 | C32: =IF($C$5=☆入力!$B$15,☆入力!$B41,☆入力!$C41) -> 0 | G32: =☆入力!D41 -> 0 | K32: =☆入力!Y41 -> 0 | O32: ➡ | Q32: =☆入力!AC41 -> 0 | U32: =IFERROR(100%-(Q32/K32),"") | Z32: 備考：
A33: 27 | C33: =IF($C$5=☆入力!$B$15,☆入力!$B42,☆入力!$C42) -> 0 | G33: =☆入力!D42 -> 0 | K33: =☆入力!Y42 -> 0 | O33: ➡ | Q33: =☆入力!AC42 -> 0 | U33: =IFERROR(100%-(Q33/K33),"") | Z33: =☆入力!X2 -> 0
A34: 28 | C34: =IF($C$5=☆入力!$B$15,☆入力!$B43,☆入力!$C43) -> 0 | G34: =☆入力!D43 -> 0 | K34: =☆入力!Y43 -> 0 | O34: ➡ | Q34: =☆入力!AC43 -> 0 | U34: =IFERROR(100%-(Q34/K34),"") | Z34: =☆入力!X3 -> 0
A35: 29 | C35: =IF($C$5=☆入力!$B$15,☆入力!$B44,☆入力!$C44) -> 0 | G35: =☆入力!D44 -> 0 | K35: =☆入力!Y44 -> 0 | O35: ➡ | Q35: =☆入力!AC44 -> 0 | U35: =IFERROR(100%-(Q35/K35),"") | Z35: =☆入力!X4 -> 0
A36: 30 | C36: =IF($C$5=☆入力!$B$15,☆入力!$B45,☆入力!$C45) -> 0 | G36: =☆入力!D45 -> 0 | K36: =☆入力!Y45 -> 0 | O36: ➡ | Q36: =☆入力!AC45 -> 0 | U36: =IFERROR(100%-(Q36/K36),"") | Z36: =☆入力!X5 -> 0
Z37: =☆入力!X6 -> 0
K38: =SUM(K7:N36) -> 0 | O38: ➡ | Q38: =SUM(Q7:T36) -> 0 | U38: =IFERROR(100%-(Q38/K38),"") | Z38: =☆入力!X7 -> 0
Z39: =☆入力!X8 -> 0
Z40: =☆入力!X9 -> 0
A41: ★電気代だけでみた毎月の削減金額・・・・ | Q41: =K38-Q38 -> 0 | Z41: =☆入力!X10 -> 0
Z42: =☆入力!X11 -> 0
A44: 【免責】本資料に記載された内容は、一定条件下における試算結果であり数値等を保証するものでは御座いません。 | BI44: 7

Sheet ⑦一式
A1: 御見積書 | F1: 発行日： | G1: =TODAY() -> 46080
A4: =☆入力!C5 -> 0
E6: =IF(代理店入力用!N3="",①表紙!I25,代理店入力用!N3) -> 株式会社ニッショー
A7: この度は、御見積もりのご依頼を頂き誠にありがとうございます。 | E7: =IF(代理店入力用!N5="",①表紙!I26,①表紙!A26) -> 〒151-0071 東京都渋谷区本町2-6-3 D'sVARIE初台ビル3F
A8: 下記の通りＬＥＤ照明改修工事の御見積もり申し上げます。 | E8: =IF(代理店入力用!N6="",①表紙!I27,①表紙!A27) -> TEL： 管理担当営業所へお問い合わせ下さい。
A9: 何卒ご用命賜りますようお願い申し上げます。
I10: リース金額(税抜)： | J10: =ROUNDDOWN(F26*LED計算式!AC2,0) -> 0
A11: 内容： | B11: 共用部分照明のＬＥＤ改修工事 | E11: リース金額(税込)： | F11: =VLOOKUP(E11,I10:J11,2,FALSE) -> 0 | G11: ="×"&LED計算式!AD2&"ヵ月" -> ×120ヵ月 | I11: リース金額(税込)： | J11: =ROUNDDOWN(J10*1.1,0) -> 0
A12: 有効期限： | B12: 発行日より1ヵ月 | I12: 一括購入金額(税抜)： | J12: =F26 -> 0
E13: 一括購入金額(税込)： | F13: =VLOOKUP(E13,I12:J13,2,FALSE) -> 0 | I13: 一括購入金額(税込)： | J13: =ROUNDDOWN(J12*1.1,0) -> 0
H15: ←税込の場合は消すの忘れないように注意
A17: No. | B17: 内容 | D17: 数量 | E17: 単価 | F17: 小計
A18: 1 | B18: ＬＥＤ照明一式 | D18: 1 | E18: =☆入力!AL14+代理店入力用!D5 -> 0 | F18: =E18*D18 -> 0
A19: 2 | B19: （工事費 / 廃棄費等 込み） | F19: =E19*D19 -> 0
A20: 3 | F20: =E20*D20 -> 0
A21: 4 | F21: =E21*D21 -> 0
A22: 5 | F22: =E22*D22 -> 0
A23: 6 | F23: =E23*D23 -> 0
A24: 7
A25: 8 | F25: =E25*D25 -> 0
E26: 小計 | F26: =ROUNDDOWN(SUM(F18:G25),0) -> 0
A27: 【備考】
A28: =☆入力!AH4 -> 生産終了品などがあった場合、同メーカーもしくは他メーカーの同等品に変更される場合がございます。
A29: =☆入力!AH5 -> 新しい照明器具が、既設よりも一回り小さくなるケースがあり、その際は外壁塗装面が露出する
A30: =☆入力!AH6 -> 可能性がございます。
A33: 内訳明細書①
A36: No. | B36: 物件名 | C36: 試算エリア | D36: 電球種別 | G36: 数量
A37: 1 | B37: =☆入力!B16 | C37: =☆入力!C16 -> 0 | D37: =☆入力!D16 -> 0 | G37: =☆入力!L16 -> 0
A38: 2 | B38: =☆入力!B17 | C38: =☆入力!C17 -> 0 | D38: =☆入力!D17 -> 0 | G38: =☆入力!L17 -> 0
A39: 3 | B39: =☆入力!B18 | C39: =☆入力!C18 -> 0 | D39: =☆入力!D18 -> 0 | G39: =☆入力!L18 -> 0
A40: 4 | B40: =☆入力!B19 | C40: =☆入力!C19 -> 0 | D40: =☆入力!D19 -> 0 | G40: =☆入力!L19 -> 0
A41: 5 | B41: =☆入力!B20 | C41: =☆入力!C20 -> 0 | D41: =☆入力!D20 -> 0 | G41: =☆入力!L20 -> 0
A42: 6 | B42: =☆入力!B21 | C42: =☆入力!C21 -> 0 | D42: =☆入力!D21 -> 0 | G42: =☆入力!L21 -> 0
A43: 7 | B43: =☆入力!B22 | C43: =☆入力!C22 -> 0 | D43: =☆入力!D22 -> 0 | G43: =☆入力!L22 -> 0
A44: 8 | B44: =☆入力!B23 | C44: =☆入力!C23 -> 0 | D44: =☆入力!D23 -> 0 | G44: =☆入力!L23 -> 0
A45: 9 | B45: =☆入力!B24 | C45: =☆入力!C24 -> 0 | D45: =☆入力!D24 -> 0 | G45: =☆入力!L24 -> 0
A46: 10 | B46: =☆入力!B25 | C46: =☆入力!C25 -> 0 | D46: =☆入力!D25 -> 0 | G46: =☆入力!L25 -> 0
A47: 11 | B47: =☆入力!B26 | C47: =☆入力!C26 -> 0 | D47: =☆入力!D26 -> 0 | G47: =☆入力!L26 -> 0
A48: 12 | B48: =☆入力!B27 | C48: =☆入力!C27 -> 0 | D48: =☆入力!D27 -> 0 | G48: =☆入力!L27 -> 0
... A61: 25 | B61: =☆入力!B40 | C61: =☆入力!C40 -> 0 | D61: =☆入力!D40 -> 0 | G61: =☆入力!L40 -> 0
A63: 内訳明細書②
A66: No. | B66: 交換種別 | C66: 試算エリア | D66: 電球種別 | G66: 数量
A67: 26
A68: 27
A69: 28
A70: 29
A71: 30
A72: 31
A73: 32
A74: 33
A75: 34
A76: 35
A77: 36
A78: 37
... A91: 50

Sheet ✖⑤複数
A1: 御見積書 | F1: 発行日： | G1: =TODAY() -> 46080
A3: =☆入力!C5 -> 0 | E3: =IF(代理店入力用!N3="",①表紙!I25,代理店入力用!N3) -> 株式会社ニッショー
E4: =IF(代理店入力用!N5="",①表紙!I26,①表紙!A26) -> 〒151-0071 東京都渋谷区本町2-6-3 D'sVARIE初台ビル3F
E5: =IF(代理店入力用!N6="",①表紙!I27,①表紙!A27) -> TEL： 管理担当営業所へお問い合わせ下さい。 | I5: リース金額(税抜)： | J5: =G35 -> 0
A6: この度は、御見積もりのご依頼を頂き誠にありがとうございます。 | I6: リース金額(税込)： | J6: =J5*1.1 -> 0
A7: 下記の通りＬＥＤ照明改修工事の御見積もり申し上げます。 | E7: 一括購入金額(税込)： | G7: リース金額(税込)： | I7: 一括購入金額(税抜)： | J7: =E35 -> 0
E8: =VLOOKUP(E7,I7:J8,2,FALSE) -> 0 | G8: =VLOOKUP(G7,I5:J6,2,FALSE) -> 0 | I8: 一括購入金額(税込)： | J8: =J7*1.1 -> 0
A9: ※複数棟キャンペーンの適応は発行日より1ヵ月間となります。
H10: ←税込の場合は消すの忘れないように注意
A11: No. | B11: 物件名 / 内容 | D11: 電球数 | E11: 小計(購入価格) | G11: 小計(リース代/月)
A12: 1 | B12: =☆入力!AG16 -> 0 | D12: =☆入力!AH16 -> 0 | E12: =☆入力!AL16+LED計算式!X4 -> 0 | G12: =ROUNDDOWN(☆入力!AK16+LED計算式!Y4,0) -> 0
A13: 2 | B13: =☆入力!AG17 -> 0 | D13: =☆入力!AH17 -> 0 | E13: =☆入力!AL17+LED計算式!X5 -> 0 | G13: =ROUNDDOWN(☆入力!AK17+LED計算式!Y5,0) -> 0
A14: 3 | B14: =☆入力!AG18 -> 0 | D14: =☆入力!AH18 -> 0 | E14: =☆入力!AL18+LED計算式!X6 -> 0 | G14: =ROUNDDOWN(☆入力!AK18+LED計算式!Y6,0) -> 0
A15: 4 | B15: =☆入力!AG19 -> 0 | D15: =☆入力!AH19 -> 0 | E15: =☆入力!AL19+LED計算式!X7 -> 0 | G15: =ROUNDDOWN(☆入力!AK19+LED計算式!Y7,0) -> 0
A16: 5 | B16: =☆入力!AG20 -> 0 | D16: =☆入力!AH20 -> 0 | E16: =☆入力!AL20+LED計算式!X8 -> 0 | G16: =ROUNDDOWN(☆入力!AK20+LED計算式!Y8,0) -> 0
A17: 6 | B17: =☆入力!AG21 -> 0 | D17: =☆入力!AH21 -> 0 | E17: =☆入力!AL21+LED計算式!X9 -> 0 | G17: =ROUNDDOWN(☆入力!AK21+LED計算式!Y9,0) -> 0
A18: 7 | B18: =☆入力!AG22 -> 0 | D18: =☆入力!AH22 -> 0 | E18: =☆入力!AL22+LED計算式!X10 -> 0 | G18: =ROUNDDOWN(☆入力!AK22+LED計算式!Y10,0) -> 0
A19: 8 | B19: =☆入力!AG23 -> 0 | D19: =☆入力!AH23 -> 0 | E19: =☆入力!AL23+LED計算式!X11 -> 0 | G19: =ROUNDDOWN(☆入力!AK23+LED計算式!Y11,0) -> 0
A20: 9 | B20: =☆入力!AG24 -> 0 | D20: =☆入力!AH24 -> 0 | E20: =☆入力!AL24+LED計算式!X12 -> 0 | G20: =ROUNDDOWN(☆入力!AK24+LED計算式!Y12,0) -> 0
A21: 10 | B21: =☆入力!AG25 -> 0 | D21: =☆入力!AH25 -> 0 | E21: =☆入力!AL25+LED計算式!X13 -> 0 | G21: =ROUNDDOWN(☆入力!AK25+LED計算式!Y13,0) -> 0
A22: 11 | B22: =☆入力!AG26 -> 0 | D22: =☆入力!AH26 -> 0 | E22: =☆入力!AL26+LED計算式!X14 -> 0 | G22: =ROUNDDOWN(☆入力!AK26+LED計算式!Y14,0) -> 0
A23: 12 | B23: =☆入力!AG27 -> 0 | D23: =☆入力!AH27 -> 0 | E23: =☆入力!AL27+LED計算式!X15 -> 0 | G23: =ROUNDDOWN(☆入力!AK27+LED計算式!Y15,0) -> 0
... A31: 20 | B31: =☆入力!AG35 -> 0 | D31: =☆入力!AH35 -> 0 | E31: =☆入力!AL35+LED計算式!X23 -> 0 | G31: =ROUNDDOWN(☆入力!AK35+LED計算式!Y23,0) -> 0
A32: =☆入力!AH12 -> 0 | D32: =IF(☆入力!AH12<>"","1","") | E32: =☆入力!AJ12 -> 0 | G32: =ROUNDDOWN(☆入力!AK36+LED計算式!Y24,0) -> 0
A33: ="複数棟キャンペーン割引（ "&TEXT(☆入力!AR11,"0%")&" OFF ）" -> 複数棟キャンペーン割引（ 0% OFF ） | D33: 1 | E33: =-(☆入力!AL14*☆入力!AR11) -> 0 | G33: =E33/54 -> 0
D35: 合計: | E35: =ROUNDDOWN(SUM(E12:E33),0) -> 0 | G35: =ROUNDDOWN(SUM(G12:G33),0) -> 0
A36: ※月額リース代(税抜)が2,728円未満の場合にはリース契約は不可となりますが、複数棟をまとめて税抜2,728円以上の場合には可能となります。

Sheet ✖⑤複数+詳細
A1: 御見積書 | G1: 発行日： | H1: =TODAY() -> 46080
A3: =☆入力!C5 -> 0
F4: =IF(代理店入力用!N3="",①表紙!I25,代理店入力用!N3) -> 株式会社ニッショー
F5: =IF(代理店入力用!N5="",①表紙!I26,①表紙!A26) -> 〒151-0071 東京都渋谷区本町2-6-3 D'sVARIE初台ビル3F
A6: この度は、御見積もりのご依頼を頂き誠にありがとうございます。 | F6: =IF(代理店入力用!N6="",①表紙!I27,①表紙!A27) -> TEL： 管理担当営業所へお問い合わせ下さい。
A7: 下記の通りＬＥＤ照明改修工事の御見積もり申し上げます。何卒ご用命賜りますようお願い申し上げます。
A9: 物件名 | B9: 試算エリア | C9: メーカー | D9: 照明種別 | E9: 電球数 | F9: 定価 | G9: 小計 | J9: リース金額(税抜)： | K9: =ROUNDDOWN(G57/54,0) -> 0
A10: =☆入力!B16 | B10: =☆入力!C16 -> 0 | C10: =IFERROR(VLOOKUP(☆入力!G16,選定!$C$3:$AG$100,11,FALSE),"") | D10: =IFERROR(VLOOKUP(☆入力!G16,選定!$C$3:$AG$100,1,FALSE),"") | E10: =☆入力!L16 -> 0 | F10: =IFERROR(VLOOKUP(☆入力!G16,選定!$C$3:$AG$100,7,FALSE),"") | G10: =IFERROR(F10*E10,"") | J10: リース金額(税込)： | K10: =K9*1.1 -> 0
A11: =☆入力!B17 | B11: =☆入力!C17 -> 0 | C11: =IFERROR(VLOOKUP(☆入力!G17,選定!$C$3:$AG$100,11,FALSE),"") | D11: =IFERROR(VLOOKUP(☆入力!G17,選定!$C$3:$AG$100,1,FALSE),"") | E11: =☆入力!L17 -> 0 | F11: =IFERROR(VLOOKUP(☆入力!G17,選定!$C$3:$AG$100,7,FALSE),"") | G11: =IFERROR(F11*E11,"") | J11: 一括購入金額(税抜)： | K11: =G57 -> 0
A12: =☆入力!B18 | B12: =☆入力!C18 -> 0 | C12: =IFERROR(VLOOKUP(☆入力!G18,選定!$C$3:$AG$100,11,FALSE),"") | D12: =IFERROR(VLOOKUP(☆入力!G18,選定!$C$3:$AG$100,1,FALSE),"") | E12: =☆入力!L18 -> 0 | F12: =IFERROR(VLOOKUP(☆入力!G18,選定!$C$3:$AG$100,7,FALSE),"") | G12: =IFERROR(F12*E12,"") | J12: 一括購入金額(税込)： | K12: =K11*1.1 -> 0
A13: =☆入力!B19 | B13: =☆入力!C19 -> 0 | C13: =IFERROR(VLOOKUP(☆入力!G19,選定!$C$3:$AG$100,11,FALSE),"") | D13: =IFERROR(VLOOKUP(☆入力!G19,選定!$C$3:$AG$100,1,FALSE),"") | E13: =☆入力!L19 -> 0 | F13: =IFERROR(VLOOKUP(☆入力!G19,選定!$C$3:$AG$100,7,FALSE),"") | G13: =IFERROR(F13*E13,"")
A14: =☆入力!B20 | B14: =☆入力!C20 -> 0 | C14: =IFERROR(VLOOKUP(☆入力!G20,選定!$C$3:$AG$100,11,FALSE),"") | D14: =IFERROR(VLOOKUP(☆入力!G20,選定!$C$3:$AG$100,1,FALSE),"") | E14: =☆入力!L20 -> 0 | F14: =IFERROR(VLOOKUP(☆入力!G20,選定!$C$3:$AG$100,7,FALSE),"") | G14: =IFERROR(F14*E14,"")
A15: =☆入力!B21 | B15: =☆入力!C21 -> 0 | C15: =IFERROR(VLOOKUP(☆入力!G21,選定!$C$3:$AG$100,11,FALSE),"") | D15: =IFERROR(VLOOKUP(☆入力!G21,選定!$C$3:$AG$100,1,FALSE),"") | E15: =☆入力!L21 -> 0 | F15: =IFERROR(VLOOKUP(☆入力!G21,選定!$C$3:$AG$100,7,FALSE),"") | G15: =IFERROR(F15*E15,"")
A16: =☆入力!B22 | B16: =☆入力!C22 -> 0 | C16: =IFERROR(VLOOKUP(☆入力!G22,選定!$C$3:$AG$100,11,FALSE),"") | D16: =IFERROR(VLOOKUP(☆入力!G22,選定!$C$3:$AG$100,1,FALSE),"") | E16: =☆入力!L22 -> 0 | F16: =IFERROR(VLOOKUP(☆入力!G22,選定!$C$3:$AG$100,7,FALSE),"") | G16: =IFERROR(F16*E16,"")
A17: =☆入力!B23 | B17: =☆入力!C23 -> 0 | C17: =IFERROR(VLOOKUP(☆入力!G23,選定!$C$3:$AG$100,11,FALSE),"") | D17: =IFERROR(VLOOKUP(☆入力!G23,選定!$C$3:$AG$100,1,FALSE),"") | E17: =☆入力!L23 -> 0 | F17: =IFERROR(VLOOKUP(☆入力!G23,選定!$C$3:$AG$100,7,FALSE),"") | G17: =IFERROR(F17*E17,"")
A18: =☆入力!B24 | B18: =☆入力!C24 -> 0 | C18: =IFERROR(VLOOKUP(☆入力!G24,選定!$C$3:$AG$100,11,FALSE),"") | D18: =IFERROR(VLOOKUP(☆入力!G24,選定!$C$3:$AG$100,1,FALSE),"") | E18: =☆入力!L24 -> 0 | F18: =IFERROR(VLOOKUP(☆入力!G24,選定!$C$3:$AG$100,7,FALSE),"") | G18: =IFERROR(F18*E18,"")
A19: =☆入力!B25 | B19: =☆入力!C25 -> 0 | C19: =IFERROR(VLOOKUP(☆入力!G25,選定!$C$3:$AG$100,11,FALSE),"") | D19: =IFERROR(VLOOKUP(☆入力!G25,選定!$C$3:$AG$100,1,FALSE),"") | E19: =☆入力!L25 -> 0 | F19: =IFERROR(VLOOKUP(☆入力!G25,選定!$C$3:$AG$100,7,FALSE),"") | G19: =IFERROR(F19*E19,"")
A20: =☆入力!B26 | B20: =☆入力!C26 -> 0 | C20: =IFERROR(VLOOKUP(☆入力!G26,選定!$C$3:$AG$100,11,FALSE),"") | D20: =IFERROR(VLOOKUP(☆入力!G26,選定!$C$3:$AG$100,1,FALSE),"") | E20: =☆入力!L26 -> 0 | F20: =IFERROR(VLOOKUP(☆入力!G26,選定!$C$3:$AG$100,7,FALSE),"") | G20: =IFERROR(F20*E20,"")
A21: =☆入力!B27 | B21: =☆入力!C27 -> 0 | C21: =IFERROR(VLOOKUP(☆入力!G27,選定!$C$3:$AG$100,11,FALSE),"") | D21: =IFERROR(VLOOKUP(☆入力!G27,選定!$C$3:$AG$100,1,FALSE),"") | E21: =☆入力!L27 -> 0 | F21: =IFERROR(VLOOKUP(☆入力!G27,選定!$C$3:$AG$100,7,FALSE),"") | G21: =IFERROR(F21*E21,"")
A22: =☆入力!B28 | B22: =☆入力!C28 -> 0 | C22: =IFERROR(VLOOKUP(☆入力!G28,選定!$C$3:$AG$100,11,FALSE),"") | D22: =IFERROR(VLOOKUP(☆入力!G28,選定!$C$3:$AG$100,1,FALSE),"") | E22: =☆入力!L28 -> 0 | F22: =IFERROR(VLOOKUP(☆入力!G28,選定!$C$3:$AG$100,7,FALSE),"") | G22: =IFERROR(F22*E22,"")
A23: =☆入力!B29 | B23: =☆入力!C29 -> 0 | C23: =IFERROR(VLOOKUP(☆入力!G29,選定!$C$3:$AG$100,11,FALSE),"") | D23: =IFERROR(VLOOKUP(☆入力!G29,選定!$C$3:$AG$100,1,FALSE),"") | E23: =☆入力!L29 -> 0 | F23: =IFERROR(VLOOKUP(☆入力!G29,選定!$C$3:$AG$100,7,FALSE),"") | G23: =IFERROR(F23*E23,"")
A24: =☆入力!B30 | B24: =☆入力!C30 -> 0 | C24: =IFERROR(VLOOKUP(☆入力!G30,選定!$C$3:$AG$100,11,FALSE),"") | D24: =IFERROR(VLOOKUP(☆入力!G30,選定!$C$3:$AG$100,1,FALSE),"") | E24: =☆入力!L30 -> 0 | F24: =IFERROR(VLOOKUP(☆入力!G30,選定!$C$3:$AG$100,7,FALSE),"") | G24: =IFERROR(F24*E24,"")
... A39: =☆入力!B45 | B39: =☆入力!C45 -> 0 | C39: =IFERROR(VLOOKUP(☆入力!G45,選定!$C$3:$AG$100,11,FALSE),"") | D39: =IFERROR(VLOOKUP(☆入力!G45,選定!$C$3:$AG$100,1,FALSE),"") | E39: =☆入力!L45 -> 0 | F39: =IFERROR(VLOOKUP(☆入力!G45,選定!$C$3:$AG$100,7,FALSE),"") | G39: =IFERROR(F39*E39,"")
A40: 小計 | E40: 1 | G40: =SUM(G10:H39) -> 0
A41: お値引き | E41: 1 | G41: =(☆入力!AL14+代理店入力用!D5)-SUM(G40,G46:H54) -> -28000
A42: ="複数棟キャンペーン割引（ "&TEXT(☆入力!AR11,"0%")&" ＯＦＦ）" -> 複数棟キャンペーン割引（ 0% ＯＦＦ） | E42: 1 | G42: =-(☆入力!AL14*☆入力!AR11) -> 0
F43: 商品代合計 | G43: =SUM(G40:H42) -> -28000
A45: 施工内容 | E45: 数量 | F45: 単価 | G45: 小計
A46: 工事費人工 | E46: =VLOOKUP(☆入力!L14,LED計算式!M21:N26,2,TRUE) -> 1 | F46: 20000 | G46: =IFERROR(F46*E46,"") -> 20000
A47: 通常施工費 | E47: =LED計算式!O36 -> 0 | F47: 3000 | G47: =IFERROR(F47*E47,"") -> 0
A48: 施工費 (非常灯別置工事) | E48: =LED計算式!O37 -> 0 | F48: 4500 | G48: =IFERROR(F48*E48,"") -> 0
A49: 施工費 (配線直結工事） | E49: =LED計算式!O38 -> 0 | F49: 2000 | G49: =IFERROR(F49*E49,"") -> 0
A50: 施工費 (ランプ交換） | E50: =LED計算式!O39 -> 0 | F50: 600 | G50: =IFERROR(F50*E50,"") -> 0
A51: 諸経費 | E51: =COUNTA(☆入力!AG16:AG45) -> 1 | F51: 3000 | G51: =IFERROR(F51*E51,"") -> 3000
A52: 廃棄代 | E52: =SUM(E47:E49) -> 0 | F52: 1000 | G52: =IFERROR(F52*E52,"") -> 0
A53: 交通費 | E53: =COUNTA(☆入力!AG16:AG45) -> 1 | F53: 5000 | G53: =IFERROR(F53*E53,"") -> 5000
A54: =☆入力!AH12 -> 0 | E54: =IF(☆入力!AH12<>"","1","") | F54: =☆入力!AJ12 -> 0 | G54: =IFERROR(F54*E54,"")
F55: 工事費合計 | G55: =SUM(G46:H54) -> 28000
A56: 【備考】
A57: =☆入力!AH4 -> 生産終了品などがあった場合、同メーカーもしくは他メーカーの同等品に変更される場合がございます。 | F57: 商品代 + 工事代 | G57: =ROUNDDOWN(G43+G55,0) -> 0
A59: =☆入力!AH5 -> 新しい照明器具が、既設よりも一回り小さくなるケースがあり、その際は外壁塗装面が露出する | F59: 一括購入金額(税抜)： | G59: =VLOOKUP(F59,J11:K12,2,FALSE) -> 0
A61: =☆入力!AH6 -> 可能性がございます。 | F61: リース金額(税抜)： | G61: =VLOOKUP(F61,J9:K10,2,FALSE) -> 0 | H61: ×60ヵ月
F63: ※消費税は別途申し受けいたします。 | I63: ←税込の場合は消すの忘れないように注意

Sheet ✖⑤詳細
A1: 御見積書 | F1: 発行日： | G1: =TODAY() -> 46080
A3: =☆入力!C5 -> 0
E4: =IF(代理店入力用!N3="",①表紙!I25,代理店入力用!N3) -> 株式会社ニッショー
E5: =IF(代理店入力用!N5="",①表紙!I26,①表紙!A26) -> 〒151-0071 東京都渋谷区本町2-6-3 D'sVARIE初台ビル3F
A6: この度は、御見積もりのご依頼を頂き誠にありがとうございます。 | E6: =IF(代理店入力用!N6="",①表紙!I27,①表紙!A27) -> TEL： 管理担当営業所へお問い合わせ下さい。
A7: 下記の通りＬＥＤ照明改修工事の御見積もり申し上げます。何卒ご用命賜りますようお願い申し上げます。
A9: No. | B9: メーカー | C9: 照明種別 | D9: 電球数 | E9: 定価 | F9: 小計 | I9: リース金額(税抜)： | J9: =ROUNDDOWN(F56/54,0) -> 0
A10: 1 | B10: =IFERROR(VLOOKUP(☆入力!G16,選定!$C$3:$AG$100,11,FALSE),"") | C10: =IFERROR(VLOOKUP(☆入力!G16,選定!$C$3:$AG$100,1,FALSE),"") | D10: =☆入力!L16 -> 0 | E10: =IFERROR(VLOOKUP(☆入力!G16,選定!$C$3:$AG$100,7,FALSE),"") | F10: =IFERROR(E10*D10,"") | I10: リース金額(税込)： | J10: =J9*1.1 -> 0
A11: 2 | B11: =IFERROR(VLOOKUP(☆入力!G17,選定!$C$3:$AG$100,11,FALSE),"") | C11: =IFERROR(VLOOKUP(☆入力!G17,選定!$C$3:$AG$100,1,FALSE),"") | D11: =☆入力!L17 -> 0 | E11: =IFERROR(VLOOKUP(☆入力!G17,選定!$C$3:$AG$100,7,FALSE),"") | F11: =IFERROR(E11*D11,"") | I11: 一括購入金額(税抜)： | J11: =F56 -> 0
A12: 3 | B12: =IFERROR(VLOOKUP(☆入力!G18,選定!$C$3:$AG$100,11,FALSE),"") | C12: =IFERROR(VLOOKUP(☆入力!G18,選定!$C$3:$AG$100,1,FALSE),"") | D12: =☆入力!L18 -> 0 | E12: =IFERROR(VLOOKUP(☆入力!G18,選定!$C$3:$AG$100,7,FALSE),"") | F12: =IFERROR(E12*D12,"") | I12: 一括購入金額(税込)： | J12: =J11*1.1 -> 0
A13: 4 | B13: =IFERROR(VLOOKUP(☆入力!G19,選定!$C$3:$AG$100,11,FALSE),"") | C13: =IFERROR(VLOOKUP(☆入力!G19,選定!$C$3:$AG$100,1,FALSE),"") | D13: =☆入力!L19 -> 0 | E13: =IFERROR(VLOOKUP(☆入力!G19,選定!$C$3:$AG$100,7,FALSE),"") | F13: =IFERROR(E13*D13,"")
A14: 5 | B14: =IFERROR(VLOOKUP(☆入力!G20,選定!$C$3:$AG$100,11,FALSE),"") | C14: =IFERROR(VLOOKUP(☆入力!G20,選定!$C$3:$AG$100,1,FALSE),"") | D14: =☆入力!L20 -> 0 | E14: =IFERROR(VLOOKUP(☆入力!G20,選定!$C$3:$AG$100,7,FALSE),"") | F14: =IFERROR(E14*D14,"")
A15: 6 | B15: =IFERROR(VLOOKUP(☆入力!G21,選定!$C$3:$AG$100,11,FALSE),"") | C15: =IFERROR(VLOOKUP(☆入力!G21,選定!$C$3:$AG$100,1,FALSE),"") | D15: =☆入力!L21 -> 0 | E15: =IFERROR(VLOOKUP(☆入力!G21,選定!$C$3:$AG$100,7,FALSE),"") | F15: =IFERROR(E15*D15,"")
A16: 7 | B16: =IFERROR(VLOOKUP(☆入力!G22,選定!$C$3:$AG$100,11,FALSE),"") | C16: =IFERROR(VLOOKUP(☆入力!G22,選定!$C$3:$AG$100,1,FALSE),"") | D16: =☆入力!L22 -> 0 | E16: =IFERROR(VLOOKUP(☆入力!G22,選定!$C$3:$AG$100,7,FALSE),"") | F16: =IFERROR(E16*D16,"")
A17: 8 | B17: =IFERROR(VLOOKUP(☆入力!G23,選定!$C$3:$AG$100,11,FALSE),"") | C17: =IFERROR(VLOOKUP(☆入力!G23,選定!$C$3:$AG$100,1,FALSE),"") | D17: =☆入力!L23 -> 0 | E17: =IFERROR(VLOOKUP(☆入力!G23,選定!$C$3:$AG$100,7,FALSE),"") | F17: =IFERROR(E17*D17,"")
A18: 9 | B18: =IFERROR(VLOOKUP(☆入力!G24,選定!$C$3:$AG$100,11,FALSE),"") | C18: =IFERROR(VLOOKUP(☆入力!G24,選定!$C$3:$AG$100,1,FALSE),"") | D18: =☆入力!L24 -> 0 | E18: =IFERROR(VLOOKUP(☆入力!G24,選定!$C$3:$AG$100,7,FALSE),"") | F18: =IFERROR(E18*D18,"")
A19: 10 | B19: =IFERROR(VLOOKUP(☆入力!G25,選定!$C$3:$AG$100,11,FALSE),"") | C19: =IFERROR(VLOOKUP(☆入力!G25,選定!$C$3:$AG$100,1,FALSE),"") | D19: =☆入力!L25 -> 0 | E19: =IFERROR(VLOOKUP(☆入力!G25,選定!$C$3:$AG$100,7,FALSE),"") | F19: =IFERROR(E19*D19,"")
A20: 11 | B20: =IFERROR(VLOOKUP(☆入力!G26,選定!$C$3:$AG$100,11,FALSE),"") | C20: =IFERROR(VLOOKUP(☆入力!G26,選定!$C$3:$AG$100,1,FALSE),"") | D20: =☆入力!L26 -> 0 | E20: =IFERROR(VLOOKUP(☆入力!G26,選定!$C$3:$AG$100,7,FALSE),"") | F20: =IFERROR(E20*D20,"")
A21: 12 | B21: =IFERROR(VLOOKUP(☆入力!G27,選定!$C$3:$AG$100,11,FALSE),"") | C21: =IFERROR(VLOOKUP(☆入力!G27,選定!$C$3:$AG$100,1,FALSE),"") | D21: =☆入力!L27 -> 0 | E21: =IFERROR(VLOOKUP(☆入力!G27,選定!$C$3:$AG$100,7,FALSE),"") | F21: =IFERROR(E21*D21,"")
A22: 13 | B22: =IFERROR(VLOOKUP(☆入力!G28,選定!$C$3:$AG$100,11,FALSE),"") | C22: =IFERROR(VLOOKUP(☆入力!G28,選定!$C$3:$AG$100,1,FALSE),"") | D22: =☆入力!L28 -> 0 | E22: =IFERROR(VLOOKUP(☆入力!G28,選定!$C$3:$AG$100,7,FALSE),"") | F22: =IFERROR(E22*D22,"")
A23: 14 | B23: =IFERROR(VLOOKUP(☆入力!G29,選定!$C$3:$AG$100,11,FALSE),"") | C23: =IFERROR(VLOOKUP(☆入力!G29,選定!$C$3:$AG$100,1,FALSE),"") | D23: =☆入力!L29 -> 0 | E23: =IFERROR(VLOOKUP(☆入力!G29,選定!$C$3:$AG$100,7,FALSE),"") | F23: =IFERROR(E23*D23,"")
A24: 15 | B24: =IFERROR(VLOOKUP(☆入力!G30,選定!$C$3:$AG$100,11,FALSE),"") | C24: =IFERROR(VLOOKUP(☆入力!G30,選定!$C$3:$AG$100,1,FALSE),"") | D24: =☆入力!L30 -> 0 | E24: =IFERROR(VLOOKUP(☆入力!G30,選定!$C$3:$AG$100,7,FALSE),"") | F24: =IFERROR(E24*D24,"")
... A39: 30 | B39: =IFERROR(VLOOKUP(☆入力!G45,選定!$C$3:$AG$100,11,FALSE),"") | C39: =IFERROR(VLOOKUP(☆入力!G45,選定!$C$3:$AG$100,1,FALSE),"") | D39: =☆入力!L45 -> 0 | E39: =IFERROR(VLOOKUP(☆入力!G45,選定!$C$3:$AG$100,7,FALSE),"") | F39: =IFERROR(E39*D39,"")
A40: 小計 | D40: 1 | F40: =SUM(F10:G39) -> 0
A41: お値引き | D41: 1 | F41: =(☆入力!AL14+代理店入力用!D5)-SUM(F40,F45:G53) -> -28000
E42: 商品代合計 | F42: =SUM(F40:G41) -> -28000
A44: 施工内容 | D44: 数量 | E44: 単価 | F44: 小計
A45: 工事費人工 | D45: =VLOOKUP(☆入力!L14,LED計算式!M21:N27,2,TRUE) -> 1 | E45: 20000 | F45: =IFERROR(E45*D45,"") -> 20000
A46: 通常施工費 | D46: =LED計算式!O36 -> 0 | E46: 3000 | F46: =IFERROR(E46*D46,"") -> 0
A47: 施工費 (非常灯別置工事) | D47: =LED計算式!O37 -> 0 | E47: 4500 | F47: =IFERROR(E47*D47,"") -> 0
A48: 施工費 (配線直結工事） | D48: =LED計算式!O38 -> 0 | E48: 2000 | F48: =IFERROR(E48*D48,"") -> 0
A49: 施工費 (ランプ交換） | D49: =LED計算式!O39 -> 0 | E49: 600 | F49: =IFERROR(E49*D49,"") -> 0
A50: 諸経費 | D50: =COUNTA(☆入力!AG16:AG45) -> 1 | E50: 3000 | F50: =IFERROR(E50*D50,"") -> 3000
A51: 廃棄代 | D51: =☆入力!L14 -> 0 | E51: 1000 | F51: =IFERROR(E51*D51,"") -> 0
A52: 交通費 | D52: =COUNTA(☆入力!AG16:AG45) -> 1 | E52: 5000 | F52: =IFERROR(E52*D52,"") -> 5000
A53: =☆入力!AH12 -> 0 | D53: =IF(☆入力!AH12<>"","1","") | E53: =☆入力!AJ12 -> 0 | F53: =IFERROR(E53*D53,"")
E54: 工事費合計 | F54: =SUM(F45:G53) -> 28000
A55: 【備考】
A56: =☆入力!AH4 -> 生産終了品などがあった場合、同メーカーもしくは他メーカーの同等品に変更される場合がございます。 | E56: 商品代 + 工事代 | F56: =ROUNDDOWN(F42+F54,0) -> 0
A58: =☆入力!AH5 -> 新しい照明器具が、既設よりも一回り小さくなるケースがあり、その際は外壁塗装面が露出する | E58: 一括購入金額(税抜)： | F58: =VLOOKUP(E58,I11:J12,2,FALSE) -> 0
A60: =☆入力!AH6 -> 可能性がございます。 | E60: リース金額(税抜)： | F60: =VLOOKUP(E60,I9:J10,2,FALSE) -> 0 | G60: ×60ヵ月
E62: ※消費税は別途申し受けいたします。 | H62: ←税込の場合は消すの忘れないように注意

Sheet ✖⑤複数+詳細2
A1: 御見積書 | H1: 発行日： | I1: =TODAY() -> 46080
A3: =☆入力!C5 -> 0
G4: =IF(代理店入力用!N3="",①表紙!I25,代理店入力用!N3) -> 株式会社ニッショー
G5: =IF(代理店入力用!N5="",①表紙!I26,①表紙!A26) -> 〒151-0071 東京都渋谷区本町2-6-3 D'sVARIE初台ビル3F
A6: この度は、御見積もりのご依頼を頂き誠にありがとうございます。 | G6: =IF(代理店入力用!N6="",①表紙!I27,①表紙!A27) -> TEL： 管理担当営業所へお問い合わせ下さい。
A7: 下記の通りＬＥＤ照明改修工事の御見積もり申し上げます。何卒ご用命賜りますようお願い申し上げます。
A9: 物件名 | B9: 試算エリア | C9: メーカー | D9: 照明種別 | F9: 電球数 | G9: 定価 | H9: 小計 | K9: リース金額(税抜)： | L9: =ROUNDDOWN(H57/54,0) -> 0
A10: =☆入力!B16 | B10: =☆入力!C16 -> 0 | C10: =IFERROR(VLOOKUP(☆入力!G16,選定!$C$3:$AG$100,11,FALSE),"") | D10: =IFERROR(VLOOKUP(☆入力!G16,選定!$C$3:$AG$100,1,FALSE),"") | F10: =☆入力!L16 -> 0 | G10: =IFERROR(VLOOKUP(☆入力!G16,選定!$C$3:$AG$100,7,FALSE),"") | H10: =IFERROR(G10*F10,"") | K10: リース金額(税込)： | L10: =L9*1.1 -> 0
A11: =☆入力!B17 | B11: =☆入力!C17 -> 0 | C11: =IFERROR(VLOOKUP(☆入力!G17,選定!$C$3:$AG$100,11,FALSE),"") | D11: =IFERROR(VLOOKUP(☆入力!G17,選定!$C$3:$AG$100,1,FALSE),"") | F11: =☆入力!L17 -> 0 | G11: =IFERROR(VLOOKUP(☆入力!G17,選定!$C$3:$AG$100,7,FALSE),"") | H11: =IFERROR(G11*F11,"") | K11: 一括購入金額(税抜)： | L11: =H57 -> 0
A12: =☆入力!B18 | B12: =☆入力!C18 -> 0 | C12: =IFERROR(VLOOKUP(☆入力!G18,選定!$C$3:$AG$100,11,FALSE),"") | D12: =IFERROR(VLOOKUP(☆入力!G18,選定!$C$3:$AG$100,1,FALSE),"") | F12: =☆入力!L18 -> 0 | G12: =IFERROR(VLOOKUP(☆入力!G18,選定!$C$3:$AG$100,7,FALSE),"") | H12: =IFERROR(G12*F12,"") | K12: 一括購入金額(税込)： | L12: =L11*1.1 -> 0
A13: =☆入力!B19 | B13: =☆入力!C19 -> 0 | C13: =IFERROR(VLOOKUP(☆入力!G19,選定!$C$3:$AG$100,11,FALSE),"") | D13: =IFERROR(VLOOKUP(☆入力!G19,選定!$C$3:$AG$100,1,FALSE),"") | F13: =☆入力!L19 -> 0 | G13: =IFERROR(VLOOKUP(☆入力!G19,選定!$C$3:$AG$100,7,FALSE),"") | H13: =IFERROR(G13*F13,"")
A14: =☆入力!B20 | B14: =☆入力!C20 -> 0 | C14: =IFERROR(VLOOKUP(☆入力!G20,選定!$C$3:$AG$100,11,FALSE),"") | D14: =IFERROR(VLOOKUP(☆入力!G20,選定!$C$3:$AG$100,1,FALSE),"") | F14: =☆入力!L20 -> 0 | G14: =IFERROR(VLOOKUP(☆入力!G20,選定!$C$3:$AG$100,7,FALSE),"") | H14: =IFERROR(G14*F14,"")
A15: =☆入力!B21 | B15: =☆入力!C21 -> 0 | C15: =IFERROR(VLOOKUP(☆入力!G21,選定!$C$3:$AG$100,11,FALSE),"") | D15: =IFERROR(VLOOKUP(☆入力!G21,選定!$C$3:$AG$100,1,FALSE),"") | F15: =☆入力!L21 -> 0 | G15: =IFERROR(VLOOKUP(☆入力!G21,選定!$C$3:$AG$100,7,FALSE),"") | H15: =IFERROR(G15*F15,"")
A16: =☆入力!B22 | B16: =☆入力!C22 -> 0 | C16: =IFERROR(VLOOKUP(☆入力!G22,選定!$C$3:$AG$100,11,FALSE),"") | D16: =IFERROR(VLOOKUP(☆入力!G22,選定!$C$3:$AG$100,1,FALSE),"") | F16: =☆入力!L22 -> 0 | G16: =IFERROR(VLOOKUP(☆入力!G22,選定!$C$3:$AG$100,7,FALSE),"") | H16: =IFERROR(G16*F16,"")
A17: =☆入力!B23 | B17: =☆入力!C23 -> 0 | C17: =IFERROR(VLOOKUP(☆入力!G23,選定!$C$3:$AG$100,11,FALSE),"") | D17: =IFERROR(VLOOKUP(☆入力!G23,選定!$C$3:$AG$100,1,FALSE),"") | F17: =☆入力!L23 -> 0 | G17: =IFERROR(VLOOKUP(☆入力!G23,選定!$C$3:$AG$100,7,FALSE),"") | H17: =IFERROR(G17*F17,"")
A18: =☆入力!B24 | B18: =☆入力!C24 -> 0 | C18: =IFERROR(VLOOKUP(☆入力!G24,選定!$C$3:$AG$100,11,FALSE),"") | D18: =IFERROR(VLOOKUP(☆入力!G24,選定!$C$3:$AG$100,1,FALSE),"") | F18: =☆入力!L24 -> 0 | G18: =IFERROR(VLOOKUP(☆入力!G24,選定!$C$3:$AG$100,7,FALSE),"") | H18: =IFERROR(G18*F18,"")
A19: =☆入力!B25 | B19: =☆入力!C25 -> 0 | C19: =IFERROR(VLOOKUP(☆入力!G25,選定!$C$3:$AG$100,11,FALSE),"") | D19: =IFERROR(VLOOKUP(☆入力!G25,選定!$C$3:$AG$100,1,FALSE),"") | F19: =☆入力!L25 -> 0 | G19: =IFERROR(VLOOKUP(☆入力!G25,選定!$C$3:$AG$100,7,FALSE),"") | H19: =IFERROR(G19*F19,"")
A20: =☆入力!B26 | B20: =☆入力!C26 -> 0 | C20: =IFERROR(VLOOKUP(☆入力!G26,選定!$C$3:$AG$100,11,FALSE),"") | D20: =IFERROR(VLOOKUP(☆入力!G26,選定!$C$3:$AG$100,1,FALSE),"") | F20: =☆入力!L26 -> 0 | G20: =IFERROR(VLOOKUP(☆入力!G26,選定!$C$3:$AG$100,7,FALSE),"") | H20: =IFERROR(G20*F20,"")
A21: =☆入力!B27 | B21: =☆入力!C27 -> 0 | C21: =IFERROR(VLOOKUP(☆入力!G27,選定!$C$3:$AG$100,11,FALSE),"") | D21: =IFERROR(VLOOKUP(☆入力!G27,選定!$C$3:$AG$100,1,FALSE),"") | F21: =☆入力!L27 -> 0 | G21: =IFERROR(VLOOKUP(☆入力!G27,選定!$C$3:$AG$100,7,FALSE),"") | H21: =IFERROR(G21*F21,"")
A22: =☆入力!B28 | B22: =☆入力!C28 -> 0 | C22: =IFERROR(VLOOKUP(☆入力!G28,選定!$C$3:$AG$100,11,FALSE),"") | D22: =IFERROR(VLOOKUP(☆入力!G28,選定!$C$3:$AG$100,1,FALSE),"") | F22: =☆入力!L28 -> 0 | G22: =IFERROR(VLOOKUP(☆入力!G28,選定!$C$3:$AG$100,7,FALSE),"") | H22: =IFERROR(G22*F22,"")
A23: =☆入力!B29 | B23: =☆入力!C29 -> 0 | C23: =IFERROR(VLOOKUP(☆入力!G29,選定!$C$3:$AG$100,11,FALSE),"") | D23: =IFERROR(VLOOKUP(☆入力!G29,選定!$C$3:$AG$100,1,FALSE),"") | F23: =☆入力!L29 -> 0 | G23: =IFERROR(VLOOKUP(☆入力!G29,選定!$C$3:$AG$100,7,FALSE),"") | H23: =IFERROR(G23*F23,"")
A24: =☆入力!B30 | B24: =☆入力!C30 -> 0 | C24: =IFERROR(VLOOKUP(☆入力!G30,選定!$C$3:$AG$100,11,FALSE),"") | D24: =IFERROR(VLOOKUP(☆入力!G30,選定!$C$3:$AG$100,1,FALSE),"") | F24: =☆入力!L30 -> 0 | G24: =IFERROR(VLOOKUP(☆入力!G30,選定!$C$3:$AG$100,7,FALSE),"") | H24: =IFERROR(G24*F24,"")
... A39: =☆入力!B45 | B39: =☆入力!C45 -> 0 | C39: =IFERROR(VLOOKUP(☆入力!G45,選定!$C$3:$AG$100,11,FALSE),"") | D39: =IFERROR(VLOOKUP(☆入力!G45,選定!$C$3:$AG$100,1,FALSE),"") | F39: =☆入力!L45 -> 0 | G39: =IFERROR(VLOOKUP(☆入力!G45,選定!$C$3:$AG$100,7,FALSE),"") | H39: =IFERROR(G39*F39,"")
F40: 商品代合計 | H40: =SUM(H10:I39) -> 0
A42: 施工内容 | F42: 数量 | G42: 単価 | H42: 小計
A43: 工事費人工 | F43: =VLOOKUP(☆入力!L14,LED計算式!M21:N26,2,TRUE) -> 1 | G43: 20000 | H43: =IFERROR(G43*F43,"") -> 20000
A44: 通常施工費 | F44: =LED計算式!O36 -> 0 | G44: 3000 | H44: =IFERROR(G44*F44,"") -> 0
A45: 施工費 (非常灯別置工事) | F45: =LED計算式!O37 -> 0 | G45: 5000 | H45: =IFERROR(G45*F45,"") -> 0
A46: 施工費 (配線直結工事） | F46: =LED計算式!O38 -> 0 | G46: 2000 | H46: =IFERROR(G46*F46,"") -> 0
A47: 施工費 (ランプ交換） | F47: =LED計算式!O39 -> 0 | G47: 600 | H47: =IFERROR(G47*F47,"") -> 0
A48: 諸経費 | F48: =COUNTA(☆入力!AG16:AG45) -> 1 | G48: 3000 | H48: =IFERROR(G48*F48,"") -> 3000
A49: 廃棄代 | F49: =SUM(F44:F46) -> 0 | G49: 1000 | H49: =IFERROR(G49*F49,"") -> 0
A50: 交通費 | F50: =COUNTA(☆入力!AG16:AG45) -> 1 | G50: 5000 | H50: =IFERROR(G50*F50,"") -> 5000
A51: =☆入力!AH12 -> 0 | F51: =IF(☆入力!AH12<>"","1","") | G51: =☆入力!AJ12 -> 0 | H51: =IFERROR(G51*F51,"")
F52: 工事費合計 | H52: =SUM(H43:I51) -> 28000
F54: 商品代 + 工事代 | H54: =ROUNDDOWN(H40+H52,0) -> 28000
F55: お値引き | H55: =(☆入力!AL14+代理店入力用!D5)-SUM(H40,H43:I51) -> -28000
A56: 【備考】 | F56: ="複数棟割引（ "&TEXT(☆入力!AR11,"0%")&" OFF ）" -> 複数棟割引（ 0% OFF ） | H56: =-(☆入力!AL14*☆入力!AR11) -> 0
A57: =☆入力!AH4 -> 生産終了品などがあった場合、同メーカーもしくは他メーカーの同等品に変更される場合がございます。 | F57: 合計 | H57: =SUM(H54:I56) -> 0
A59: =☆入力!AH5 -> 新しい照明器具が、既設よりも一回り小さくなるケースがあり、その際は外壁塗装面が露出する | F59: 一括購入金額(税込)： | H59: =VLOOKUP(F59,K11:L12,2,FALSE) -> 0
A61: =☆入力!AH6 -> 可能性がございます。 | F61: リース金額(税込)： | H61: =VLOOKUP(F61,K9:L10,2,FALSE) -> 0 | I61: ×60ヵ月
J63: ←税込の場合は消すの忘れないように注意

Sheet ⑧見積書
A1: 御見積書 | F1: 発行日： | G1: =TODAY() -> 46080
A3: =☆入力!C5 -> 0
E4: =IF(代理店入力用!N3="",①表紙!I25,代理店入力用!N3) -> 株式会社ニッショー
A6: この度は、御見積もりのご依頼を頂き誠にありがとうございます。 | E6: =IF(代理店入力用!N6="",①表紙!I27,①表紙!A27) -> TEL： 管理担当営業所へお問い合わせ下さい。
A7: 下記の通りＬＥＤ照明改修工事の御見積もり申し上げます。何卒ご用命賜りますようお願い申し上げます。
A9: No. | B9: メーカー | C9: 照明種別 | D9: 電球数 | E9: 定価 | F9: 小計 | I9: リース金額(税抜)： | J9: =ROUNDDOWN(G54*LED計算式!AC2,0) -> 0
A10: 1 | B10: =IFERROR(VLOOKUP(☆入力!G16,選定!$C$3:$AG$100,11,FALSE),"") | C10: =IFERROR(VLOOKUP(☆入力!G16,選定!$C$3:$AG$100,1,FALSE),"") | D10: =☆入力!L16 -> 0 | E10: =IFERROR(VLOOKUP(☆入力!G16,選定!$C$3:$AG$100,7,FALSE),"") | F10: =IFERROR(E10*D10,"") | I10: リース金額(税込)： | J10: =ROUNDDOWN(J9*1.1,0) -> 0
A11: 2 | B11: =IFERROR(VLOOKUP(☆入力!G17,選定!$C$3:$AG$100,11,FALSE),"") | C11: =IFERROR(VLOOKUP(☆入力!G17,選定!$C$3:$AG$100,1,FALSE),"") | D11: =☆入力!L17 -> 0 | E11: =IFERROR(VLOOKUP(☆入力!G17,選定!$C$3:$AG$100,7,FALSE),"") | F11: =IFERROR(E11*D11,"") | I11: 一括購入金額(税抜)： | J11: =G54 -> 0
A12: 3 | B12: =IFERROR(VLOOKUP(☆入力!G18,選定!$C$3:$AG$100,11,FALSE),"") | C12: =IFERROR(VLOOKUP(☆入力!G18,選定!$C$3:$AG$100,1,FALSE),"") | D12: =☆入力!L18 -> 0 | E12: =IFERROR(VLOOKUP(☆入力!G18,選定!$C$3:$AG$100,7,FALSE),"") | F12: =IFERROR(E12*D12,"") | I12: 一括購入金額(税込)： | J12: =ROUNDDOWN(J11*1.1,0) -> 0
A13: 4 | B13: =IFERROR(VLOOKUP(☆入力!G19,選定!$C$3:$AG$100,11,FALSE),"") | C13: =IFERROR(VLOOKUP(☆入力!G19,選定!$C$3:$AG$100,1,FALSE),"") | D13: =☆入力!L19 -> 0 | E13: =IFERROR(VLOOKUP(☆入力!G19,選定!$C$3:$AG$100,7,FALSE),"") | F13: =IFERROR(E13*D13,"")
A14: 5 | B14: =IFERROR(VLOOKUP(☆入力!G20,選定!$C$3:$AG$100,11,FALSE),"") | C14: =IFERROR(VLOOKUP(☆入力!G20,選定!$C$3:$AG$100,1,FALSE),"") | D14: =☆入力!L20 -> 0 | E14: =IFERROR(VLOOKUP(☆入力!G20,選定!$C$3:$AG$100,7,FALSE),"") | F14: =IFERROR(E14*D14,"")
A15: 6 | B15: =IFERROR(VLOOKUP(☆入力!G21,選定!$C$3:$AG$100,11,FALSE),"") | C15: =IFERROR(VLOOKUP(☆入力!G21,選定!$C$3:$AG$100,1,FALSE),"") | D15: =☆入力!L21 -> 0 | E15: =IFERROR(VLOOKUP(☆入力!G21,選定!$C$3:$AG$100,7,FALSE),"") | F15: =IFERROR(E15*D15,"")
A16: 7 | B16: =IFERROR(VLOOKUP(☆入力!G22,選定!$C$3:$AG$100,11,FALSE),"") | C16: =IFERROR(VLOOKUP(☆入力!G22,選定!$C$3:$AG$100,1,FALSE),"") | D16: =☆入力!L22 -> 0 | E16: =IFERROR(VLOOKUP(☆入力!G22,選定!$C$3:$AG$100,7,FALSE),"") | F16: =IFERROR(E16*D16,"")
A17: 8 | B17: =IFERROR(VLOOKUP(☆入力!G23,選定!$C$3:$AG$100,11,FALSE),"") | C17: =IFERROR(VLOOKUP(☆入力!G23,選定!$C$3:$AG$100,1,FALSE),"") | D17: =☆入力!L23 -> 0 | E17: =IFERROR(VLOOKUP(☆入力!G23,選定!$C$3:$AG$100,7,FALSE),"") | F17: =IFERROR(E17*D17,"")
A18: 9 | B18: =IFERROR(VLOOKUP(☆入力!G24,選定!$C$3:$AG$100,11,FALSE),"") | C18: =IFERROR(VLOOKUP(☆入力!G24,選定!$C$3:$AG$100,1,FALSE),"") | D18: =☆入力!L24 -> 0 | E18: =IFERROR(VLOOKUP(☆入力!G24,選定!$C$3:$AG$100,7,FALSE),"") | F18: =IFERROR(E18*D18,"")
A19: 10 | B19: =IFERROR(VLOOKUP(☆入力!G25,選定!$C$3:$AG$100,11,FALSE),"") | C19: =IFERROR(VLOOKUP(☆入力!G25,選定!$C$3:$AG$100,1,FALSE),"") | D19: =☆入力!L25 -> 0 | E19: =IFERROR(VLOOKUP(☆入力!G25,選定!$C$3:$AG$100,7,FALSE),"") | F19: =IFERROR(E19*D19,"")
A20: 11 | B20: =IFERROR(VLOOKUP(☆入力!G26,選定!$C$3:$AG$100,11,FALSE),"") | C20: =IFERROR(VLOOKUP(☆入力!G26,選定!$C$3:$AG$100,1,FALSE),"") | D20: =☆入力!L26 -> 0 | E20: =IFERROR(VLOOKUP(☆入力!G26,選定!$C$3:$AG$100,7,FALSE),"") | F20: =IFERROR(E20*D20,"")
A21: 12 | B21: =IFERROR(VLOOKUP(☆入力!G27,選定!$C$3:$AG$100,11,FALSE),"") | C21: =IFERROR(VLOOKUP(☆入力!G27,選定!$C$3:$AG$100,1,FALSE),"") | D21: =☆入力!L27 -> 0 | E21: =IFERROR(VLOOKUP(☆入力!G27,選定!$C$3:$AG$100,7,FALSE),"") | F21: =IFERROR(E21*D21,"")
A22: 13 | B22: =IFERROR(VLOOKUP(☆入力!G28,選定!$C$3:$AG$100,11,FALSE),"") | C22: =IFERROR(VLOOKUP(☆入力!G28,選定!$C$3:$AG$100,1,FALSE),"") | D22: =☆入力!L28 -> 0 | E22: =IFERROR(VLOOKUP(☆入力!G28,選定!$C$3:$AG$100,7,FALSE),"") | F22: =IFERROR(E22*D22,"")
A23: 14 | B23: =IFERROR(VLOOKUP(☆入力!G29,選定!$C$3:$AG$100,11,FALSE),"") | C23: =IFERROR(VLOOKUP(☆入力!G29,選定!$C$3:$AG$100,1,FALSE),"") | D23: =☆入力!L29 -> 0 | E23: =IFERROR(VLOOKUP(☆入力!G29,選定!$C$3:$AG$100,7,FALSE),"") | F23: =IFERROR(E23*D23,"")
A24: 15 | B24: =IFERROR(VLOOKUP(☆入力!G30,選定!$C$3:$AG$100,11,FALSE),"") | C24: =IFERROR(VLOOKUP(☆入力!G30,選定!$C$3:$AG$100,1,FALSE),"") | D24: =☆入力!L30 -> 0 | E24: =IFERROR(VLOOKUP(☆入力!G30,選定!$C$3:$AG$100,7,FALSE),"") | F24: =IFERROR(E24*D24,"")
... A39: 30 | B39: =IFERROR(VLOOKUP(☆入力!G45,選定!$C$3:$AG$100,11,FALSE),"") | C39: =IFERROR(VLOOKUP(☆入力!G45,選定!$C$3:$AG$100,1,FALSE),"") | D39: =☆入力!L45 -> 0 | E39: =IFERROR(VLOOKUP(☆入力!G45,選定!$C$3:$AG$100,7,FALSE),"") | F39: =IFERROR(E39*D39,"")
E40: 商品代合計 | F40: =SUM(F10:G39) -> 0
A42: 施工内容 | D42: 数量 | E42: 単価 | F42: 小計
A43: 工事費人工 | D43: =VLOOKUP(☆入力!L14,LED計算式!M21:N27,2,TRUE) -> 1 | E43: 20000 | F43: =IFERROR(E43*D43,"") -> 20000
A44: 通常施工費 | D44: =LED計算式!O36 -> 0 | E44: 3000 | F44: =IFERROR(E44*D44,"") -> 0
A45: 施工費 (非常灯別置工事/蛍光灯埋込器具工事) | D45: =LED計算式!O37 -> 0 | E45: 5000 | F45: =IFERROR(E45*D45,"") -> 0
A46: 施工費 (ランプ交換） | D46: =LED計算式!O39 -> 0 | E46: 600 | F46: =IFERROR(E46*D46,"") -> 0
A47: 廃棄代 | D47: =☆入力!L14 -> 0 | E47: 1000 | F47: =IFERROR(E47*D47,"") -> 0
F48: =IFERROR(E48*D48,"") -> 0
A49: =☆入力!AH12 -> 0 | D49: =IF(☆入力!AH12<>"","1","") | E49: =☆入力!AJ12 -> 0 | F49: =IFERROR(E49*D49,"")
E50: 工事費合計 | F50: =SUM(F43:G49) -> 20000
E52: 商品代 + 工事代 | F52: =ROUNDDOWN(F40+F50,0) -> 20000
E53: お値引き | F53: =(☆入力!AL14+代理店入力用!D5)-SUM(F40,F43:G49) -> -20000
A54: 【備考】 | E54: 合計 | G54: =SUM(F52:G53) -> 0
A55: =☆入力!AH4 -> 生産終了品などがあった場合、同メーカーもしくは他メーカーの同等品に変更される場合がございます。
A57: =☆入力!AH5 -> 新しい照明器具が、既設よりも一回り小さくなるケースがあり、その際は外壁塗装面が露出する | E57: 一括購入金額(税込)： | F57: =VLOOKUP(E57,I11:J12,2,FALSE) -> 0
A59: =☆入力!AH6 -> 可能性がございます。 | E59: リース金額(税込)： | F59: =VLOOKUP(E59,I9:J10,2,FALSE) -> 0 | G59: ="×"&LED計算式!AD2&"ヵ月" -> ×120ヵ月
G61: 8

Sheet ⑦小単体
A1: 御見積書 | J1: 発行日： | K1: =TODAY() -> 46080
H3: 一括購入の費用 | K3: 毎月の削減金額(平均)
A4: =☆入力!C5 -> 0 | H4: =F39 -> 0 | J4: ÷ | K4: =④前後a!BA29/120 -> 0
E6: =IF(代理店入力用!N3="",①表紙!I25,代理店入力用!N3) -> 株式会社ニッショー | N6: 一括購入金額(税抜)： | O6: =F39 -> 0
A7: この度は、御見積もりのご依頼を頂き誠にありがとうございます。 | E7: =IF(代理店入力用!N5="",①表紙!I26,①表紙!A26) -> 〒151-0071 東京都渋谷区本町2-6-3 D'sVARIE初台ビル3F | K7: 回収年数 | N7: 一括購入金額(税込)： | O7: =O6*1.1 -> 0
A8: 下記の通りＬＥＤ照明改修工事の御見積もり申し上げます。 | E8: =IF(代理店入力用!N6="",①表紙!I27,①表紙!A27) -> TEL： 管理担当営業所へお問い合わせ下さい。 | J8: = | K8: =IFERROR((H4/K4)/12,"0") -> 0
A10: 内容： | C10: 共用部分照明のＬＥＤ改修工事 | E10: 一括購入金額(税込)： | F10: =VLOOKUP(E10,N6:O7,2,FALSE) -> 0
A11: 有効期限： | C11: 発行日より1ヵ月
M12: ←←←←←税込の場合は消すの忘れないように注意
A13: No. | B13: 設置場所 | C13: メーカー/型番 | D13: 数量 | E13: 定価 | F13: 小計
A14: 1 | B14: =☆入力!C16 -> 0 | C14: =IFERROR(VLOOKUP(☆入力!G16,選定!$C$3:$AG$100,11,FALSE)&" "&VLOOKUP(☆入力!G16,選定!$C$3:$AG$100,1,FALSE),"") | D14: =☆入力!L16 -> 0 | E14: =IFERROR(VLOOKUP(☆入力!G16,選定!$C$3:$AG$100,7,FALSE),"") | F14: =IFERROR(E14*D14,"")
A15: 2 | B15: =☆入力!C17 -> 0 | C15: =IFERROR(VLOOKUP(☆入力!G17,選定!$C$3:$AG$100,11,FALSE)&" "&VLOOKUP(☆入力!G17,選定!$C$3:$AG$100,1,FALSE),"") | D15: =☆入力!L17 -> 0 | E15: =IFERROR(VLOOKUP(☆入力!G17,選定!$C$3:$AG$100,7,FALSE),"") | F15: =IFERROR(E15*D15,"")
A16: 3 | B16: =☆入力!C18 -> 0 | C16: =IFERROR(VLOOKUP(☆入力!G18,選定!$C$3:$AG$100,11,FALSE)&" "&VLOOKUP(☆入力!G18,選定!$C$3:$AG$100,1,FALSE),"") | D16: =☆入力!L18 -> 0 | E16: =IFERROR(VLOOKUP(☆入力!G18,選定!$C$3:$AG$100,7,FALSE),"") | F16: =IFERROR(E16*D16,"")
A17: 4 | B17: =☆入力!C19 -> 0 | C17: =IFERROR(VLOOKUP(☆入力!G19,選定!$C$3:$AG$100,11,FALSE)&" "&VLOOKUP(☆入力!G19,選定!$C$3:$AG$100,1,FALSE),"") | D17: =☆入力!L19 -> 0 | E17: =IFERROR(VLOOKUP(☆入力!G19,選定!$C$3:$AG$100,7,FALSE),"") | F17: =IFERROR(E17*D17,"")
A18: 5 | B18: =☆入力!C20 -> 0 | C18: =IFERROR(VLOOKUP(☆入力!G20,選定!$C$3:$AG$100,11,FALSE)&" "&VLOOKUP(☆入力!G20,選定!$C$3:$AG$100,1,FALSE),"") | D18: =☆入力!L20 -> 0 | E18: =IFERROR(VLOOKUP(☆入力!G20,選定!$C$3:$AG$100,7,FALSE),"") | F18: =IFERROR(E18*D18,"")
A19: 6 | B19: =☆入力!C21 -> 0 | C19: =IFERROR(VLOOKUP(☆入力!G21,選定!$C$3:$AG$100,11,FALSE)&" "&VLOOKUP(☆入力!G21,選定!$C$3:$AG$100,1,FALSE),"") | D19: =☆入力!L21 -> 0 | E19: =IFERROR(VLOOKUP(☆入力!G21,選定!$C$3:$AG$100,7,FALSE),"") | F19: =IFERROR(E19*D19,"")
A20: 7 | B20: =☆入力!C22 -> 0 | C20: =IFERROR(VLOOKUP(☆入力!G22,選定!$C$3:$AG$100,11,FALSE)&" "&VLOOKUP(☆入力!G22,選定!$C$3:$AG$100,1,FALSE),"") | D20: =☆入力!L22 -> 0 | E20: =IFERROR(VLOOKUP(☆入力!G22,選定!$C$3:$AG$100,7,FALSE),"") | F20: =IFERROR(E20*D20,"")
A21: 8 | B21: =☆入力!C23 -> 0 | C21: =IFERROR(VLOOKUP(☆入力!G23,選定!$C$3:$AG$100,11,FALSE)&" "&VLOOKUP(☆入力!G23,選定!$C$3:$AG$100,1,FALSE),"") | D21: =☆入力!L23 -> 0 | E21: =IFERROR(VLOOKUP(☆入力!G23,選定!$C$3:$AG$100,7,FALSE),"") | F21: =IFERROR(E21*D21,"")
A22: 9 | B22: =☆入力!C24 -> 0 | C22: =IFERROR(VLOOKUP(☆入力!G24,選定!$C$3:$AG$100,11,FALSE)&" "&VLOOKUP(☆入力!G24,選定!$C$3:$AG$100,1,FALSE),"") | D22: =☆入力!L24 -> 0 | E22: =IFERROR(VLOOKUP(☆入力!G24,選定!$C$3:$AG$100,7,FALSE),"") | F22: =IFERROR(E22*D22,"")
A23: 10 | B23: =☆入力!C25 -> 0 | C23: =IFERROR(VLOOKUP(☆入力!G25,選定!$C$3:$AG$100,11,FALSE)&" "&VLOOKUP(☆入力!G25,選定!$C$3:$AG$100,1,FALSE),"") | D23: =☆入力!L25 -> 0 | E23: =IFERROR(VLOOKUP(☆入力!G25,選定!$C$3:$AG$100,7,FALSE),"") | F23: =IFERROR(E23*D23,"")
E24: 商品代小計 | F24: =ROUNDDOWN(SUM(F14:G23),0) -> 0
A25: 施工内容 | D25: 数量 | E25: 単価 | F25: 小計
A26: 工事費人工 | D26: =VLOOKUP(☆入力!L14,LED計算式!M21:N26,2,TRUE) -> 1 | E26: 20000 | F26: =IFERROR(E26*D26,"") -> 20000
A27: 通常施工費 | D27: =LED計算式!O36 -> 0 | E27: 3000 | F27: =IFERROR(E27*D27,"") -> 0
A28: 施工費 (非常灯別置工事) | D28: =LED計算式!O37 -> 0 | E28: 5000 | F28: =IFERROR(E28*D28,"") -> 0
A29: 施工費 (配線直結工事） | D29: =LED計算式!O38 -> 0 | E29: 2000 | F29: =IFERROR(E29*D29,"") -> 0
A30: 施工費 (ランプ交換） | D30: =LED計算式!O39 -> 0 | E30: 600 | F30: =IFERROR(E30*D30,"") -> 0
A31: 諸経費 | D31: =COUNTA(☆入力!AG16:AG45) -> 1 | E31: 3000 | F31: =IFERROR(E31*D31,"") -> 3000
A32: 廃棄代 | D32: =☆入力!L14 -> 0 | E32: 1000 | F32: =IFERROR(E32*D32,"") -> 0
A33: 交通費 | D33: =COUNTA(☆入力!AG16:AG45) -> 1 | E33: 5000 | F33: =IFERROR(E33*D33,"") -> 5000
A34: =☆入力!AH12 -> 0 | D34: =IF(☆入力!AH12<>"","1","") | E34: =☆入力!AJ12 -> 0 | F34: =IFERROR(E34*D34,"")
E35: 工事費小計 | F35: =ROUNDDOWN(SUM(F26:G34),0) -> 28000
E37: 商品代+工事費 | F37: =F24+F35 -> 28000
E38: お値引き | F38: =(☆入力!AL14+代理店入力用!D5)-SUM(F24,F35) -> -28000
E39: 合計 | F39: =F37+F38 -> 0
B41: 【備考】
B42: =☆入力!AH4 -> 生産終了品などがあった場合、同メーカーもしくは他メーカーの同等品に変更される場合がございます。
B43: =☆入力!AH5 -> 新しい照明器具が、既設よりも一回り小さくなるケースがあり、その際は外壁塗装面が露出する
B44: =☆入力!AH6 -> 可能性がございます。

Sheet ⑨シミュレーション
A1: ～LED照明の導入パターン～
A2: ＜リースで交換した場合＞ 無償譲渡型リース | AF2: ＜一括購入で交換した場合＞
A5: ★リースで交換した場合のリース料金： | N5: =⑧見積書!J10 -> 0 | S5: ✖ | U5: =LED計算式!AD2 -> 120 | Y5: = | Z5: =N5*U5 -> 0 | AF5: ★一括購入で交換した場合の交換費用： | AR5: =⑧見積書!J12 -> 0
B7: ※照明器具ごとLED照明に交換を致します。 | N7: 工事費込み | Z7: ※総支払金額 | AG7: ※照明器具ごとLED照明に交換を致します。 | AR7: 工事費込み
A9: 【リースで導入した場合のイメージ図】 | AF9: 【回収予測グラフ】
A26: (※)交換コストとは2ページ目、3ページ目で算出した白熱球と非常灯バッテリーの交換コスト(120ヵ月)を1ヵ月に振り分けて算出した金額
AG27: 一括購入の費用 | AQ27: 毎月の削減金額（平均）
A28: ="◆設置から"&LED計算式!AD1&"年間での交換費用を含めたCF改善金額・・・・・・・" -> ◆設置から10年間での交換費用を含めたCF改善金額・・・・・・・ | V28: =LED計算式!J23*LED計算式!AD2 -> 0 | AG28: =AR5 -> 0 | AO28: ÷ | AQ28: =④前後a!BA29/120 -> 0
A30: ="◆"&LED計算式!AD1+1&"年目以降の交換費用を含めたCF改善金額・・・・・・・・・・" -> ◆11年目以降の交換費用を含めたCF改善金額・・・・・・・・・・ | V30: =LED計算式!K23*LED計算式!AE2 -> 0
AQ31: 回収年数
A32: ◆設置からLED電球が寿命を迎えるまでのCF改善金額 ・・・・・ | V32: =V28+V30 -> 0 | AO32: ＝ | AQ32: =IFERROR((AG28/AQ28)/12,"0") -> 0
AQ34: =IFERROR(AG28/AQ28,"0") -> 0 | AX34: 9

Sheet ⑧-bｼﾐｭ
A1: ～新電力セットプラン～
A2: ◇既存の地域電力との契約を弊社指定の新電力会社に切り替えて頂きますと、電気単価のコスト削減につながり、LED導入費用から5%の割引を適応します。
A3: ＜リースで交換した場合＞ 無償譲渡型リース | AF3: ＜一括購入で交換した場合＞
I6: 《通常価格》 | Q6: 《セットプラン価格》 | AH6: 《通常価格》 | AR6: 《セットプラン価格》
I7: =⑨シミュレーション!N5 -> 0 | R7: =ROUNDDOWN(AR7*LED計算式!AC2,0) -> 0 | AG7: =⑨シミュレーション!AR5 -> 0 | AR7: =AG7*(100%-☆入力!AR12) -> 0
W8: （税抜）
A9: 電力セットプラン適応で、毎月 | M9: =I7-R7 -> 0 | S9: お値引き！ | AF9: セットプランで | AM9: =AG7-AR7 -> 0 | AS9: お値引き！
D11: =M9 -> 0 | I11: ="×"&LED計算式!AD2&"ヵ月=" -> ×120ヵ月= | M11: =D11*LED計算式!AD2 -> 0 | S11: 相当のお値引きです
A13: 【リースで導入した場合のイメージ図】 | AF13: 【回収予測グラフ】
A30: (※)交換コストとは2ページ目、3ページ目で算出した白熱球と非常灯バッテリーの交換コスト(120ヵ月)を1ヵ月に振り分けて算出した金額
AG31: 一括購入の費用 | AQ31: 毎月の削減金額（平均）
A32: ="◆設置から"&LED計算式!AD1&"年間での交換費用を含めたCF改善金額・・・・・・・" -> ◆設置から10年間での交換費用を含めたCF改善金額・・・・・・・ | V32: =LED計算式!J23*LED計算式!AD2 -> 0 | AG32: =AR7 -> 0 | AO32: ÷ | AQ32: =④前後a!BA29/120 -> 0
A34: ="◆"&LED計算式!AD1+1&"年目以降の交換費用を含めたCF改善金額・・・・・・・・・・" -> ◆11年目以降の交換費用を含めたCF改善金額・・・・・・・・・・ | V34: =LED計算式!K23*LED計算式!AE2 -> 0
AQ35: 回収年数
A36: ◆設置から10年間合計の交換費用を含めたCF改善金額 ・・・・・ | V36: =V32+V34 -> 0 | AQ36: =IFERROR((AG32/AQ32)/12,"0") -> 0
AQ38: =IFERROR(AG32/AQ32,"0") -> 0
AX39: 8-b

Sheet ⑥非あり
A1: ～LED照明の導入パターン～
A2: ＜リースで交換した場合＞ 無償譲渡型リース | AF2: ＜一括購入で交換した場合＞
A5: ★リースで交換した場合のリース料金： | N5: =ROUNDDOWN((☆入力!AK14)*(100%-☆入力!AR11)+(代理店入力用!D5/54),0) -> 0 | S5: ✖ | U5: 60 | Y5: = | Z5: =N5*U5 -> 0 | AF5: ★一括購入で交換した場合の交換費用： | AR5: =ROUNDDOWN((☆入力!AL14)*(100%-☆入力!AR11)+代理店入力用!D5,0) -> 0
B7: ※照明器具ごとLED照明に交換を致します。 | N7: 工事費込み（税抜） | Z7: ※総支払金額 | AG7: ※照明器具ごとLED照明に交換を致します。 | AR7: 工事費込み（税抜）
A9: 【リースで導入した場合のイメージ図】 | AF9: 【回収予測グラフ】
A26: (※)交換コストとは2ページ目、3ページ目で算出した白熱球と非常灯バッテリーの交換コスト(120ヵ月)を1ヵ月に振り分けて算出した金額
AG27: 一括購入の費用 | AQ27: 毎月の削減金額（平均）
A28: ◆設置から5年間での交換費用を含めたCF改善金額・・・・・・・ | V28: =LED計算式!J23*60 -> 0 | AG28: =AR5 -> 0 | AO28: ÷ | AQ28: =④前後a!BA29/120 -> 0
A30: ◆6年目以降の交換費用を含めたCF改善金額・・・・・・・・・・ | V30: =LED計算式!K23*60 -> 0
AQ31: 回収年数
A32: ◆設置から10年間合計の交換費用を含めたCF改善金額 ・・・・・ | V32: =V28+V30 -> 0 | AO32: ＝ | AQ32: =IFERROR((AG28/AQ28)/12,"0") -> 0
AQ34: =IFERROR(AG28/AQ28,"0") -> 0 | AY34: 6

Sheet ⑦非あり
A1: ～新電力セットプラン～
A2: ◇既存の地域電力との契約を弊社指定の新電力会社に切り替えて頂きますと、電気単価のコスト削減につながり、LED導入費用から5%の割引を適応します。
A3: ＜リースで交換した場合＞ 無償譲渡型リース | AF3: ＜一括購入で交換した場合＞
I6: 《通常価格》 | Q6: 《セットプラン価格》 | AH6: 《通常価格》 | AR6: 《セットプラン価格》
I7: =⑥非あり!N5 -> 0 | R7: =AR7/54 -> 0 | AG7: =ROUNDDOWN((☆入力!AL14)*(100%-☆入力!AR11)+代理店入力用!D5,0) -> 0 | AR7: =(AG7/(100%-☆入力!AR11))*(100%-☆入力!AR11-☆入力!AR12) -> 0
W8: （税抜）
A9: 電力セットプラン適応で、毎月 | M9: =I7-R7 -> 0 | S9: お値引き！ | AF9: セットプランで | AM9: =AG7-AR7 -> 0 | AS9: お値引き！
D11: =M9 -> 0 | I11: ×60ヵ月= | M11: =D11*60 -> 0 | S11: 相当のお値引きです
A13: 【リースで導入した場合のイメージ図】 | AF13: 【回収予測グラフ】
A30: (※)交換コストとは2ページ目、3ページ目で算出した白熱球と非常灯バッテリーの交換コスト(120ヵ月)を1ヵ月に振り分けて算出した金額
AG31: 一括購入の費用 | AQ31: 毎月の削減金額（平均）
A32: ◆設置から5年間での交換費用を含めたCF改善金額・・・・・・・ | V32: =LED計算式!J36*60 -> 0 | AG32: =AR7 -> 0 | AO32: ÷ | AQ32: =④前後a!BA29/120 -> 0
A34: ◆6年目以降の交換費用を含めたCF改善金額・・・・・・・・・・ | V34: =LED計算式!K36*60 -> 0
AQ35: 回収年数
A36: ◆設置から10年間合計の交換費用を含めたCF改善金額 ・・・・・ | V36: =V32+V34 -> 0 | AQ36: =IFERROR((AG32/AQ32)/12,"0") -> 0
AQ38: =IFERROR(AG32/AQ32,"0") -> 0
AY39: 7

Sheet ⑧複非なし
A1: ～各物件の単体での削減シミュレーション～
A3: =LED計算式!B43 -> 0 | AC3: =LED計算式!G43 -> 0
A4: リース導入 | P4: 一括導入 | AC4: リース導入 | AR4: 一括導入
I13: ◆5年間でのCF改善額 | S13: 交換コストを含めた回収予想年数 | AK13: ◆5年間でのCF改善額 | AU13: 交換コストを含めた回収予想年数
I14: =LED計算式!C50 -> 0 | S14: =IFERROR(S17/(LED計算式!C46+LED計算式!C47-LED計算式!D47)/12,"0") -> 0 | AK14: =LED計算式!H50 -> 0 | AU14: =IFERROR(AU17/(LED計算式!H46+LED計算式!H47-LED計算式!I47)/12,"0") -> 0
I15: ◆6年目以降のCF改善額 | AK15: ◆6年目以降のCF改善額
I16: =LED計算式!C51 -> 0 | S16: 一括導入費用 | AK16: =LED計算式!H51 -> 0 | AU16: 一括導入費用
I17: ◆10年間のCF改善額合計 | S17: =☆入力!AO16 -> 0 | AK17: ◆10年間のCF改善額合計 | AU17: =☆入力!AO17 -> 0
I18: =LED計算式!C52 -> 0 | AK18: =LED計算式!H52 -> 0
A21: =LED計算式!L43 -> 0 | AC21: =LED計算式!Q43 -> 0
A22: リース導入 | P22: 一括導入 | AC22: リース導入 | AR22: 一括導入
I31: ◆5年間でのCF改善額 | S31: 交換コストを含めた回収予想年数 | AK31: ◆5年間でのCF改善額 | AU31: 交換コストを含めた回収予想年数
I32: =LED計算式!M50 -> 0 | S32: =IFERROR(S35/(LED計算式!M46+LED計算式!M47-LED計算式!N47)/12,"0") -> 0 | AK32: =LED計算式!R50 -> 0 | AU32: =IFERROR(AU35/(LED計算式!R46+LED計算式!R47-LED計算式!S47)/12,"0") -> 0
I33: ◆6年目以降のCF改善額 | AK33: ◆6年目以降のCF改善額
I34: =LED計算式!M51 -> 0 | S34: 一括導入費用 | AK34: =LED計算式!R51 -> 0 | AU34: 一括導入費用
I35: ◆10年間のCF改善額合計 | S35: =☆入力!AO18 -> 0 | AK35: ◆10年間のCF改善額合計 | AU35: =☆入力!AO19 -> 0
I36: =LED計算式!M52 -> 0 | AK36: =LED計算式!R52 -> 0

Sheet ⑧複非あり
A1: ～各物件の単体での削減シミュレーション～
A3: =LED計算式!B43 -> 0 | AC3: =LED計算式!G43 -> 0
A4: リース導入 | P4: 一括導入 | AC4: リース導入 | AR4: 一括導入
I13: ◆5年間でのCF改善額 | S13: 交換コストを含めた回収予想年数 | AK13: ◆5年間でのCF改善額 | AU13: 交換コストを含めた回収予想年数
I14: =LED計算式!C61 -> 0 | S14: =IFERROR(S17/((LED計算式!C57+LED計算式!C58)-(LED計算式!D58+LED計算式!D57))/12,"0") -> 0 | AK14: =LED計算式!H61 -> 0 | AU14: =IFERROR(AU17/((LED計算式!H57+LED計算式!H58)-(LED計算式!I58+LED計算式!I57))/12,"0") -> 0
I15: ◆6年目以降のCF改善額 | AK15: ◆6年目以降のCF改善額
I16: =LED計算式!C62 -> 0 | S16: 一括導入費用 | AK16: =LED計算式!H62 -> 0 | AU16: 一括導入費用
I17: ◆10年間のCF改善額合計 | S17: =☆入力!AO16 -> 0 | AK17: ◆10年間のCF改善額合計 | AU17: =☆入力!AO17 -> 0
I18: =LED計算式!C63 -> 0 | AK18: =LED計算式!H63 -> 0
A21: =LED計算式!L43 -> 0 | AC21: =LED計算式!Q43 -> 0
A22: リース導入 | P22: 一括導入 | AC22: リース導入 | AR22: 一括導入
I31: ◆5年間でのCF改善額 | S31: 交換コストを含めた回収予想年数 | AK31: ◆5年間でのCF改善額 | AU31: 交換コストを含めた回収予想年数
I32: =LED計算式!M61 -> 0 | S32: =IFERROR(S35/((LED計算式!M57+LED計算式!M58)-(LED計算式!N58+LED計算式!N57))/12,"0") -> 0 | AK32: =LED計算式!R61 -> 0 | AU32: =IFERROR(AU35/((LED計算式!R57+LED計算式!R58)-(LED計算式!S58+LED計算式!S57))/12,"0") -> 0
I33: ◆6年目以降のCF改善額 | AK33: ◆6年目以降のCF改善額
I34: =LED計算式!M62 -> 0 | S34: 一括導入費用 | AK34: =LED計算式!R62 -> 0 | AU34: 一括導入費用
I35: ◆10年間のCF改善額合計 | S35: =☆入力!AO18 -> 0 | AK35: ◆10年間のCF改善額合計 | AU35: =☆入力!AO19 -> 0
I36: =LED計算式!M63 -> 0 | AK36: =LED計算式!R63 -> 0

Sheet ⑧ｼﾝｴﾅ案内
A1: 新電力会社（シンエナジー）に電力を変更すると、さらにお得にLED導入が可能です
B20: ～～～10年間での実際の電気代比較～～～
B21: LEDのみを交換した場合の電気代： | F21: =LED計算式!AJ2*120 -> 0
B23: LEDと電力を交換した場合の電気代： | F23: =LED計算式!AK2*120 -> 0
B25: セットで交換してお得になる金額： | F25: =F23-F21 -> 0

Sheet ⑩内訳
A1: 設置電球内訳 | I1: 設置電球内訳② | Q1: 設置電球内訳③ | Y1: 設置電球内訳③
A4: No. | B4: 1 | C4: 2 | D4: 3 | E4: 4 | F4: 5 | G4: 6 | H4: 7 | I4: 8 | J4: 9 | K4: 10 | L4: 11 | M4: 12 | N4: 13 | O4: 14 | P4: 15 | Q4: 16 | R4: 17 | S4: 18 | T4: 19 | U4: 20 | V4: 21 | W4: 22 | X4: 23 | Y4: 24 | Z4: 25 | AA4: 26 | AB4: 27 | AC4: 28 | AD4: 29 | AE4: 30
A5: 物件名 | B5: =☆入力!$B$16 | C5: =☆入力!$B$17 | D5: =☆入力!$B$18 | E5: =☆入力!$B$19 | F5: =☆入力!$B$20 | G5: =☆入力!$B$21 | H5: =☆入力!$B$22 | I5: =☆入力!$B$23 | J5: =☆入力!$B$24 | K5: =☆入力!$B$25 | L5: =☆入力!$B$26 | M5: =☆入力!$B$27 | N5: =☆入力!$B$28 | O5: =☆入力!$B$29 | P5: =☆入力!$B$30 | Q5: =☆入力!$B$31 | R5: =☆入力!$B$32 | S5: =☆入力!$B$33 | T5: =☆入力!$B$34 | U5: =☆入力!$B$35 | V5: =☆入力!$B$36 | W5: =☆入力!$B$37 | X5: =☆入力!$B$38 | Y5: =☆入力!$B$39 | Z5: =☆入力!$B$40 | AA5: =☆入力!$B$41 | AB5: =☆入力!$B$42 | AC5: =☆入力!$B$43 | AD5: =☆入力!$B$44 | AE5: =☆入力!$B$45
A6: 設置場所 | B6: =☆入力!$C$16 -> 0 | C6: =☆入力!$C$17 -> 0 | D6: =☆入力!$C$18 -> 0 | E6: =☆入力!$C$19 -> 0 | F6: =☆入力!$C$20 -> 0 | G6: =☆入力!$C$21 -> 0 | H6: =☆入力!$C$22 -> 0 | I6: =☆入力!$C$23 -> 0 | J6: =☆入力!$C$24 -> 0 | K6: =☆入力!$C$25 -> 0 | L6: =☆入力!$C$26 -> 0 | M6: =☆入力!$C$27 -> 0 | N6: =☆入力!$C$28 -> 0 | O6: =☆入力!$C$29 -> 0 | P6: =☆入力!$C$30 -> 0 | Q6: =☆入力!$C$31 -> 0 | R6: =☆入力!$C$32 -> 0 | S6: =☆入力!$C$33 -> 0 | T6: =☆入力!$C$34 -> 0 | U6: =☆入力!$C$35 -> 0 | V6: =☆入力!$C$36 -> 0 | W6: =☆入力!$C$37 -> 0 | X6: =☆入力!$C$38 -> 0 | Y6: =☆入力!$C$39 -> 0 | Z6: =☆入力!$C$40 -> 0 | AA6: =☆入力!$C$41 -> 0 | AB6: =☆入力!$C$42 -> 0 | AC6: =☆入力!$C$43 -> 0 | AD6: =☆入力!$C$44 -> 0 | AE6: =☆入力!$C$45 -> 0
A7: 既存照明写真 | B7: photo | C7: photo | D7: photo | E7: photo | F7: photo | G7: photo | H7: photo | I7: photo | J7: photo | K7: photo | L7: photo | M7: photo | N7: photo | O7: photo | P7: photo | Q7: photo | R7: photo | S7: photo | T7: photo | U7: photo | V7: photo | W7: photo | X7: photo | Y7: photo | Z7: photo | AA7: photo | AB7: photo | AC7: photo | AD7: photo | AE7: photo
A8: 設置数 | B8: =☆入力!$L$16 -> 0 | C8: =☆入力!$L$17 -> 0 | D8: =☆入力!$L$18 -> 0 | E8: =☆入力!$L$19 -> 0 | F8: =☆入力!$L$20 -> 0 | G8: =☆入力!$L$21 -> 0 | H8: =☆入力!$L$22 -> 0 | I8: =☆入力!$L$23 -> 0 | J8: =☆入力!$L$24 -> 0 | K8: =☆入力!$L$25 -> 0 | L8: =☆入力!$L$26 -> 0 | M8: =☆入力!$L$27 -> 0 | N8: =☆入力!$L$28 -> 0 | O8: =☆入力!$L$29 -> 0 | P8: =☆入力!$L$30 -> 0 | Q8: =☆入力!$L$31 -> 0 | R8: =☆入力!$L$32 -> 0 | S8: =☆入力!$L$33 -> 0 | T8: =☆入力!$L$34 -> 0 | U8: =☆入力!$L$35 -> 0 | V8: =☆入力!$L$36 -> 0 | W8: =☆入力!$L$37 -> 0 | X8: =☆入力!$L$38 -> 0 | Y8: =☆入力!$L$39 -> 0 | Z8: =☆入力!$L$40 -> 0 | AA8: =☆入力!$L$41 -> 0 | AB8: =☆入力!$L$42 -> 0 | AC8: =☆入力!$L$43 -> 0 | AD8: =☆入力!$L$44 -> 0 | AE8: =☆入力!$L$45 -> 0
A9: 点灯時間 | B9: =☆入力!$H$16 -> 0 | C9: =☆入力!$H$17 -> 0 | D9: =☆入力!$H$18 -> 0 | E9: =☆入力!$H$19 -> 0 | F9: =☆入力!$H$20 -> 0 | G9: =☆入力!$H$21 -> 0 | H9: =☆入力!$H$22 -> 0 | I9: =☆入力!$H$23 -> 0 | J9: =☆入力!$H$24 -> 0 | K9: =☆入力!$H$25 -> 0 | L9: =☆入力!$H$26 -> 0 | M9: =☆入力!$H$27 -> 0 | N9: =☆入力!$H$28 -> 0 | O9: =☆入力!$H$29 -> 0 | P9: =☆入力!$H$30 -> 0 | Q9: =☆入力!$H$31 -> 0 | R9: =☆入力!$H$32 -> 0 | S9: =☆入力!$H$33 -> 0 | T9: =☆入力!$H$34 -> 0 | U9: =☆入力!$H$35 -> 0 | V9: =☆入力!$H$36 -> 0 | W9: =☆入力!$H$37 -> 0 | X9: =☆入力!$H$38 -> 0 | Y9: =☆入力!$H$39 -> 0 | Z9: =☆入力!$H$40 -> 0 | AA9: =☆入力!$H$41 -> 0 | AB9: =☆入力!$H$42 -> 0 | AC9: =☆入力!$H$43 -> 0 | AD9: =☆入力!$H$44 -> 0 | AE9: =☆入力!$H$45 -> 0
A10: 既存照明種別 | B10: =☆入力!$D$16 -> 0 | C10: =☆入力!$D$17 -> 0 | D10: =☆入力!$D$18 -> 0 | E10: =☆入力!$D$19 -> 0 | F10: =☆入力!$D$20 -> 0 | G10: =☆入力!$D$21 -> 0 | H10: =☆入力!$D$22 -> 0 | I10: =☆入力!$D$23 -> 0 | J10: =☆入力!$D$24 -> 0 | K10: =☆入力!$D$25 -> 0 | L10: =☆入力!$D$26 -> 0 | M10: =☆入力!$D$27 -> 0 | N10: =☆入力!$D$28 -> 0 | O10: =☆入力!$D$29 -> 0 | P10: =☆入力!$D$30 -> 0 | Q10: =☆入力!$D$31 -> 0 | R10: =☆入力!$D$32 -> 0 | S10: =☆入力!$D$33 -> 0 | T10: =☆入力!$D$34 -> 0 | U10: =☆入力!$D$35 -> 0 | V10: =☆入力!$D$36 -> 0 | W10: =☆入力!$D$37 -> 0 | X10: =☆入力!$D$38 -> 0 | Y10: =☆入力!$D$39 -> 0 | Z10: =☆入力!$D$40 -> 0 | AA10: =☆入力!$D$41 -> 0 | AB10: =☆入力!$D$42 -> 0 | AC10: =☆入力!$D$43 -> 0 | AD10: =☆入力!$D$44 -> 0 | AE10: =☆入力!$D$45 -> 0
B11: ↓ | C11: ↓ | D11: ↓ | E11: ↓ | F11: ↓ | G11: ↓ | H11: ↓ | I11: ↓ | J11: ↓ | K11: ↓ | L11: ↓ | M11: ↓ | N11: ↓ | O11: ↓ | P11: ↓ | Q11: ↓ | R11: ↓ | S11: ↓ | T11: ↓ | U11: ↓ | V11: ↓ | W11: ↓ | X11: ↓ | Y11: ↓ | Z11: ↓ | AA11: ↓ | AB11: ↓ | AC11: ↓ | AD11: ↓ | AE11: ↓
A12: LED照明種別 | B12: =☆入力!$G$16 -> 0 | C12: =☆入力!$G$17 -> 0 | D12: =☆入力!$G$18 -> 0 | E12: =☆入力!$G$19 -> 0 | F12: =☆入力!$G$20 -> 0 | G12: =☆入力!$G$21 -> 0 | H12: =☆入力!$G$22 -> 0 | I12: =☆入力!$G$23 -> 0 | J12: =☆入力!$G$24 -> 0 | K12: =☆入力!$G$25 -> 0 | L12: =☆入力!$G$26 -> 0 | M12: =☆入力!$G$27 -> 0 | N12: =☆入力!$G$28 -> 0 | O12: =☆入力!$G$29 -> 0 | P12: =☆入力!$G$30 -> 0 | Q12: =☆入力!$G$31 -> 0 | R12: =☆入力!$G$32 -> 0 | S12: =☆入力!$G$33 -> 0 | T12: =☆入力!$G$34 -> 0 | U12: =☆入力!$G$35 -> 0 | V12: =☆入力!$G$36 -> 0 | W12: =☆入力!$G$37 -> 0 | X12: =☆入力!$G$38 -> 0 | Y12: =☆入力!$G$39 -> 0 | Z12: =☆入力!$G$40 -> 0 | AA12: =☆入力!$G$41 -> 0 | AB12: =☆入力!$G$42 -> 0 | AC12: =☆入力!$G$43 -> 0 | AD12: =☆入力!$G$44 -> 0 | AE12: =☆入力!$G$45 -> 0
A13: 交換種別 | B13: =IFERROR(VLOOKUP(B$12,選定!$C$3:$AG$100,31,FALSE),"") | C13: =IFERROR(VLOOKUP(C$12,選定!$C$3:$AG$100,31,FALSE),"") | D13: =IFERROR(VLOOKUP(D$12,選定!$C$3:$AG$100,31,FALSE),"") | E13: =IFERROR(VLOOKUP(E$12,選定!$C$3:$AG$100,31,FALSE),"") | F13: =IFERROR(VLOOKUP(F$12,選定!$C$3:$AG$100,31,FALSE),"") | G13: =IFERROR(VLOOKUP(G$12,選定!$C$3:$AG$100,31,FALSE),"") | H13: =IFERROR(VLOOKUP(H$12,選定!$C$3:$AG$100,31,FALSE),"") | I13: =IFERROR(VLOOKUP(I$12,選定!$C$3:$AG$100,31,FALSE),"") | ... AE13: =IFERROR(VLOOKUP(AE$12,選定!$C$3:$AG$100,31,FALSE),"")
A14: LED設置 予定照明 | B14: photo | C14: photo | D14: photo | E14: photo | F14: photo | G14: photo | H14: photo | I14: photo | J14: photo | K14: photo | L14: photo | M14: photo | N14: photo | O14: photo | P14: photo | Q14: photo | R14: photo | S14: photo | T14: photo | U14: photo | V14: photo | W14: photo | X14: photo | Y14: photo | Z14: photo | AA14: photo | AB14: photo | AC14: photo | AD14: photo | AE14: photo
A15: 選定照明色 | B15: =IFERROR(VLOOKUP(B$12,選定!$C$3:$AG$100,2,FALSE),"") | C15: =IFERROR(VLOOKUP(C$12,選定!$C$3:$AG$100,2,FALSE),"") | D15: =IFERROR(VLOOKUP(D$12,選定!$C$3:$AG$100,2,FALSE),"") | E15: =IFERROR(VLOOKUP(E$12,選定!$C$3:$AG$100,2,FALSE),"") | F15: =IFERROR(VLOOKUP(F$12,選定!$C$3:$AG$100,2,FALSE),"") | G15: =IFERROR(VLOOKUP(G$12,選定!$C$3:$AG$100,2,FALSE),"") | H15: =IFERROR(VLOOKUP(H$12,選定!$C$3:$AG$100,2,FALSE),"") | I15: =IFERROR(VLOOKUP(I$12,選定!$C$3:$AG$100,2,FALSE),"") | ... AE15: =IFERROR(VLOOKUP(AE$12,選定!$C$3:$AG$100,2,FALSE),"")
A16: 選定器具色 | B16: =IFERROR(VLOOKUP(B$12,選定!$C$3:$AG$100,3,FALSE),"") | C16: =IFERROR(VLOOKUP(C$12,選定!$C$3:$AG$100,3,FALSE),"") | D16: =IFERROR(VLOOKUP(D$12,選定!$C$3:$AG$100,3,FALSE),"") | E16: =IFERROR(VLOOKUP(E$12,選定!$C$3:$AG$100,3,FALSE),"") | F16: =IFERROR(VLOOKUP(F$12,選定!$C$3:$AG$100,3,FALSE),"") | G16: =IFERROR(VLOOKUP(G$12,選定!$C$3:$AG$100,3,FALSE),"") | H16: =IFERROR(VLOOKUP(H$12,選定!$C$3:$AG$100,3,FALSE),"") | I16: =IFERROR(VLOOKUP(I$12,選定!$C$3:$AG$100,3,FALSE),"") | ... AE16: =IFERROR(VLOOKUP(AE$12,選定!$C$3:$AG$100,3,FALSE),"")
A17: 器具ｻｲｽﾞ(設置面) | B17: =IFERROR(VLOOKUP(B$12,選定!$C$3:$AG$100,4,FALSE),"") | C17: =IFERROR(VLOOKUP(C$12,選定!$C$3:$AG$100,4,FALSE),"") | D17: =IFERROR(VLOOKUP(D$12,選定!$C$3:$AG$100,4,FALSE),"") | E17: =IFERROR(VLOOKUP(E$12,選定!$C$3:$AG$100,4,FALSE),"") | F17: =IFERROR(VLOOKUP(F$12,選定!$C$3:$AG$100,4,FALSE),"") | G17: =IFERROR(VLOOKUP(G$12,選定!$C$3:$AG$100,4,FALSE),"") | H17: =IFERROR(VLOOKUP(H$12,選定!$C$3:$AG$100,4,FALSE),"") | I17: =IFERROR(VLOOKUP(I$12,選定!$C$3:$AG$100,4,FALSE),"") | ... AE17: =IFERROR(VLOOKUP(AE$12,選定!$C$3:$AG$100,4,FALSE),"")
A18: 消費 電力 | B18: =IFERROR(VLOOKUP(B$12,選定!$C$3:$AG$100,5,FALSE),"") | C18: =IFERROR(VLOOKUP(C$12,選定!$C$3:$AG$100,5,FALSE),"") | D18: =IFERROR(VLOOKUP(D$12,選定!$C$3:$AG$100,5,FALSE),"") | E18: =IFERROR(VLOOKUP(E$12,選定!$C$3:$AG$100,5,FALSE),"") | F18: =IFERROR(VLOOKUP(F$12,選定!$C$3:$AG$100,5,FALSE),"") | G18: =IFERROR(VLOOKUP(G$12,選定!$C$3:$AG$100,5,FALSE),"") | H18: =IFERROR(VLOOKUP(H$12,選定!$C$3:$AG$100,5,FALSE),"") | I18: =IFERROR(VLOOKUP(I$12,選定!$C$3:$AG$100,5,FALSE),"") | ... AE18: =IFERROR(VLOOKUP(AE$12,選定!$C$3:$AG$100,5,FALSE),"")
A19: 全光束 | B19: =IFERROR(VLOOKUP(B$12,選定!$C$3:$AG$100,6,FALSE),"") | C19: =IFERROR(VLOOKUP(C$12,選定!$C$3:$AG$100,6,FALSE),"") | D19: =IFERROR(VLOOKUP(D$12,選定!$C$3:$AG$100,6,FALSE),"") | E19: =IFERROR(VLOOKUP(E$12,選定!$C$3:$AG$100,6,FALSE),"") | F19: =IFERROR(VLOOKUP(F$12,選定!$C$3:$AG$100,6,FALSE),"") | G19: =IFERROR(VLOOKUP(G$12,選定!$C$3:$AG$100,6,FALSE),"") | H19: =IFERROR(VLOOKUP(H$12,選定!$C$3:$AG$100,6,FALSE),"") | I19: =IFERROR(VLOOKUP(I$12,選定!$C$3:$AG$100,6,FALSE),"") | ... AE19: =IFERROR(VLOOKUP(AE$12,選定!$C$3:$AG$100,6,FALSE),"")
A20: 合算 定価 | B20: =IFERROR(VLOOKUP(B$12,選定!$C$3:$AG$100,7,FALSE),"") | C20: =IFERROR(VLOOKUP(C$12,選定!$C$3:$AG$100,7,FALSE),"") | D20: =IFERROR(VLOOKUP(D$12,選定!$C$3:$AG$100,7,FALSE),"") | E20: =IFERROR(VLOOKUP(E$12,選定!$C$3:$AG$100,7,FALSE),"") | F20: =IFERROR(VLOOKUP(F$12,選定!$C$3:$AG$100,7,FALSE),"") | G20: =IFERROR(VLOOKUP(G$12,選定!$C$3:$AG$100,7,FALSE),"") | H20: =IFERROR(VLOOKUP(H$12,選定!$C$3:$AG$100,7,FALSE),"") | I20: =IFERROR(VLOOKUP(I$12,選定!$C$3:$AG$100,7,FALSE),"") | ... AE20: =IFERROR(VLOOKUP(AE$12,選定!$C$3:$AG$100,7,FALSE),"")
A22: 防滴 | B22: =IFERROR(VLOOKUP(B$12,選定!$C$3:$AG$100,9,FALSE),"") | C22: =IFERROR(VLOOKUP(C$12,選定!$C$3:$AG$100,9,FALSE),"") | D22: =IFERROR(VLOOKUP(D$12,選定!$C$3:$AG$100,9,FALSE),"") | E22: =IFERROR(VLOOKUP(E$12,選定!$C$3:$AG$100,9,FALSE),"") | F22: =IFERROR(VLOOKUP(F$12,選定!$C$3:$AG$100,9,FALSE),"") | G22: =IFERROR(VLOOKUP(G$12,選定!$C$3:$AG$100,9,FALSE),"") | H22: =IFERROR(VLOOKUP(H$12,選定!$C$3:$AG$100,9,FALSE),"") | I22: =IFERROR(VLOOKUP(I$12,選定!$C$3:$AG$100,9,FALSE),"") | ... AE22: =IFERROR(VLOOKUP(AE$12,選定!$C$3:$AG$100,9,FALSE),"")
A23: 電球種別 | B23: =IFERROR(VLOOKUP(B$12,選定!$C$3:$AG$100,10,FALSE),"") | C23: =IFERROR(VLOOKUP(C$12,選定!$C$3:$AG$100,10,FALSE),"") | D23: =IFERROR(VLOOKUP(D$12,選定!$C$3:$AG$100,10,FALSE),"") | E23: =IFERROR(VLOOKUP(E$12,選定!$C$3:$AG$100,10,FALSE),"") | F23: =IFERROR(VLOOKUP(F$12,選定!$C$3:$AG$100,10,FALSE),"") | G23: =IFERROR(VLOOKUP(G$12,選定!$C$3:$AG$100,10,FALSE),"") | H23: =IFERROR(VLOOKUP(H$12,選定!$C$3:$AG$100,10,FALSE),"") | I23: =IFERROR(VLOOKUP(I$12,選定!$C$3:$AG$100,10,FALSE),"") | ... AE23: =IFERROR(VLOOKUP(AE$12,選定!$C$3:$AG$100,10,FALSE),"")
A24: メーカー | B24: =IFERROR(VLOOKUP(B$12,選定!$C$3:$AG$100,11,FALSE),"") | C24: =IFERROR(VLOOKUP(C$12,選定!$C$3:$AG$100,11,FALSE),"") | D24: =IFERROR(VLOOKUP(D$12,選定!$C$3:$AG$100,11,FALSE),"") | E24: =IFERROR(VLOOKUP(E$12,選定!$C$3:$AG$100,11,FALSE),"") | F24: =IFERROR(VLOOKUP(F$12,選定!$C$3:$AG$100,11,FALSE),"") | G24: =IFERROR(VLOOKUP(G$12,選定!$C$3:$AG$100,11,FALSE),"") | H24: =IFERROR(VLOOKUP(H$12,選定!$C$3:$AG$100,11,FALSE),"") | I24: =IFERROR(VLOOKUP(I$12,選定!$C$3:$AG$100,11,FALSE),"") | ... AE24: =IFERROR(VLOOKUP(AE$12,選定!$C$3:$AG$100,11,FALSE),"")
A25: W相当 | B25: =IFERROR(VLOOKUP(B$12,選定!$C$3:$AG$100,12,FALSE),"") | C25: =IFERROR(VLOOKUP(C$12,選定!$C$3:$AG$100,12,FALSE),"") | D25: =IFERROR(VLOOKUP(D$12,選定!$C$3:$AG$100,12,FALSE),"") | E25: =IFERROR(VLOOKUP(E$12,選定!$C$3:$AG$100,12,FALSE),"") | F25: =IFERROR(VLOOKUP(F$12,選定!$C$3:$AG$100,12,FALSE),"") | G25: =IFERROR(VLOOKUP(G$12,選定!$C$3:$AG$100,12,FALSE),"") | H25: =IFERROR(VLOOKUP(H$12,選定!$C$3:$AG$100,12,FALSE),"") | I25: =IFERROR(VLOOKUP(I$12,選定!$C$3:$AG$100,12,FALSE),"") | ... AE25: =IFERROR(VLOOKUP(AE$12,選定!$C$3:$AG$100,12,FALSE),"")
A26: 器具型番 | B26: =IFERROR(VLOOKUP(B$12,選定!$C$3:$AG$100,13,FALSE),"") | C26: =IFERROR(VLOOKUP(C$12,選定!$C$3:$AG$100,13,FALSE),"") | D26: =IFERROR(VLOOKUP(D$12,選定!$C$3:$AG$100,13,FALSE),"") | E26: =IFERROR(VLOOKUP(E$12,選定!$C$3:$AG$100,13,FALSE),"") | F26: =IFERROR(VLOOKUP(F$12,選定!$C$3:$AG$100,13,FALSE),"") | G26: =IFERROR(VLOOKUP(G$12,選定!$C$3:$AG$100,13,FALSE),"") | H26: =IFERROR(VLOOKUP(H$12,選定!$C$3:$AG$100,13,FALSE),"") | I26: =IFERROR(VLOOKUP(I$12,選定!$C$3:$AG$100,13,FALSE),"") | ... AE26: =IFERROR(VLOOKUP(AE$12,選定!$C$3:$AG$100,13,FALSE),"")
A27: 定価 | B27: =IFERROR(VLOOKUP(B$12,選定!$C$3:$AG$100,14,FALSE),"") | C27: =IFERROR(VLOOKUP(C$12,選定!$C$3:$AG$100,14,FALSE),"") | D27: =IFERROR(VLOOKUP(D$12,選定!$C$3:$AG$100,14,FALSE),"") | E27: =IFERROR(VLOOKUP(E$12,選定!$C$3:$AG$100,14,FALSE),"") | F27: =IFERROR(VLOOKUP(F$12,選定!$C$3:$AG$100,14,FALSE),"") | G27: =IFERROR(VLOOKUP(G$12,選定!$C$3:$AG$100,14,FALSE),"") | H27: =IFERROR(VLOOKUP(H$12,選定!$C$3:$AG$100,14,FALSE),"") | I27: =IFERROR(VLOOKUP(I$12,選定!$C$3:$AG$100,14,FALSE),"") | ... AE27: =IFERROR(VLOOKUP(AE$12,選定!$C$3:$AG$100,14,FALSE),"")
A29: 型番② | B29: =IFERROR(VLOOKUP(B$12,選定!$C$3:$AG$100,16,FALSE),"") | C29: =IFERROR(VLOOKUP(C$12,選定!$C$3:$AG$100,16,FALSE),"") | D29: =IFERROR(VLOOKUP(D$12,選定!$C$3:$AG$100,16,FALSE),"") | E29: =IFERROR(VLOOKUP(E$12,選定!$C$3:$AG$100,16,FALSE),"") | F29: =IFERROR(VLOOKUP(F$12,選定!$C$3:$AG$100,16,FALSE),"") | G29: =IFERROR(VLOOKUP(G$12,選定!$C$3:$AG$100,16,FALSE),"") | H29: =IFERROR(VLOOKUP(H$12,選定!$C$3:$AG$100,16,FALSE),"") | I29: =IFERROR(VLOOKUP(I$12,選定!$C$3:$AG$100,16,FALSE),"") | ... AE29: =IFERROR(VLOOKUP(AE$12,選定!$C$3:$AG$100,16,FALSE),"")
A30: 定価② | B30: =IFERROR(VLOOKUP(B$12,選定!$C$3:$AG$100,17,FALSE),"") | C30: =IFERROR(VLOOKUP(C$12,選定!$C$3:$AG$100,17,FALSE),"") | D30: =IFERROR(VLOOKUP(D$12,選定!$C$3:$AG$100,17,FALSE),"") | E30: =IFERROR(VLOOKUP(E$12,選定!$C$3:$AG$100,17,FALSE),"") | F30: =IFERROR(VLOOKUP(F$12,選定!$C$3:$AG$100,17,FALSE),"") | G30: =IFERROR(VLOOKUP(G$12,選定!$C$3:$AG$100,17,FALSE),"") | H30: =IFERROR(VLOOKUP(H$12,選定!$C$3:$AG$100,17,FALSE),"") | I30: =IFERROR(VLOOKUP(I$12,選定!$C$3:$AG$100,17,FALSE),"") | ... AE30: =IFERROR(VLOOKUP(AE$12,選定!$C$3:$AG$100,17,FALSE),"")
A32: 型番③ | B32: =IFERROR(VLOOKUP(B$12,選定!$C$3:$AG$100,19,FALSE),"") | C32: =IFERROR(VLOOKUP(C$12,選定!$C$3:$AG$100,19,FALSE),"") | D32: =IFERROR(VLOOKUP(D$12,選定!$C$3:$AG$100,19,FALSE),"") | E32: =IFERROR(VLOOKUP(E$12,選定!$C$3:$AG$100,19,FALSE),"") | F32: =IFERROR(VLOOKUP(F$12,選定!$C$3:$AG$100,19,FALSE),"") | G32: =IFERROR(VLOOKUP(G$12,選定!$C$3:$AG$100,19,FALSE),"") | H32: =IFERROR(VLOOKUP(H$12,選定!$C$3:$AG$100,19,FALSE),"") | I32: =IFERROR(VLOOKUP(I$12,選定!$C$3:$AG$100,19,FALSE),"") | ... AE32: =IFERROR(VLOOKUP(AE$12,選定!$C$3:$AG$100,19,FALSE),"")
A33: 定価③ | B33: =IFERROR(VLOOKUP(B$12,選定!$C$3:$AG$100,20,FALSE),"") | C33: =IFERROR(VLOOKUP(C$12,選定!$C$3:$AG$100,20,FALSE),"") | D33: =IFERROR(VLOOKUP(D$12,選定!$C$3:$AG$100,20,FALSE),"") | E33: =IFERROR(VLOOKUP(E$12,選定!$C$3:$AG$100,20,FALSE),"") | F33: =IFERROR(VLOOKUP(F$12,選定!$C$3:$AG$100,20,FALSE),"") | G33: =IFERROR(VLOOKUP(G$12,選定!$C$3:$AG$100,20,FALSE),"") | H33: =IFERROR(VLOOKUP(H$12,選定!$C$3:$AG$100,20,FALSE),"") | I33: =IFERROR(VLOOKUP(I$12,選定!$C$3:$AG$100,20,FALSE),"") | ... AE33: =IFERROR(VLOOKUP(AE$12,選定!$C$3:$AG$100,20,FALSE),"")
A35: 消費電力 | B35: =IFERROR(VLOOKUP(B$12,選定!$C$3:$AG$100,22,FALSE),"") | C35: =IFERROR(VLOOKUP(C$12,選定!$C$3:$AG$100,22,FALSE),"") | D35: =IFERROR(VLOOKUP(D$12,選定!$C$3:$AG$100,22,FALSE),"") | E35: =IFERROR(VLOOKUP(E$12,選定!$C$3:$AG$100,22,FALSE),"") | F35: =IFERROR(VLOOKUP(F$12,選定!$C$3:$AG$100,22,FALSE),"") | G35: =IFERROR(VLOOKUP(G$12,選定!$C$3:$AG$100,22,FALSE),"") | H35: =IFERROR(VLOOKUP(H$12,選定!$C$3:$AG$100,22,FALSE),"") | I35: =IFERROR(VLOOKUP(I$12,選定!$C$3:$AG$100,22,FALSE),"") | ... AE35: =IFERROR(VLOOKUP(AE$12,選定!$C$3:$AG$100,22,FALSE),"")
A36: 全光束 | B36: =IFERROR(VLOOKUP(B$12,選定!$C$3:$AG$100,23,FALSE),"") | C36: =IFERROR(VLOOKUP(C$12,選定!$C$3:$AG$100,23,FALSE),"") | D36: =IFERROR(VLOOKUP(D$12,選定!$C$3:$AG$100,23,FALSE),"") | E36: =IFERROR(VLOOKUP(E$12,選定!$C$3:$AG$100,23,FALSE),"") | F36: =IFERROR(VLOOKUP(F$12,選定!$C$3:$AG$100,23,FALSE),"") | G36: =IFERROR(VLOOKUP(G$12,選定!$C$3:$AG$100,23,FALSE),"") | H36: =IFERROR(VLOOKUP(H$12,選定!$C$3:$AG$100,23,FALSE),"") | I36: =IFERROR(VLOOKUP(I$12,選定!$C$3:$AG$100,23,FALSE),"") | ... AE36: =IFERROR(VLOOKUP(AE$12,選定!$C$3:$AG$100,23,FALSE),"")
A37: 器具素材 | B37: =IFERROR(VLOOKUP(B$12,選定!$C$3:$AG$100,24,FALSE),"") | C37: =IFERROR(VLOOKUP(C$12,選定!$C$3:$AG$100,24,FALSE),"") | D37: =IFERROR(VLOOKUP(D$12,選定!$C$3:$AG$100,24,FALSE),"") | E37: =IFERROR(VLOOKUP(E$12,選定!$C$3:$AG$100,24,FALSE),"") | F37: =IFERROR(VLOOKUP(F$12,選定!$C$3:$AG$100,24,FALSE),"") | G37: =IFERROR(VLOOKUP(G$12,選定!$C$3:$AG$100,24,FALSE),"") | H37: =IFERROR(VLOOKUP(H$12,選定!$C$3:$AG$100,24,FALSE),"") | I37: =IFERROR(VLOOKUP(I$12,選定!$C$3:$AG$100,24,FALSE),"") | ... AE37: =IFERROR(VLOOKUP(AE$12,選定!$C$3:$AG$100,24,FALSE),"")
A38: 器具色 選択肢 | B38: =IFERROR(VLOOKUP(B$12,選定!$C$3:$AG$100,27,FALSE),"") | C38: =IFERROR(VLOOKUP(C$12,選定!$C$3:$AG$100,27,FALSE),"") | D38: =IFERROR(VLOOKUP(D$12,選定!$C$3:$AG$100,27,FALSE),"") | E38: =IFERROR(VLOOKUP(E$12,選定!$C$3:$AG$100,27,FALSE),"") | F38: =IFERROR(VLOOKUP(F$12,選定!$C$3:$AG$100,27,FALSE),"") | G38: =IFERROR(VLOOKUP(G$12,選定!$C$3:$AG$100,27,FALSE),"") | H38: =IFERROR(VLOOKUP(H$12,選定!$C$3:$AG$100,27,FALSE),"") | I38: =IFERROR(VLOOKUP(I$12,選定!$C$3:$AG$100,27,FALSE),"") | ... AE38: =IFERROR(VLOOKUP(AE$12,選定!$C$3:$AG$100,27,FALSE),"")
A39: 照明色 選択肢 | B39: =IFERROR(VLOOKUP(B$12,選定!$C$3:$AG$100,28,FALSE),"") | C39: =IFERROR(VLOOKUP(C$12,選定!$C$3:$AG$100,28,FALSE),"") | D39: =IFERROR(VLOOKUP(D$12,選定!$C$3:$AG$100,28,FALSE),"") | E39: =IFERROR(VLOOKUP(E$12,選定!$C$3:$AG$100,28,FALSE),"") | F39: =IFERROR(VLOOKUP(F$12,選定!$C$3:$AG$100,28,FALSE),"") | G39: =IFERROR(VLOOKUP(G$12,選定!$C$3:$AG$100,28,FALSE),"") | H39: =IFERROR(VLOOKUP(H$12,選定!$C$3:$AG$100,28,FALSE),"") | I39: =IFERROR(VLOOKUP(I$12,選定!$C$3:$AG$100,28,FALSE),"") | ... AE39: =IFERROR(VLOOKUP(AE$12,選定!$C$3:$AG$100,28,FALSE),"")
A40: 定格 寿命 | B40: =IFERROR(VLOOKUP(B$12,選定!$C$3:$AG$100,27,FALSE),"") | C40: =IFERROR(VLOOKUP(C$12,選定!$C$3:$AG$100,27,FALSE),"") | D40: =IFERROR(VLOOKUP(D$12,選定!$C$3:$AG$100,27,FALSE),"") | E40: =IFERROR(VLOOKUP(E$12,選定!$C$3:$AG$100,27,FALSE),"") | F40: =IFERROR(VLOOKUP(F$12,選定!$C$3:$AG$100,27,FALSE),"") | G40: =IFERROR(VLOOKUP(G$12,選定!$C$3:$AG$100,27,FALSE),"") | H40: =IFERROR(VLOOKUP(H$12,選定!$C$3:$AG$100,27,FALSE),"") | I40: =IFERROR(VLOOKUP(I$12,選定!$C$3:$AG$100,27,FALSE),"") | ... AE40: =IFERROR(VLOOKUP(AE$12,選定!$C$3:$AG$100,27,FALSE),"")
A41: 交換 方法 | B41: =IFERROR(VLOOKUP(B$12,選定!$C$3:$AG$100,28,FALSE),"") | C41: =IFERROR(VLOOKUP(C$12,選定!$C$3:$AG$100,28,FALSE),"") | D41: =IFERROR(VLOOKUP(D$12,選定!$C$3:$AG$100,28,FALSE),"") | E41: =IFERROR(VLOOKUP(E$12,選定!$C$3:$AG$100,28,FALSE),"") | F41: =IFERROR(VLOOKUP(F$12,選定!$C$3:$AG$100,28,FALSE),"") | G41: =IFERROR(VLOOKUP(G$12,選定!$C$3:$AG$100,28,FALSE),"") | H41: =IFERROR(VLOOKUP(H$12,選定!$C$3:$AG$100,28,FALSE),"") | I41: =IFERROR(VLOOKUP(I$12,選定!$C$3:$AG$100,28,FALSE),"") | ... AE41: =IFERROR(VLOOKUP(AE$12,選定!$C$3:$AG$100,28,FALSE),"")
A42: 備考
H45: 10 | P45: 9-b | X45: 9-c | AE45: 9-d
A46: 選定の 引継ぎ 事項
B52: 非常灯●カ所あり | C52: 既存器具●●mm | E52: LED交換済み箇所
B53: 削減が出ない為除外 | C53: 器具ｻｲｽﾞが小さくなる
B54: 交換の場合:13,500円/個 | C54: のでご注意ください
A80: 照明色 | B80: 器具色 | C80: 器具サイズ （設置面） | D80: 消費 電力 | E80: 全光束 | F80: 合算 定価 | G80: 合算 仕入 | H80: 防滴 | I80: 電球種別 | J80: メーカー | K80: W相当 | L80: 器具型番 | M80: 定価 | N80: 仕入れ | O80: 型番② | P80: 定価② | Q80: 仕入② | R80: 型番③ | S80: 定価③ | T80: 仕入③ | U80: 消費電力 | V80: 全光束 | W80: 器具素材 | X80: 器具色 選択肢 | Y80: 照明色 選択肢 | Z80: 定格 寿命 | AA80: 交換 方法 | AB80: 口金

Sheet ⑪除外
A1: 見積り除外箇所
A4: 1 | B4: photo | C4: 対象物件 | D4: =☆入力!B49 | E4: 試算エリア | F4: =☆入力!C49 -> 0 | H4: 7 | I4: photo | J4: 対象物件 | K4: =☆入力!B55 | L4: 試算エリア | M4: =☆入力!C55 -> 0
C5: 照明種別 | D5: =☆入力!D49 -> 0 | E5: 数量 | F5: =☆入力!L49 -> 0 | J5: 照明種別 | K5: =☆入力!D55 -> 0 | L5: 数量 | M5: =☆入力!L55 -> 0
C6: 除外理由 | D6: =☆入力!W49 -> 0 | J6: 除外理由 | K6: =☆入力!W55 -> 0
C7: アドバイス | D7: =☆入力!AC49 -> 0 | J7: アドバイス | K7: =☆入力!AC55 -> 0
A8: 2 | B8: photo | C8: 対象物件 | D8: =☆入力!B50 | E8: 試算エリア | F8: =☆入力!C50 -> 0 | H8: 8 | I8: photo | J8: 対象物件 | K8: =☆入力!B56 | L8: 試算エリア | M8: =☆入力!C56 -> 0
C9: 照明種別 | D9: =☆入力!D50 -> 0 | E9: 数量 | F9: =☆入力!L50 -> 0 | J9: 照明種別 | K9: =☆入力!D56 -> 0 | L9: 数量 | M9: =☆入力!L56 -> 0
C10: 除外理由 | D10: =☆入力!W50 -> 0 | J10: 除外理由 | K10: =☆入力!W56 -> 0
C11: アドバイス | D11: =☆入力!AC50 -> 0 | J11: アドバイス | K11: =☆入力!AC56 -> 0
A12: 3 | B12: photo | C12: 対象物件 | D12: =☆入力!B51 | E12: 試算エリア | F12: =☆入力!C51 -> 0 | H12: 9 | I12: photo | J12: 対象物件 | K12: =☆入力!B57 | L12: 試算エリア | M12: =☆入力!C57 -> 0
C13: 照明種別 | D13: =☆入力!D51 -> 0 | E13: 数量 | F13: =☆入力!L51 -> 0 | J13: 照明種別 | K13: =☆入力!D57 -> 0 | L13: 数量 | M13: =☆入力!L57 -> 0
C14: 除外理由 | D14: =☆入力!W51 -> 0 | J14: 除外理由 | K14: =☆入力!W57 -> 0
C15: アドバイス | D15: =☆入力!AC51 -> 0 | J15: アドバイス | K15: =☆入力!AC57 -> 0
A16: 4 | B16: photo | C16: 対象物件 | D16: =☆入力!B52 | E16: 試算エリア | F16: =☆入力!C52 -> 0 | H16: 10 | I16: photo | J16: 対象物件 | K16: =☆入力!B58 | L16: 試算エリア | M16: =☆入力!C58 -> 0
C17: 照明種別 | D17: =☆入力!D52 -> 0 | E17: 数量 | F17: =☆入力!L52 -> 0 | J17: 照明種別 | K17: =☆入力!D58 -> 0 | L17: 数量 | M17: =☆入力!L58 -> 0
C18: 除外理由 | D18: =☆入力!W52 -> 0 | J18: 除外理由 | K18: =☆入力!W58 -> 0
C19: アドバイス | D19: =☆入力!AC52 -> 0 | J19: アドバイス | K19: =☆入力!AC58 -> 0
A20: 5 | B20: photo | C20: 対象物件 | D20: =☆入力!B53 | E20: 試算エリア | F20: =☆入力!C53 -> 0 | H20: 11 | I20: photo | J20: 対象物件 | K20: =☆入力!B59 | L20: 試算エリア | M20: =☆入力!C59 -> 0
C21: 照明種別 | D21: =☆入力!D53 -> 0 | E21: 数量 | F21: =☆入力!L53 -> 0 | J21: 照明種別 | K21: =☆入力!D59 -> 0 | L21: 数量 | M21: =☆入力!L59 -> 0
C22: 除外理由 | D22: =☆入力!W53 -> 0 | J22: 除外理由 | K22: =☆入力!W59 -> 0
C23: アドバイス | D23: =☆入力!AC53 -> 0 | J23: アドバイス | K23: =☆入力!AC59 -> 0
A24: 6 | B24: photo | C24: 対象物件 | D24: =☆入力!B54 | E24: 試算エリア | F24: =☆入力!C54 -> 0 | H24: 12 | I24: photo | J24: 対象物件 | K24: =☆入力!B60 | L24: 試算エリア | M24: =☆入力!C60 -> 0
C25: 照明種別 | D25: =☆入力!D54 -> 0 | E25: 数量 | F25: =☆入力!L54 -> 0 | J25: 照明種別 | K25: =☆入力!D60 -> 0 | L25: 数量 | M25: =☆入力!L60 -> 0
C26: 除外理由 | D26: =☆入力!W54 -> 0 | J26: 除外理由 | K26: =☆入力!W60 -> 0
C27: アドバイス | D27: =☆入力!AC54 -> 0 | J27: アドバイス | K27: =☆入力!AC60 -> 0
M28: 11
A29: ◆ 非常用専用照明に関して
B31: 弊社のご提案では、コストメリットを出して利回りを良くすることを重視して作成しておりますので、非常用専用照明（非常時にか点灯しない照明）は基本的に見積から除外をしております。
B32: ただ、非常用専用照明も消防法上定期的なバッテリー交換が必要で、各メーカーLEDに切り替えがなされておりますので次回交換時にはLED化が必須となります。
B33: 交換をする場合には別途、御見積を致しますのでお申しつけください。
M34: 10

Sheet 代理店入力用
H2: ※※ | J2: の部分の入力をお願い致します。
B3: 卸値： | D3: =☆入力!AL14*(100%-☆入力!AR11) -> 0 | M3: 会社名 | N3: 株式会社ニッショー
H4: 【リース期間】 | M4: 郵便番号
B5: 利益： | D5: 0 | E5: ←こちらに上乗せする利益を入力ください。 | H5: 10 | I5: ←3～10年でリース期間選択可能です | M5: 住所
M6: 電話番号 | N6: 管理担当営業所へお問い合わせ下さい。
M7: 担当 | N7: 物件担当者
B8: 電球交換費用： | D8: 0
B9: ※電球が切れた際のオーナー様へご請求している「1箇所あたりの交換費用」を入力お願い致します。
B12: 売価： | C12: =D3+D5 -> 0 | D12: 1箇所単価： | E12: =IFERROR(C12/☆入力!AH14,"0") -> 0 | F12: 回収期間： | G12: =☆入力!AN12 -> 0
B14: 備考
B24: シート内容
B25: ①表紙 | C25: 表紙です
B26: ②説明 | C26: LEDをいま検討しないといけない理由を説明するページです
B27: ③説明2 | C27: LED照明導入のメリットを説明するページです
B28: ④説明3 | C28: 照明の交換方法(器具交換を推奨する理由)を説明するページです
B29: ⑤前 | C29: 現地調査結果および従来の白熱球を使い続けた場合の１０年間で照明にかかるコスト全体
B30: ⑥後 | C30: 現地調査の結果からLED照明を導入した場合の１０年間で照明にかかるコスト全体
B31: ⑦前後 | C31: ②と③の導入前後の金額的な差異
B33: ⑦一式 | C33: 細かな詳細などの記載がないお見積り。詳細の見積でお値引きがプラスになってしまう場合はこちらを使用。
B34: ⑦見積書 | C34: 細かな詳細の記載のあるお見積書、回収期間の記載がない見積です
B35: ⑤複数 | C35: 複数棟同時にお見積りをした際の割引が適応された詳細がない物件毎の金額のみ表示をしたお見積り。２棟～４棟→５％OFF 5棟以上→10％ＯＦＦ
B36: ⑤複数＋詳細 | C36: 『⑤複数』と同様お値引きが入るお見積り。物件毎の金額がないので複数の場合は基本的に『⑤複数 ＆ ⑤複数＋詳細』両方利用がおすすめ。
C37: ※複数棟で新電力セット適応の場合は新電力セット適応物件のみ『⑤複数』の物件毎のお値段よりお値引きをいたします。
B38: ⑤小単体 | C38: リース代の月額最低額が税込3,000円の為、金額を上乗せしてもリース代が3,000円を下回る場合のみ利用してください。
B40: ⑨-シミュ | C40: 一括支払い時の投資回収イメージ、リース導入時の月々のCFイメージの説明ページです
B41: ⑧-bｼﾐｭ | C41: 削減シミュレーションのページです。電気代が8,000円以上の場合には電力契約も一緒に変えることでお得に導入が可能です。
B43: ⑦非なし | C43: ⑥とセットでつけていただく新電力セットの際のお値引き後の削減シミュレーションを表示したシートです。
B44: ⑦非あり | C44: 同上
B46: ⑨内訳 | C46: 照明のビフォーアフターです。
B47: ⑩除外 | C47: LED済みの照明、テナント部など除外している箇所の一覧です。

Sheet 発注書兼発注請書
A1: 発 注 書
M2: 発行日 | O2: =TODAY() -> 46080
A4: バズエリア株式会社 | J4: 御中
A7: 下記のとおり、御注文を致します。
A9: 物件名 | D9: =☆入力!C5 -> 0 | L9: =代理店入力用!N3 -> 株式会社ニッショー | S9: 個 | T9: 0.1
A10: 物件住所 | D10: =☆入力!C6 -> 0 | L10: =代理店入力用!N4 -> 0 | S10: 式
A11: 解錠方法 | D11: =☆入力!C7 -> 0 | L11: =代理店入力用!N5 -> 0 | S11: 時間
A12: その他 | L12: TEL： | N12: =代理店入力用!N6 -> 管理担当営業所へお問い合わせ下さい。 | S12: 日
S13: ヶ月
L14: 担当： | N14: =代理店入力用!N7 -> 物件担当者
A16: 合計金額 | D16: =O34 -> 0 | I16: （税込）
A19: No. | B19: 摘要 | J19: 数量 | L19: 単価 | O19: 金額
A20: 1 | B20: LED照明工事 | J20: 1 | K20: 式 | L20: =代理店入力用!D3 -> 0 | O20: =L20*J20 -> 0
L32: 小計 | O32: =SUM(O20:Q31) -> 0
L33: 消費税 | O33: =ROUNDDOWN(O32*0.1,0) -> 0
L34: 合計金額 | O34: =SUM(O32:Q33) -> 0
A35: 上記の内容にてご注文を受領致しました。
B37: バズエリア株式会社
B38: 〒151-0062 東京都渋谷区上原1-47-8 藤本ビル2階
B39: TEL:03-4586-6571 FAX:03-6812-9253
